Workbook

Sheet FICHE (2)
E4: STE NAP SARL
D7: PLOT NO 14 GLODJIGBE ECONIMIC ZONEREPUBLIC OF BENIN RCCM RB / COT / 21 B 30710, IFU 3202113334014 TEL: +229 0194940414, 0197974506
F11: Bon de paiement
D13: Date | E13: 46177 | G13: Prestataires/Fournisseurs | H13: HOUNKONSI FLORENT
D14: No de transaction | E14: CC0004-2026
D15: Type d'operation | E15: SERVICE | G15: Nom du bénéficiaire | H15: HOUNKONSI FLORENT
D16: Produit | E16: ENTRETIEN | G16: Num. Pieces d'identite | H16: 8505929556
G17: Date d'expiration | H17: 24/03/2031
G18: Addresse /Telephone | H18: 0196199915
D20: Details des operations
D21: Numero de facture | E21: Description/Objet du paiement | G21: Montant | H21: Observation
E22: NETTOYAGE BUREAU | G22: 20000 | H22: -
E23: NETTOYAGE TANK | G23: 3000 | H23: -
F24: Montant Total | G24: =SUM(G22:G23) -> 23000
D26: Montant en lettre : | E26: Vingt trois mille francs CFA
G29: Mode paiement | H29: ESPECES
G30: Numero de cheque | H30: -
G31: Banque | H31: CAISSE
D33: Manager logistics | F33: Comptablité | H33: Bénéficiaire
D37: visa | F37: visa | H37: visa
D38: NB: Toute remise de chèque doit être confirmée par signature du bénéficiaire et accompagnée d’une copie du chèque et pièce pour fins de traçabilité.

Sheet Mvt Caisse
D3: STE NAP SARL
D6: PLOT NO 14 GLODJIGBE ECONIMIC ZONEREPUBLIC OF BENIN RCCM RB / COT / 21 B 30710, IFU 3202113334014 TEL: +229 0194940414, 0197974506
E10: MOUVEMENT DE CAISSE
C13: DATE | D13: LIBELLE | E13: MOTIF | F13: DEBIT | G13: CREDIT | H13: SOLDE
D14: SOLDE INITIAL

Sheet DEPENSES
B3: Date | C3: No de transaction | D3: Type d'operation | E3: Produit | F3: Prestataires/Fournisseurs | G3: Nom du bénéficiaire | H3: Num. Pieces d'identite | I3: Date d'expiration | J3: Addresse /Telephone | K3: Ref doc | L3: Description/Objet du paiement | M3: Montant | N3: Observation | O3: Montant en lettre | P3: Mode paiement | Q3: Numero de cheque | R3: Banque
B4: 46175 | C4: CC-0001-2026 | D4: EXPORT | E4: FRET EXPORT | F4: ALFRED | G4: SOGLO MARTIAL | H4: 7506116519 | I4: 48001 | J4: 0197601003 | K4: BJCOOA260021857/ EBKG15552571 _MEDUCT182978 | L4: ACHAT BL-MANIPULATION-FRAIS SEGUB-TIMBRE-ACHAT PLOMB | M4: 49658 | N4: PAYE | O4: Quarante neuf mille six cent ciquante huit francs CFA | P4: ESPECES | Q4: - | R4: CAISSE
B5: 46175 | C5: CC-0001-2026 | D5: EXPORT | E5: FRET EXPORT | F5: ALFRED | G5: SOGLO MARTIAL | H5: 7506116519 | I5: 48001 | J5: 0197601003 | K5: BJCOOPX260001101/ EBKG15552571 _MEDUCT182978 | L5: INTERNATIONAL SHIPS AND PORT SECURITY (ISPS) | M5: 41300 | N5: PAYE | O5: Quarante un mille trois cents francs CFA | P5: ESPECES | Q5: - | R5: CAISSE
B6: 46175 | C6: CC-0001-2026 | D6: EXPORT | E6: FRET EXPORT | F6: ALFRED | G6: SOGLO MARTIAL | H6: 7506116519 | I6: 48001 | J6: 0197601003 | K6: BJCOOA260025613/ EBKG15552571 _MEDUCT182978 | L6: FRAIS DE RETARD BL | M6: 29500 | N6: PAYE | O6: Vingt neuf mille cinq cent franc CFA | P6: ESPECES | R6: CAISSE
B7: 46175 | C7: CC-0001-2026 | D7: EXPORT | E7: FRET EXPORT | F7: ALFRED | G7: SOGLO MARTIAL | H7: 7506116519 | I7: 48001 | J7: 0197601003 | K7: BJCOOA260030030/ EBKG15552571 _MEDUCT182978 | L7: LETTRE DE GARANTIE | M7: 17966 | N7: PAYE | O7: Dix sept mille soixante six francs CFA | P7: ESPECES | R7: CAISSE
B8: 46175 | C8: CC-0001-2026 | D8: EXPORT | E8: FRET EXPORT | F8: ALFRED | G8: SOGLO MARTIAL | H8: 7506116519 | I8: 48001 | J8: 0197601003 | K8: BJCOOA260030014/ EBKG15552571 _MEDUCT182978 | L8: COMMISION EXP CHARGES FOR EQUIPMENT | M8: 189768 | N8: PAYE | O8: Qatre vingt seize six cent quatre vingt deux francs CFA | P8: ESPECES | R8: CAISSE
B9: 46175 | C9: CC-0001-2026 | D9: EXPORT | E9: FRET EXPORT | F9: ALFRED | G9: SOGLO MARTIAL | H9: 7506116519 | I9: 48001 | J9: 0197601003 | K9: BJCOOA260030252/ EBKG15552571 _MEDUCT182978 | L9: FRAIS DE RETARD BL | M9: 70800 | N9: PAYE | O9: Soixante mille francs CFA | P9: ESPECES | R9: CAISSE
B10: 46175 | C10: CC-0001-2026 | D10: EXPORT | E10: FRET EXPORT | F10: ALFRED | G10: SOGLO MARTIAL | H10: 7506116519 | I10: 48001 | J10: 0197601003 | K10: BJCOOP260009286/ EBKG15552571 _MEDUCT182978 | L10: COMMISSION EXP CHARGES FOR EQUIPMENT | M10: 6325772 | N10: PAYE | O10: Six millions trois cent vingt cinq mille sept cent soixante douze francs CFA | P10: ESPECES | R10: CAISSE
B11: 46175 | C11: CC-0002-2026 | D11: PURCHASE | E11: SOYABEAN | F11: HOUEDANOU ENAGNON JUSTIN | G11: HOUEDANOU ENAGNON JUSTIN | H11: 2546545404 | I11: 28/2/2031 | J11: 0197684561 | K11: WEIGHMENT TICKET ATRAL : 6615 _ 39380 KG | L11: PURCHASE OF SOYABEAN | M11: 2000000 | N11: AVANCE | O11: Deux millions francs CFA | P11: ESPECES | R11: CAISSE
B12: 46175 | C12: CC-0003-2026 | D12: SERVICE | E12: TRANSFERT DHL | F12: DHL | G12: DHL | H12: - | I12: - | J12: benincustomerservice@dhl.com | K12: WAYBILL : 7171660414 | L12: TRANSFERT DE DOCUMENT PAR DHL (COO_267756955) | M12: 63902 | N12: PAYE | O12: Soixante trois mille neuf cents deux francs CFA | P12: MOBILE MONEY | Q12: - | R12: CAISSE
B13: 46177 | C13: CC0004-2026 | D13: SERVICE | E13: ENTRETIEN | F13: HOUNKONSI FLORENT | G13: HOUNKONSI FLORENT | H13: 8505929556 | I13: 24/03/2031 | J13: 0196199915 | L13: NETOYAGE BUREAU | M13: 20000 | N13: PAYE | O13: Vingt mille franc CFA | P13: ESPECES | R13: CAISSE
B14: 46177 | C14: CC0004-2026 | D14: SERVICE | E14: ENTRETIEN | F14: HOUNKONSI FLORENT | G14: HOUNKONSI FLORENT | H14: 8505929556 | I14: 24/03/2031 | J14: 0196199915 | L14: NETOYAGE TANK | M14: 3000 | N14: PAYE | O14: Trois mille franc CFA | P14: ESPECES | R14: CAISSE
B15: 46183 | C15: CC-0005-2026 | D15: EXPORT | E15: SERVICE TRANSIT | F15: TRANS SOHA | G15: TRANS SOHA | H15: - | I15: - | J15: - | K15: Facture Administrative 265000443 | L15: FACTURE POUR RETOUR VIDE DE 01 TC DE 20' TLLU2296161(22G1)//BOOKING 271486702 | M15: 46879 | N15: PAYE | O15: Qarante sux huit cents soixante dix neuf | P15: ESPECES | Q15: - | R15: CAISSE
B16: 46183 | C16: CC-0006-2026 | D16: SERVICE | E16: SALARY | F16: EMPLOYE USINE | G16: ADIGNON SYLVAIN | H16: 8188560503 | I16: 48094 | J16: 01 95 55 78 89 | K16: - | L16: SALARY AND LOCAL ALLOWANCE MAY 2026 | M16: 7592333 | N16: PAYE | O16: Sept millions neuf cents quatre vingt douze mille trois cents trente mille francs CFA | P16: ESPECES | Q16: - | R16: CAISSE
B17: 46189 | C17: CC-0007-2026 | D17: SERVICE | E17: SALARY | F17: HOUNVLESSI HOSPICE | G17: HOUNVLESSI HOSPICE | H17: 21PP35301 | I17: 21/11/2027 | L17: SALARY MAY 2026 | M17: 250000 | N17: PAYE | O17: Deux cent cinquante mille francs CFA | P17: ESPECES | R17: CAISSE
B18: 46195 | C18: CC-0008-2026 | D18: SERVICE | E18: TRANSFERT DHL | F18: DHL | G18: DHL | H18: - | I18: - | J18: benincustomerservice@dhl.com | K18: WAYBILL : 2489910581 | L18: TRANSFERT DE DOCUMENT PAR DHL | M18: 63902 | N18: PAYE | O18: Soixante trois mille neuf cents deux francs CFA | P18: MOBILE MONEY | Q18: - | R18: CAISSE
B19: 46197 | C19: CC-0009-2026 | D19: SERVICE | E19: TRANSFERT DHL | F19: DHL | G19: DHL | H19: - | I19: - | J19: benincustomerservice@dhl.com | K19: WAYBILL : 9550147524/9250148891/9250152796 | L19: TRANSFERT DE DOCUMENT PAR DHL | M19: 191706 | N19: PAYE | O19: Cent quatre vingt onze mille sept cent six francs CFA | P19: MOBILE MONEY | Q19: - | R19: CAISSE
B20: 46197 | C20: CC-0010-2026 | D20: EXPORT | E20: COQ/COW | F20: GLOHI GEOFRANE | G20: GLOHI GEOFRANE | H20: - | I20: - | J20: - | K20: - | L20: ETABLISSEMENT DE COQ & COW | M20: 500000 | N20: PAYE | O20: Cinq cent dix mille francs CFA | P20: ESPECES | Q20: - | R20: CAISSE
B21: 46198 | C21: CC-0011-2026 | D21: EXPORT | E21: COQ/COW | F21: GLOHI GEOFRANE | G21: GLOHI GEOFRANE | H21: - | I21: - | J21: - | K21: - | L21: ETABLISSEMENT DE COQ & COW | M21: 200000 | N21: PAYE | O21: Deux cent mille francs CFA | P21: ESPECES | Q21: - | R21: CAISSE
B22: 46198 | C22: CC-0012-2026 | D22: SERVICE | E22: SERVICE | F22: STE DE PAPETERIE MODERNE | G22: STE DE PAPETERIE MODERNE | H22: - | I22: - | J22: - | K22: - | L22: ACHAT DE FOURNITURE BUREAU | M22: 3227 | N22: PAYE | O22: Trois mille deux cent vingt sept francs CFA | P22: ESPECES | Q22: - | R22: CAISSE
B23: 46198 | C23: CC-0013-2026 | D23: SERVICE | E23: SERVICE | F23: MARILOG AFRICA | G23: MARILOG AFRICA | H23: - | I23: - | J23: - | K23: - | L23: VERIFICATION DE STOCK USINE DE GDIZ & SITE DE SEKOU | M23: 1500000 | N23: PAYE | O23: Un million cinq cent mille francs CFA | P23: VIREMENT | Q23: - | R23: ECOBANK BENIN
B24: 46198 | C24: CC-0014-2026 | D24: SERVICE | E24: SERVICE | F24: LA GRACE DE DIEU | G24: LA GRACE DE DIEU | H24: - | I24: - | J24: - | K24: - | L24: ESSENCE | M24: 20000 | N24: PAYE | O24: Vingt mille franc CFA | P24: ESPECES | Q24: - | R24: CAISSE
B25: 46198 | C25: CC-0015-2026 | D25: SERVICE | E25: SERVICE | F25: CERCLE DE DIEU | G25: CERCLE DE DIEU | H25: - | I25: - | J25: - | K25: - | L25: LABOUR WORK SOYA ACC | M25: 192904 | N25: PAYE | O25: Cent quatre vingt douze mille neuf cent quatre francs CFA | P25: ESPECES | Q25: - | R25: CAISSE
B26: 46175 | C26: CC-0016-2026 | D26: SERVICE | E26: TRANSFERT DHL | F26: DHL | G26: DHL | H26: - | I26: - | J26: benincustomerservice@dhl.com | K26: WAYBILL : 7018927156 | L26: TRANSFERT DE DOCUMENT PAR DHL | M26: 63902 | N26: PAYE | O26: Soixante trois mille neuf cents deux francs CFA | P26: MOBILE MONEY | Q26: - | R26: CAISSE
B27: 46200 | C27: CC-0017-2026 | D27: SERVICE | E27: TRANSFERT DHL | F27: DHL | G27: DHL | H27: - | I27: - | J27: benincustomerservice@dhl.com | K27: WAYBILL : 1790527410 | L27: TRANSFERT DE DOCUMENT PAR DHL | M27: 127804 | N27: PAYE | O27: Cent vingt sept mille huit cent quatre francs CFA | P27: MOBILE MONEY | Q27: - | R27: CAISSE
B28: 46199 | C28: CC-0018-2026 | D28: EXPORT | E28: TELEX | F28: MAERSK | G28: MAERSK | H28: - | I28: - | J28: - | K28: - | L28: REQUEST OF TELEX BL269555573 | M28: 20491 | N28: PAYE | O28: Vingt mille quatre cent quatre vingt onze francs CFA | P28: ESPECES | Q28: - | R28: CAISSE
B29: 46199 | C29: CC-0019-2026 | D29: SERVICE | E29: SERVICE | F29: VIGAN JUSTIN | G29: VIGAN JUSTIN | H29: - | I29: - | J29: - | K29: - | L29: LABOUR WORK SOYA ACC | M29: 190162 | N29: PAYE | O29: Cent quatre vingt dix mille cent soixante deux francs CFA | P29: ESPECES | Q29: - | R29: CAISSE
... B32: 46212 | C32: CC-0022-2026 | D32: SERVICE | E32: TRANSFERT DHL | F32: DHL | G32: DHL | H32: - | I32: - | J32: benincustomerservice@dhl.com | K32: WAYBILL : 6192239734 | L32: TRANSFERT DE DOCUMENT PAR DHL | M32: 63902 | N32: PAYE | O32: Soixante trois mille neuf cents deux francs CFA | P32: MOBILE MONEY | Q32: - | R32: CAISSE
B33: 46221 | C33: CC-0023-2026 | D33: SERVICE | E33: SERVICE | F33: JUSTIN VIGAN | G33: JUSTIN VIGAN | H33: 20921662429826 | I33: 47997 | J33: 8924266129 | K33: No 058/PS-26 | L33: LABOUR WORK SOYA ACC | M33: 107939 | N33: PAYE | O33: Cent sept mille neuf cent trente neuf francs CFA | P33: ESPECES | Q33: - | R33: CAISSE
B34: 46219 | C34: CC-0024-2026 | D34: SERVICE | E34: TRANSFERT DHL | F34: DHL | G34: DHL | H34: - | I34: - | J34: benincustomerservice@dhl.com | K34: WAYBILL : 6192239734 | L34: TRANSFERT DE DOCUMENT PAR DHL | M34: 63902 | N34: PAYE | O34: Soixante trois mille neuf cents deux francs CFA | P34: MOBILE MONEY | Q34: - | R34: CAISSE
B35: 46216 | C35: CC-0025-2026 | D35: SERVICE | E35: SERVICE | F35: STE PAPETERIE MODERNE SARL | G35: STE PAPETERIE MODERNE SARL | H35: - | I35: - | J35: - | K35: FACTURE 13195 | L35: ACHAT DE FOURNITURE BUREAU | M35: 41448 | N35: PAYE | O35: Quarante un mille quatre cent quarante huit francs CFA | P35: ESPECES | Q35: - | R35: CAISSE
B36: 46216 | C36: CC-0026-2026 | D36: SERVICE | E36: SERVICE | F36: CBP | G36: CBP | H36: - | I36: - | J36: - | K36: FACTURE 35059-2026 | L36: ACHAT DE FOURNITURE BUREAU | M36: 11850 | N36: PAYE | O36: Onze mille huit cent cinquante francs CFA | P36: ESPECES | Q36: - | R36: CAISSE
B37: 46216 | C37: CC-0027-2026 | D37: SERVICE | E37: SERVICE | F37: SONAEC | G37: SONAEC | H37: - | I37: - | J37: - | K37: FACTURE CC246704 | L37: ACHAT DE FOURNITURE BUREAU | M37: 48300 | N37: PAYE | O37: Quarante huit mille trois cent francs CFA | P37: ESPECES | Q37: - | R37: CAISSE
B38: 46200 | C38: CC-0028-2026 | D38: SERVICE | E38: SERVICE | F38: IDRISSOU APHISSOU | G38: IDRISSOU APHISSOU | H38: 5924678990 | I38: 30/8/2027 | J38: 0196109481 | K38: - | L38: LABOUR WORK SOYA ACC | M38: 1500000 | N38: AVANCE | O38: Un million cinq cent mille francs CFA | P38: ESPECES | Q38: - | R38: CAISSE
B39: 46216 | C39: CC-0029-2026 | D39: SERVICE | E39: SERVICE | F39: SBEE | G39: SBEE | H39: - | I39: - | J39: - | K39: REF 2559224 | L39: PAIEMENT FACTURE D'ELECTRICITE SBEE/ ZE PLAQUE | M39: 20200 | N39: PAYE | O39: Vingt mille deux cents francs CFA | P39: ESPECES | Q39: - | R39: CAISSE
B40: 46220 | C40: CC-0030-2026 | D40: SERVICE | E40: SALARY | F40: EMPLOYE USINE | G40: ADIGNON SYLVAIN | H40: 8188560503 | I40: 48094 | J40: 01 95 55 78 89 | K40: - | L40: SALARY AND LOCAL ALLOWANCE JUIN 2026 | M40: 2930000 | N40: PAYE | O40: Deux millions neuf cent trente mille francs CFA | P40: ESPECES | Q40: - | R40: CAISSE
B41: 46218 | C41: CC-0031-2026 | D41: SERVICE | E41: SERVICE | F41: MARILOG AFRICA | G41: MARILOG AFRICA | H41: - | I41: - | J41: - | K41: 270-FACT | L41: VERIFICATION DE STOCK USINE DE GDIZ & SITE DE SEKOU | M41: 1500000 | N41: PAYE | O41: Un million cinq cent mille francs CFA | P41: VIREMENT | Q41: - | R41: ECOBANK BENIN
B42: 46221 | C42: CC-0032-2026 | D42: SERVICE | E42: SERVICE | F42: STE PAPETERIE MODERNE SARL | G42: STE PAPETERIE MODERNE SARL | H42: - | I42: - | J42: - | K42: - | L42: ACHAT DE FOURNITURE BUREAU | M42: 3026 | N42: PAYE | O42: Trois mille vingt six francs CFA | P42: ESPECES | Q42: - | R42: CAISSE
B43: 46227 | C43: CC-0033-2026 | D43: SERVICE | E43: SERVICE | F43: SBEE | G43: SBEE | H43: - | I43: - | J43: - | K43: REF 2627531 | L43: PAIEMENT FACTURE D'ELECTRICITE SBEE/ AJAY BABU | M43: 50000 | N43: PAYE | O43: Cinquante mille francs CFA | P43: MOBILE MONEY | Q43: - | R43: CAISSE
B44: 46227 | C44: CC-0034-2026 | D44: SERVICE | E44: SERVICE | F44: SBEE | G44: SBEE | H44: - | I44: - | J44: - | K44: REF aaec52a885 | L44: PAIEMENT FACTURE D'ELECTRICITE SBEE/ MAISON GLO | M44: 100000 | N44: PAYE | O44: Cent mille francs CFA | P44: MOBILE MONEY | Q44: - | R44: CAISSE
B45: 46228 | C45: CC-0035-2026 | D45: SERVICE | E45: TRANSFERT DHL | F45: DHL | G45: DHL | H45: - | I45: - | J45: benincustomerservice@dhl.com | K45: WAYBILL : 4074627966 | L45: TRANSFERT DE DOCUMENT PAR DHL | M45: 127804 | N45: PAYE | O45: Cent vingt sept mille huit cent quatre francs CFA | P45: MOBILE MONEY | Q45: - | R45: CAISSE
B46: 46227 | C46: CC-0036-2026 | D46: SERVICE | E46: SERVICE | F46: SBEE | G46: SBEE | H46: - | I46: - | J46: - | K46: REF DGT3EQONVF | L46: PAIEMENT FACTURE D'ELECTRICITE SBEE/ NAP OFFICE | M46: 24900 | N46: PAYE | O46: Vingt quatre neuf cent francs CFA | P46: MOBILE MONEY | Q46: - | R46: CAISSE
B47: 46232 | C47: CC-0037-2026 | D47: SERVICE | E47: SERVICE | F47: KINHO VODOUNOUN SETH LIE ROSLIN | G47: KINHO VODOUNOUN SETH LIE ROSLIN | H47: 20410262291725 | I47: 46581 | J47: 0196194609 | K47: - | L47: FRAIS D'ETABLISSEMENT DES NON-GMO | M47: 700000 | N47: PAYE | O47: Sept cent mille francs CFA | P47: ESPECES | Q47: - | R47: ECOBANK BENIN
B48: 46233 | C48: CC-0038-2026 | D48: SERVICE | E48: SERVICE | F48: KINHO VODOUNOUN SETH LIE ROSLIN | G48: KINHO VODOUNOUN SETH LIE ROSLIN | H48: 20410262291725 | I48: 46581 | J48: 0196194609 | K48: - | L48: FRAIS D'ETABLISSEMENT DES NON-GMO | M48: 300000 | N48: PAYE | O48: Trois cent mille francs CFA | P48: ESPECES | Q48: - | R48: ECOBANK BENIN
B49: 46233 | C49: CC-0039-2026 | D49: SERVICE | E49: SERVICE | F49: JUSTIN VIGAN | G49: JUSTIN VIGAN | H49: 20921662429826 | I49: 47997 | J49: 8924266129 | K49: No 059/PS-26 | L49: LABOUR WORK SOYA ACC | M49: 82954 | N49: PAYE | O49: Quatre vingt deux mille neuf cent cinquante quatre francs CFA | P49: ESPECES | Q49: - | R49: CAISSE
B50: 46233 | C50: CC-0040-2026 | D50: SERVICE | E50: SERVICE | F50: ACE GLOBAL | G50: GLONI | H50: SETON AMOUROS GEOFRANE | I50: 46263 | J50: 0168457478 | K50: - | L50: CERTIFICAT DE QUALITE ET DE POIDS POUR 10 BL | M50: 600000 | N50: PAYE | O50: Six cents mille francs CFA | P50: ESPECES | Q50: - | R50: CAISSE
B51: 46233 | C51: CC-0041-2026 | D51: SERVICE | E51: SERVICE | F51: SBEE | G51: SBEE | H51: - | I51: - | J51: - | K51: REF 2697622 | L51: PAIEMENT FACTURE D'ELECTRICITE SBEE/ NAP OFFICE | M51: 25250 | N51: PAYE | O51: Vingt cinq mille deux cent cinquante francs CFA | P51: MOBILE MONEY | Q51: - | R51: CAISSE
B52: 46233 | C52: CC-0042-2026 | D52: SERVICE | E52: SERVICE | F52: SBEE | G52: SBEE | H52: - | I52: - | J52: - | K52: REF 2698084 | L52: PAIEMENT FACTURE D'ELECTRICITE SBEE/ NAP OFFICE | M52: 15150 | N52: PAYE | O52: Quinze mille cent cinquante francs CFA | P52: MOBILE MONEY | Q52: - | R52: CAISSE
B53: 46228 | C53: CC-0043-2026 | D53: AUTRE | E53: AUTRE | F53: CABINET DENTAIRE DIAMON | G53: NARALASETTI AJE YABABU | H53: - | I53: - | J53: - | K53: ED05001152 | L53: SOINS DENTAIRE / NARALASETTI AJE YABABU | M53: 40400 | N53: PAYE | O53: Quarante mille quatre cent francs CFA | P53: ESPECES | Q53: - | R53: CAISSE
B54: 46227 | C54: CC-0044-2026 | D54: AUTRE | E54: AUTRE | F54: NAGA SRINIVAS | G54: NAGA SRINIVAS | H54: - | I54: - | J54: - | K54: EM01066672-282 | L54: PRESTATION DE SOINS MEDICAUX DE NAGA SRINIVAS | M54: 80000 | N54: PAYE | O54: Quatre vingt mille francs CFA | P54: ESPECES | Q54: - | R54: CAISSE
B55: 46237 | C55: CC-0045-2026 | D55: SERVICE | E55: SERVICE | F55: VOYELO FINANGNON | G55: VOYELO FINANGNON | H55: 4918023191 | I55: 47919 | J55: 0197963302 | K55: - | L55: 30 SACS DE CIMENT / Mr. ARMEL | M55: 115500 | N55: PAYE | O55: Cent quinze mille cinq cent francs CFA | P55: ESPECES | Q55: - | R55: CAISSE
B56: 46237 | C56: CC-0046-2026 | D56: SERVICE | E56: TRANSFERT DHL | F56: DHL | G56: DHL | H56: - | I56: - | J56: benincustomerservice@dhl.com | K56: WAYBILL : 2408274606 | L56: TRANSFERT DE DOCUMENT PAR DHL | M56: 63902 | N56: PAYE | O56: Soixante trois mille neuf cents deux francs CFA | P56: MOBILE MONEY | Q56: - | R56: CAISSE
B57: 46238 | C57: CC-0047-2026 | D57: SERVICE | E57: SERVICE | F57: HPC | G57: HPC | H57: - | I57: - | J57: - | K57: - | L57: MAINTENANCE PC | M57: 51000 | N57: PAYE | O57: Cinquante un mille francs CFA | P57: ESPECES | Q57: - | R57: CAISSE
B58: 46241 | C58: CC-0048-2026 | D58: SERVICE | E58: COMPTABILITE | F58: SYNEX CONSULTING | G58: GANDOTE MARTIAL SEDJRO | H58: 21PP36956 | I58: 46715 | J58: - | K58: - | L58: RAPPORTS DU COMMISSAIRE AUX COMPTES SUR LES COMPTES ANNUELS DE L'EXCERCICE CLOS LE 31-12-2025 | M58: 1500000 | N58: PAYE | O58: Un million cinq cent mille francs CFA | P58: ESPECES | Q58: - | R58: CAISSE
B59: 46244 | C59: CC-0049-2026 | D59: SERVICE | E59: SERVICE | F59: KINHO VODOUNOUN SETH LIE ROSLIN | G59: KINHO VODOUNOUN SETH LIE ROSLIN | H59: 20410262291725 | I59: 46581 | J59: 0196194609 | K59: - | L59: FRAIS D'ETABLISSEMENT DES NON-GMO / Bl MEDUCT202800 | M59: 100000 | N59: PAYE | O59: Cent mille francs CFA | P59: ESPECES | Q59: - | R59: ECOBANK BENIN
B60: 46245 | C60: CC-0050-2026 | D60: SERVICE | E60: SERVICE | F60: SBIN | G60: - | H60: - | I60: - | J60: - | K60: K0004233855 | L60: CONNEXION INTERNET OFFICE | M60: 24900 | N60: PAYE | O60: =SUBSTITUTE(_xlfn.TRANSLATE(BAHTTEXT(Table1[[#This Row],[Montant]]),"th","fr")," bahts"," francs CFA") -> #NAME? | P60: MOBILE MONEY | Q60: - | R60: CAISSE
B61: 46245 | C61: CC-0051-2026 | D61: SERVICE | E61: SERVICE | F61: - | G61: - | H61: - | I61: - | J61: - | K61: No 2602951282-001D/BN | L61: ETABLISSEMENT DE CARTE BIOMETRIQUE DE GARBA BOURAIMA | M61: 6000 | N61: PAYE | O61: =SUBSTITUTE(_xlfn.TRANSLATE(BAHTTEXT(Table1[[#This Row],[Montant]]),"th","fr")," bahts"," francs CFA") -> #NAME? | P61: MOBILE MONEY | Q61: - | R61: CAISSE
B62: 46245 | C62: CC-0052-2026 | D62: EXPORT | E62: FRET EXPORT | F62: MAERSK | G62: MAERSK | H62: - | I62: - | J62: - | K62: - | L62: PAYEMENT FACTURE COMMISSION EXPORT POUR LES BL : 274133691, 274133543 | M62: 102960 | N62: PAYE | O62: =SUBSTITUTE(_xlfn.TRANSLATE(BAHTTEXT(Table1[[#This Row],[Montant]]),"th","fr")," bahts"," francs CFA") -> #NAME? | P62: ESPECES | Q62: - | R62: CAISSE
B63: 46240 | C63: CC-0053-2026 | D63: SERVICE | E63: TRANSFERT DHL | F63: DHL | G63: DHL | H63: - | I63: - | J63: benincustomerservice@dhl.com | K63: WAYBILL : 7393715173 | L63: TRANSFERT DE DOCUMENT PAR DHL | M63: 63902 | N63: PAYE | O63: =SUBSTITUTE(_xlfn.TRANSLATE(BAHTTEXT(Table1[[#This Row],[Montant]]),"th","fr")," bahts"," francs CFA") -> #NAME? | P63: MOBILE MONEY | Q63: - | R63: CAISSE
B64: 46245 | C64: CC-0054-2026 | D64: SERVICE | E64: TRANSFERT DHL | F64: DHL | G64: DHL | H64: - | I64: - | J64: benincustomerservice@dhl.com | K64: WAYBILL : 3439610930 | L64: TRANSFERT DE DOCUMENT PAR DHL | M64: 55904 | N64: PAYE | O64: =SUBSTITUTE(_xlfn.TRANSLATE(BAHTTEXT(Table1[[#This Row],[Montant]]),"th","fr")," bahts"," francs CFA") -> #NAME? | P64: MOBILE MONEY | Q64: - | R64: CAISSE
B65: 46246 | C65: CC-0055-2026 | D65: SERVICE | E65: SERVICE | F65: KINHO VODOUNOUN SETH LIE ROSLIN | G65: KINHO VODOUNOUN SETH LIE ROSLIN | H65: 20410262291725 | I65: 46581 | J65: 0196194609 | K65: - | L65: FRAIS D'ETABLISSEMENT DES NON-GMO / BL MEDUCT202875 | M65: 100000 | N65: PAYE | O65: Cent mille francs CFA | P65: ESPECES | Q65: - | R65: CAISSE
B66: 46247 | C66: CC-0056-2026 | D66: EXPORT | E66: FRET EXPORT | F66: MAERSK | G66: MAERSK | H66: - | I66: - | J66: - | K66: - | L66: PAYEMENT FACTURE COMMISSION EXPORT POUR LES BL : 272826020, 272826117, 273955510, 273955686, 272826293, 274567204 | M66: 277992 | N66: PAYE | O66: =SUBSTITUTE(_xlfn.TRANSLATE(BAHTTEXT(Table1[[#This Row],[Montant]]),"th","fr")," bahts"," francs CFA") -> #NAME? | P66: ESPECES | Q66: - | R66: CAISSE
B67: 46248 | C67: CC-0057-2026 | D67: EXPORT | E67: FRET EXPORT | F67: MAERSK | G67: MAERSK | H67: - | I67: - | J67: - | K67: - | L67: FACTURE POUR DE TELEX BL 271337976 & 271172498 | M67: 41695 | N67: PAYE | O67: =SUBSTITUTE(_xlfn.TRANSLATE(BAHTTEXT(Table1[[#This Row],[Montant]]),"th","fr")," bahts"," francs CFA") -> #NAME? | P67: ESPECES | Q67: - | R67: CAISSE
B68: 46248 | C68: CC-0058-2026 | D68: SERVICE | E68: SERVICE | F68: SBEE | G68: SBEE | H68: - | I68: - | J68: - | K68: REF 2836843 | L68: PAIEMENT FACTURE D'ELECTRICITE SBEE/ ALLADA | M68: 20000 | N68: PAYE | O68: Quinze mille cent cinquante francs CFA | P68: MOBILE MONEY | Q68: - | R68: CAISSE
B69: 46251 | C69: CC-0059-2026 | D69: EXPORT | E69: TELEX | F69: MAERSK | G69: MAERSK | H69: - | I69: - | J69: - | K69: - | L69: REQUEST OF TELEX BL 272005087, 272299963, 271285360 | M69: 62505 | N69: PAYE | O69: =SUBSTITUTE(_xlfn.TRANSLATE(BAHTTEXT(Table1[[#This Row],[Montant]]),"th","fr")," bahts"," francs CFA") -> #NAME? | P69: ESPECES | Q69: - | R69: CAISSE
B70: 46251 | C70: CC-0060-2026 | D70: SERVICE | E70: TRANSFERT DHL | F70: DHL | G70: DHL | H70: - | I70: - | J70: benincustomerservice@dhl.com | K70: WAYBILL : 2926070173 | L70: TRANSFERT DE DOCUMENT PAR DHL | M70: 55904 | N70: PAYE | O70: =SUBSTITUTE(_xlfn.TRANSLATE(BAHTTEXT(Table1[[#This Row],[Montant]]),"th","fr")," bahts"," francs CFA") -> #NAME? | P70: MOBILE MONEY | Q70: - | R70: CAISSE
B71: 46251 | C71: CC-0061-2026 | D71: SERVICE | E71: TRANSFERT DHL | F71: DHL | G71: DHL | H71: - | I71: - | J71: benincustomerservice@dhl.com | K71: - | L71: TRANSFERT DE DOCUMENT PAR DHL | M71: 8000 | N71: PAYE | O71: =SUBSTITUTE(_xlfn.TRANSLATE(BAHTTEXT(Table1[[#This Row],[Montant]]),"th","fr")," bahts"," francs CFA") -> #NAME? | P71: MOBILE MONEY | Q71: - | R71: CAISSE
B72: 46251 | C72: CC-0062-2026 | D72: EXPORT | E72: TELEX | F72: MAERSK | G72: MAERSK | H72: - | I72: - | J72: - | K72: - | L72: REQUEST OF TELEX BL 271321384 | M72: 20875 | N72: PAYE | O72: =SUBSTITUTE(_xlfn.TRANSLATE(BAHTTEXT(Table1[[#This Row],[Montant]]),"th","fr")," bahts"," francs CFA") -> #NAME? | P72: ESPECES | Q72: - | R72: CAISSE
B73: 46252 | C73: CC-0063-2026 | D73: EXPORT | E73: SERVICE | F73: KINHO VODOUNOUN SETH LIE ROSLIN | G73: KINHO VODOUNOUN SETH LIE ROSLIN | H73: 20410262291725 | I73: 46581 | J73: 0196194609 | K73: - | L73: FRAIS D'ETABLISSEMENT DES NON-GMO / BL 271322421 ET BL272808713 | M73: 200000 | N73: PAYE | O73: Cent mille francs CFA | P73: ESPECES | Q73: - | R73: CAISSE
B74: 46254 | C74: CC-0064-2026 | D74: SERVICE | E74: CERTICAT | F74: HAMA INTER | G74: EGOUCHOLA TETEDE DAMIEN | H74: 7668041413 | I74: 46670 | J74: 0166562863 | K74: - | L74: FRAIS DE PRESTATION_POUR CERTICAT EXPRESS BL 271322421 | M74: 20000 | N74: PAYE | O74: Vingt mille franc CFA | P74: ESPECES | R74: CAISSE
B75: 46254 | C75: CC-0065-2026 | D75: EXPORT | E75: SERVICE | F75: KINHO VODOUNOUN SETH LIE ROSLIN | G75: KINHO VODOUNOUN SETH LIE ROSLIN | H75: 20410262291725 | I75: 46581 | J75: 0196194609 | K75: - | L75: FRAIS D'ETABLISSEMENT DES NON-GMO 271321717 // 274133691 // 273955686 // 273955510 // 272826020 | M75: 500000 | N75: PAYE | O75: Cinq Cent mille francs CFA | P75: ESPECES | Q75: - | R75: CAISSE
B76: 46248 | C76: CC-0066-2026 | D76: SERVICE | E76: TRANSFERT DHL | F76: DHL | G76: DHL | H76: - | I76: - | J76: benincustomerservice@dhl.com | K76: WAYBILL : 8550163344 | L76: TRANSFERT DE DOCUMENT PAR DHL | M76: 63902 | N76: PAYE | O76: =SUBSTITUTE(_xlfn.TRANSLATE(BAHTTEXT(Table1[[#This Row],[Montant]]),"th","fr")," bahts"," francs CFA") -> #NAME? | P76: MOBILE MONEY | Q76: - | R76: CAISSE
B77: 46251 | C77: CC-0067-2026 | D77: SERVICE | E77: TRANSFERT DHL | F77: DHL | G77: DHL | H77: - | I77: - | J77: benincustomerservice@dhl.com | K77: WAYBILL : 6406435991 | L77: TRANSFERT DE DOCUMENT PAR DHL | M77: 63902 | N77: PAYE | O77: =SUBSTITUTE(_xlfn.TRANSLATE(BAHTTEXT(Table1[[#This Row],[Montant]]),"th","fr")," bahts"," francs CFA") -> #NAME? | P77: MOBILE MONEY | Q77: - | R77: CAISSE
B78: 46251 | C78: CC-0068-2026 | D78: SERVICE | E78: TRANSFERT DHL | F78: DHL | G78: DHL | H78: - | I78: - | J78: benincustomerservice@dhl.com | K78: WAYBILL : 8488455032 | L78: TRANSFERT DE DOCUMENT PAR DHL | M78: 63902 | N78: PAYE | O78: =SUBSTITUTE(_xlfn.TRANSLATE(BAHTTEXT(Table1[[#This Row],[Montant]]),"th","fr")," bahts"," francs CFA") -> #NAME? | P78: MOBILE MONEY | Q78: - | R78: CAISSE
B79: 46253 | C79: CC-0069-2026 | D79: SERVICE | E79: SERVICE | F79: MARILOG AFRICA | G79: MARILOG AFRICA | H79: - | I79: - | J79: - | K79: 343-FACT | L79: VERIFICATION DE STOCK USINE DE GDIZ & SITE DE SEKOU | M79: 1500000 | N79: PAYE | O79: =SUBSTITUTE(_xlfn.TRANSLATE(BAHTTEXT(Table1[[#This Row],[Montant]]),"th","fr")," bahts"," francs CFA") -> #NAME? | P79: VIREMENT | Q79: - | R79: ECOBANK BENIN
B80: 46255 | C80: CC-0070-2026 | D80: SERVICE | E80: SERVICE | F80: SBEE | G80: SBEE | H80: - | I80: - | J80: - | K80: REF aaec572d2f | L80: PAIEMENT FACTURE D'ELECTRICITE SBEE/ MAISON GLO | M80: 50000 | N80: PAYE | O80: =SUBSTITUTE(_xlfn.TRANSLATE(BAHTTEXT(Table1[[#This Row],[Montant]]),"th","fr")," bahts"," francs CFA") -> #NAME? | P80: MOBILE MONEY | Q80: - | R80: CAISSE
B81: 46255 | C81: CC-0071-2026 | D81: PURCHASE | E81: SHEA | F81: DOSSOU GOUDOU ROMAIN | G81: DOSSOU GOUDOU ROMAIN | H81: 20468091846526 | I81: 47930 | J81: 0197720697 | K81: BB9793RB/BD3472RB_34.98 MT | L81: PURCHASE OF SHEA | M81: 200000 | N81: AVANCE | O81: Deux cent mille francs CFA | P81: ESPECES | Q81: - | R81: CAISSE
B82: 46255 | C82: CC-0072-2026 | D82: EXPORT | E82: SERVICE | F82: KINHO VODOUNOUN SETH LIE ROSLIN | G82: KINHO VODOUNOUN SETH LIE ROSLIN | H82: 20410262291725 | I82: 46581 | J82: 0196194609 | K82: - | L82: FRAIS D'ETABLISSEMENT DES NON-GMO / Bl 272826117 | M82: 100000 | N82: PAYE | O82: Cent mille francs CFA | P82: ESPECES | Q82: - | R82: CAISSE
B83: 46258 | C83: CC-0073-2026 | D83: EXPORT | E83: SERVICE | F83: KINHO VODOUNOUN SETH LIE ROSLIN | G83: KINHO VODOUNOUN SETH LIE ROSLIN | H83: 20410262291725 | I83: 46581 | J83: 0196194609 | K83: - | L83: FRAIS D'ETABLISSEMENT DES NON-GMO / Bl MEDUCT204509, MEDUCT203543, 274133543 | M83: 300000 | N83: PAYE | O83: =SUBSTITUTE(_xlfn.TRANSLATE(BAHTTEXT(Table1[[#This Row],[Montant]]),"th","fr")," bahts"," francs CFA") -> #NAME? | P83: ESPECES | Q83: - | R83: CAISSE
B84: 46260 | C84: CC-0074-2026 | D84: PURCHASE | E84: SHEA | F84: MEHSAN DANIEL JOEL | G84: KPADONOU SOUROU JOEL | H84: 20278660572226 | I84: 48091 | J84: 0196309042 | K84: BA0693RB/BG9156RB_45.30 MT | L84: PURCHASE OF SHEA | M84: 100000 | N84: AVANCE | O84: Cent mille francs CFA | P84: ESPECES | Q84: - | R84: CAISSE
B85: 46260 | C85: CC-0075-2026 | D85: PURCHASE | E85: SHEA | F85: AHEGNI CASIMIR | G85: AHEGNI HIPPOLYTE | H85: 20411113178625 | I85: 46585 | J85: 0196034539 | K85: AP7150RB/AL0466RB_33.98 MT & CA5858RB/AC1719RB_46.92 MT | L85: PURCHASE OF SHEA | M85: 5000000 | N85: AVANCE | O85: =SUBSTITUTE(_xlfn.TRANSLATE(BAHTTEXT(Table1[[#This Row],[Montant]]),"th","fr")," bahts"," francs CFA") -> #NAME? | P85: ESPECES | Q85: - | R85: CAISSE
B86: 46260 | C86: CC-0076-2026 | D86: EXPORT | E86: TELEX | F86: MAERSK | G86: MAERSK | H86: - | I86: - | J86: - | K86: - | L86: REQUEST OF TELEX BL 271172507 | M86: 20802 | N86: PAYE | O86: =SUBSTITUTE(_xlfn.TRANSLATE(BAHTTEXT(Table1[[#This Row],[Montant]]),"th","fr")," bahts"," francs CFA") -> #NAME? | P86: ESPECES | Q86: - | R86: CAISSE
B87: 46261 | C87: CC-0077-2026 | D87: SERVICE | E87: TRANSFERT DHL | F87: DHL | G87: DHL | H87: - | I87: - | J87: benincustomerservice@dhl.com | K87: WAYBILL : 1609260870 | L87: TRANSFERT DE DOCUMENT PAR DHL | M87: 63902 | N87: PAYE | O87: =SUBSTITUTE(_xlfn.TRANSLATE(BAHTTEXT(Table1[[#This Row],[Montant]]),"th","fr")," bahts"," francs CFA") -> #NAME? | P87: MOBILE MONEY | Q87: - | R87: CAISSE
B88: 46258 | C88: CC-0078-2026 | D88: SERVICE | E88: TRANSFERT DHL | F88: DHL | G88: DHL | H88: - | I88: - | J88: benincustomerservice@dhl.com | K88: WAYBILL : 6863120714 | L88: TRANSFERT DE DOCUMENT PAR DHL | M88: 63902 | N88: PAYE | O88: =SUBSTITUTE(_xlfn.TRANSLATE(BAHTTEXT(Table1[[#This Row],[Montant]]),"th","fr")," bahts"," francs CFA") -> #NAME? | P88: MOBILE MONEY | Q88: - | R88: CAISSE
B89: 46258 | C89: CC-0079-2026 | D89: SERVICE | E89: SERVICE | F89: NAP SARL | G89: NAP SARL | H89: - | I89: - | J89: - | K89: - | L89: HUILE A MOTEUR VIDANGE POUR VEHICULE ADMINISTRATIF | M89: 15000 | N89: PAYE | O89: =SUBSTITUTE(_xlfn.TRANSLATE(BAHTTEXT(Table1[[#This Row],[Montant]]),"th","fr")," bahts"," francs CFA") -> #NAME? | P89: ESPECES | Q89: - | R89: CAISSE
B90: 46259 | C90: CC-0080-2026 | D90: SERVICE | E90: SERVICE | F90: SBEE | G90: SBEE | H90: - | I90: - | J90: - | K90: REF 2916710 | L90: PAIEMENT FACTURE D'ELECTRICITE SBEE/ MAISON DES CEO | M90: 20200 | N90: PAYE | O90: =SUBSTITUTE(_xlfn.TRANSLATE(BAHTTEXT(Table1[[#This Row],[Montant]]),"th","fr")," bahts"," francs CFA") -> #NAME? | P90: MOBILE MONEY | Q90: - | R90: CAISSE
B91: 46256 | C91: CC-0081-2026 | D91: SERVICE | E91: SERVICE | F91: ELECTRO ZONE | G91: ELECTRO ZONE | H91: - | I91: - | J91: - | K91: REF FACT 0002536 | L91: ACHAT TELEVISION | M91: 135000 | N91: PAYE | O91: =SUBSTITUTE(_xlfn.TRANSLATE(BAHTTEXT(Table1[[#This Row],[Montant]]),"th","fr")," bahts"," francs CFA") -> #NAME? | P91: ESPECES | Q91: - | R91: CAISSE
B92: 46261 | C92: CC-0082-2026 | D92: SERVICE | E92: TRANSFERT DHL | F92: DHL | G92: DHL | H92: - | I92: - | J92: benincustomerservice@dhl.com | K92: WAYBILL : 8997737490 /8997734686 | L92: TRANSFERT DE DOCUMENT PAR DHL | M92: 142806 | N92: PAYE | O92: =SUBSTITUTE(_xlfn.TRANSLATE(BAHTTEXT(Table1[[#This Row],[Montant]]),"th","fr")," bahts"," francs CFA") -> #NAME? | P92: MOBILE MONEY | Q92: - | R92: CAISSE
B93: 46263 | C93: CC-0083-2026 | D93: PURCHASE | E93: SHEA | F93: VLAVONOU PIERRE | G93: DAOUDA MACHOUDI | H93: 100160634 | I93: 46573 | J93: - | K93: CL2204RB/BU2541RB_50.32 MT | L93: PURCHASE OF SHEA | M93: 1000000 | N93: AVANCE | O93: =SUBSTITUTE(_xlfn.TRANSLATE(BAHTTEXT(Table1[[#This Row],[Montant]]),"th","fr")," bahts"," francs CFA") -> #NAME? | P93: MOBILE MONEY | Q93: - | R93: CAISSE
B94: 46266 | C94: CC-0084-2026 | D94: EXPORT | E94: SERVICE | F94: KINHO VODOUNOUN SETH LIE ROSLIN | G94: KINHO VODOUNOUN SETH LIE ROSLIN | H94: 20410262291725 | I94: 46581 | J94: 0196194609 | K94: - | L94: FRAIS D'ETABLISSEMENT DES NON-GMO / BL 274567204 & 272826293 | M94: 200000 | N94: PAYE | O94: Deux cent mille francs CFA | P94: ESPECES | Q94: - | R94: CAISSE
B95: 46266 | C95: CC-0085-2026 | D95: EXPORT | E95: FRET EXPORT | F95: MSC BENIN | G95: MSC BENIN | H95: - | I95: - | J95: - | K95: - | L95: PAYEMENT FRET EXPORT POUR LES BL : MEDUCT204962, MEDUCT205431, MEDUCT206777 | M95: 4261061 | N95: PAYE | O95: =SUBSTITUTE(_xlfn.TRANSLATE(BAHTTEXT(Table1[[#This Row],[Montant]]),"th","fr")," bahts"," francs CFA") -> #NAME? | P95: ESPECES | Q95: - | R95: CAISSE
B96: 46267 | C96: CC-0086-2026 | D96: EXPORT | E96: FRET EXPORT | F96: MSC BENIN | G96: MSC BENIN | H96: - | I96: - | J96: - | K96: - | L96: PAYEMENT FRET EXPORT POUR LES BL : MEDUCT205464 | M96: 1625442 | N96: PAYE | O96: =SUBSTITUTE(_xlfn.TRANSLATE(BAHTTEXT(Table1[[#This Row],[Montant]]),"th","fr")," bahts"," francs CFA") -> #NAME? | P96: ESPECES | Q96: - | R96: CAISSE
B97: 46267 | C97: CC-0087-2026 | D97: EXPORT | E97: FRET EXPORT | F97: MSC BENIN | G97: MSC BENIN | H97: - | I97: - | J97: - | K97: - | L97: PAYEMENT FACTURE RECTIF POUR LES BL : MEDUCT204962, MEDUCT205431, MEDUCT206777 | M97: 132705 | N97: PAYE | O97: =SUBSTITUTE(_xlfn.TRANSLATE(BAHTTEXT(Table1[[#This Row],[Montant]]),"th","fr")," bahts"," francs CFA") -> #NAME? | P97: ESPECES | Q97: - | R97: CAISSE
B98: 46267 | C98: CC-0088-2026 | D98: SERVICE | E98: SERVICE | F98: SBEE | G98: SBEE | H98: - | I98: - | J98: - | K98: REF aaec5b0d20 | L98: PAIEMENT FACTURE D'ELECTRICITE SBEE/ NAP OFFICE | M98: 100000 | N98: PAYE | O98: Cent mille francs CFA | P98: ESPECES | Q98: - | R98: CAISSE
B99: 46268 | C99: CC-0089-2026 | D99: TRANSFERT DE FOND | E99: TRANSFERT DE FOND | F99: NAP SARL | G99: ADIGNON SYLVAIN | H99: 8188560503 | I99: 48094 | J99: 01 95 55 78 89 | K99: - | L99: CAISSE GDIZ | M99: 1000000 | N99: PAYE | O99: =SUBSTITUTE(_xlfn.TRANSLATE(BAHTTEXT(Table1[[#This Row],[Montant]]),"th","fr")," bahts"," francs CFA") -> #NAME? | P99: ESPECES | Q99: - | R99: CAISSE
B100: 46268 | C100: CC-0090-2026 | D100: EXPORT | E100: FRET EXPORT | F100: MSC BENIN | G100: MSC BENIN | H100: - | I100: - | J100: - | K100: - | L100: PAYEMENT FACTURE RECTIF POUR LES BL : MEDUCT205464 | M100: 44235 | N100: PAYE | O100: =SUBSTITUTE(_xlfn.TRANSLATE(BAHTTEXT(Table1[[#This Row],[Montant]]),"th","fr")," bahts"," francs CFA") -> #NAME? | P100: ESPECES | Q100: - | R100: CAISSE
B101: 46268 | C101: CC-0091-2026 | D101: EXPORT | E101: TELEX | F101: MAERSK | G101: MAERSK | H101: - | I101: - | J101: - | K101: - | L101: REQUEST OF TELEX BL 274567204, 272826293 | M101: 41184 | N101: PAYE | O101: =SUBSTITUTE(_xlfn.TRANSLATE(BAHTTEXT(Table1[[#This Row],[Montant]]),"th","fr")," bahts"," francs CFA") -> #NAME? | P101: ESPECES | Q101: - | R101: CAISSE
B102: 46262 | C102: CC-0092-2026 | D102: SERVICE | E102: TRANSFERT DHL | F102: DHL | G102: DHL | H102: - | I102: - | J102: benincustomerservice@dhl.com | K102: WAYBILL : 4130821343 | L102: TRANSFERT DE DOCUMENT PAR DHL | M102: 63902 | N102: PAYE | O102: =SUBSTITUTE(_xlfn.TRANSLATE(BAHTTEXT(Table1[[#This Row],[Montant]]),"th","fr")," bahts"," francs CFA") -> #NAME? | P102: MOBILE MONEY | Q102: - | R102: CAISSE
B103: 46262 | C103: CC-0093-2026 | D103: SERVICE | E103: TRANSFERT DHL | F103: DHL | G103: DHL | H103: - | I103: - | J103: benincustomerservice@dhl.com | K103: WAYBILL : 1121401315, 8227327953, 8227317420 | L103: TRANSFERT DE DOCUMENT PAR DHL | M103: 191706 | N103: PAYE | O103: =SUBSTITUTE(_xlfn.TRANSLATE(BAHTTEXT(Table1[[#This Row],[Montant]]),"th","fr")," bahts"," francs CFA") -> #NAME? | P103: MOBILE MONEY | Q103: - | R103: CAISSE
B104: 46269 | C104: CC-0094-2026 | D104: PURCHASE | E104: SHEA | F104: VLAVONOU PIERRE | G104: VLAVONOU PIERRE | H104: 23PP67637 | I104: 47393 | J104: - | K104: CL2204RB/BU2541RB_50.32 MT | L104: PURCHASE OF SHEA | M104: 5000000 | N104: AVANCE | O104: =SUBSTITUTE(_xlfn.TRANSLATE(BAHTTEXT(Table1[[#This Row],[Montant]]),"th","fr")," bahts"," francs CFA") -> #NAME? | P104: ESPECES | Q104: - | R104: CAISSE
...

Sheet FICHE
D3: `
E4: STE NAP SARL
D7: PLOT NO 14 GLODJIGBE ECONIMIC ZONEREPUBLIC OF BENIN RCCM RB / COT / 21 B 30710, IFU 3202113334014 TEL: +229 0194940414, 0197974506
F11: Bon de paiement
D13: Date | E13: =_xlfn.XLOOKUP($E$14,DEPENSES!C:C,DEPENSES!B:B) -> 46311 | G13: Prestataires/Fournisseurs | H13: =_xlfn.XLOOKUP($E$14,DEPENSES!C:C,DEPENSES!F:F) -> AHEGNI CASIMIR
D14: No de transaction | E14: CHQ-0391-2026
D15: Type d'operation | E15: =_xlfn.XLOOKUP($E$14,DEPENSES!C:C,DEPENSES!D:D) -> PURCHASE | G15: Nom du percepteur | H15: =_xlfn.XLOOKUP($E$14,DEPENSES!C:C,DEPENSES!G:G) -> AHEGNI HIPPOLYTE
D16: Produit | E16: =_xlfn.XLOOKUP($E$14,DEPENSES!C:C,DEPENSES!E:E) -> SHEA | G16: Num. Pieces d'identite | H16: =_xlfn.XLOOKUP($E$14,DEPENSES!C:C,DEPENSES!H:H) -> 20411113178625
G17: Date d'expiration | H17: =_xlfn.XLOOKUP($E$14,DEPENSES!C:C,DEPENSES!I:I) -> 46585
G18: Addresse /Telephone | H18: =_xlfn.XLOOKUP($E$14,DEPENSES!C:C,DEPENSES!J:J) -> 0196034539
D20: Details des operations
D21: Ref Doc | E21: Description/Objet du paiement | G21: Montant | H21: Observation
D22: =_xlfn.XLOOKUP($E$14,DEPENSES!C:C,DEPENSES!K:K) -> CB6370RB/BY4656RB_50.0 MT & CA5858RB/AC1719RB_45.46 MT | E22: =_xlfn.XLOOKUP($E$14,DEPENSES!C:C,DEPENSES!L:L) -> PURCHASE OF SHEA | G22: =_xlfn.XLOOKUP($E$14,DEPENSES!C:C,DEPENSES!M:M) -> 29611200 | H22: =_xlfn.XLOOKUP($E$14,DEPENSES!C:C,DEPENSES!N:N) -> PAYE
F24: Montant Total | G24: =SUM(G22:G23) -> 29611200
D26: Montant en lettre : | F26: =_xlfn.XLOOKUP($E$14,DEPENSES!C:C,DEPENSES!O:O) -> Vingt neuf millions Six cent onze mille Deux cent francs CFA
G29: Mode paiement | H29: =_xlfn.XLOOKUP($E$14,DEPENSES!C:C,DEPENSES!P:P) -> CHEQUE
G30: Numero de cheque | H30: =_xlfn.XLOOKUP($E$14,DEPENSES!C:C,DEPENSES!Q:Q) -> 2000755
G31: Banque | H31: =_xlfn.XLOOKUP($E$14,DEPENSES!C:C,DEPENSES!R:R) -> ECOBANK BENIN
D33: Manager logistics | F33: Comptablité | H33: Bénéficiaire
D37: visa | F37: visa | H37: visa
D38: NB: Toute remise de chèque doit être confirmée par signature du bénéficiaire et accompagnée d’une copie du chèque et pièce pour fins de traçabilité.

Sheet VERSEMENTS
C2: SUIVI DES VERSEMENTS
C3: DATE | D3: DOC REF | E3: NOM DU DEPOSANT | F3: MOTIF DE VERSEMENT | G3: MONTANT | H3: BANQUE
C4: 46174 | D4: M33CHDP261520548 | E4: GARBA IBRAHIM | F4: RECETTE | G4: 16000000 | H4: ECOBANK BENIN
C5: 46176 | D5: BD0410563 | E5: SHARMA RISHI | F5: RECETTE | G5: 700000 | H5: ATLANTIC BANK BENIN
C6: 46177 | E6: PAN TRADING | G6: 75477008 | H6: ECOBANK BENIN
C7: 46181 | D7: INVOICE NAP-1033-2026 AND NAP-1043-2026 | E7: PAN TRADING | G7: 70229590 | H7: ECOBANK BENIN
C8: 46182 | E8: VERSEMENT D'ESPECE PAR MITC | G8: 12000000 | H8: ECOBANK BENIN
C9: 46182 | E9: VERSEMENT D'ESPECE PAR MITC | G9: 13000000 | H9: ECOBANK BENIN
C10: 46183 | D10: INVOICE NAP-1038-2026A | E10: MAHARASHTRA SOLVENT EXTRACTION-EXPORT | G10: 6129482 | H10: ECOBANK BENIN
C11: 46183 | D11: M33CHDP261660033 | E11: AFFO MOUSSA IBRAHIM | F11: RECETTE | G11: 16000000 | H11: ECOBANK BENIN
C12: 46177 | D12: 4839552 | E12: BENIN COTON | G12: 54916680 | H12: BIIC
C13: 46186 | D13: 30601 | E13: AFFO MOUSSA IBRAHIM | F13: RECETTE | G13: 999900 | H13: BIIC
C14: 46182 | D14: 30499 | E14: AFFO MOUSSA IBRAHIM | F14: RECETTE | G14: 8000000 | H14: BIIC
C15: 46195 | D15: M33CHDP261730035 | E15: AFFO MOUSSA IBRAHIM | F15: RECETTE | G15: 8000000 | H15: ECOBANK BENIN
C16: 46195 | D16: M33CHDP261730036 | E16: AFFO MOUSSA IBRAHIM | F16: RECETTE | G16: 16000000 | H16: ECOBANK BENIN
C17: 46195 | D17: M33CHDP261730530 | E17: GARBA IBRAHIM | F17: RECETTE | G17: 16000000 | H17: ECOBANK BENIN
C18: 46195 | D18: M33CHDP261730531 | E18: GARBA IBRAHIM | F18: RECETTE | G18: 10000000 | H18: ECOBANK BENIN
C22: 46206 | D22: INVOICE NAP-1080-2026 | E22: SANJAY SOYA PRIVATE LIMITED | G22: 80960262 | H22: ATLANTIC BANK BENIN
C23: 46206 | D23: INVOICE NAP-1083-2026 | E23: SANJAY SOYA PRIVATE LIMITED | G23: 77936295 | H23: ATLANTIC BANK BENIN
C24: 46209 | D24: M33CHDP261870033 | E24: SHARMA RISHI | F24: RECETTE | G24: 2000000 | H24: ECOBANK BENIN
