Workbook

Sheet Synthese
A1: TABLEAU DE BORD — CHIFFRE D'AFFAIRES EXPORT
A3: INDICATEURS CLÉS
A4: Chiffre d'affaires HT (XOF) | B4: =Ventes!M56 -> 0
A5: Total Encaissé (XOF) | B5: =Ventes!N56 -> 0
A6: Reste à encaisser (XOF) | B6: =Ventes!O56 -> 0
A7: % Encaissé | B7: =IF(B4=0,0,B5/B4) -> 0
A8: Volume total vendu (MT) | B8: =Ventes!H56 -> 0
A11: COMMENT UTILISER
A12: 1. Onglet VENTES : saisissez chaque facture export (client, BL, produit, quantité, prix, devise, taux de change).
A13: 2. Le CA HT (devise et XOF) se calcule tout seul. Indiquez le montant encaissé en case jaune.
A14: 3. Statut se met à jour : Émise / Partiellement payée / Payée.
A15: 4. CA par Client et CA par Produit : vues automatiques pour piloter l'activité.
A16: 5. Onglet Listes : ajoutez vos clients et produits pour les listes déroulantes.
A19: NAP SARL — Suivi Chiffre d'Affaires Export — Fichier simple

Sheet Ventes
A1: SUIVI DU CHIFFRE D'AFFAIRES — VENTES EXPORT — NAP SARL
A2: Une ligne = une facture / une vente. Le CA HT se calcule automatiquement (Quantité × Prix). Renseignez les encaissements pour suivre ce qui est réellement rentré.
A4: N° | B4: Date Facture | C4: N° Facture | D4: Client | E4: N° Contrat | F4: N° BL | G4: Produit | H4: Quantité (MT) | I4: Prix Unitaire | J4: Devise | K4: Taux de change (vers XOF) | L4: CA HT (Devise) | M4: CA HT (XOF) | N4: Montant Encaissé (XOF) | O4: Reste à Encaisser (XOF) | P4: Incoterm | Q4: Statut | R4: Observations
A5: 1 | L5: =IF(OR(H5="",I5=""),"",H5*I5) | M5: =IF(OR(L5="",K5=""),"",L5*K5) | O5: =IF(M5="","",M5-IF(N5="",0,N5)) | Q5: =IF(M5="","",IF(N5="", "Émise", IF(O5<=0, "Payée", IF(N5>0, "Partiellement payée", "Émise"))))
A6: 2 | L6: =IF(OR(H6="",I6=""),"",H6*I6) | M6: =IF(OR(L6="",K6=""),"",L6*K6) | O6: =IF(M6="","",M6-IF(N6="",0,N6)) | Q6: =IF(M6="","",IF(N6="", "Émise", IF(O6<=0, "Payée", IF(N6>0, "Partiellement payée", "Émise"))))
A7: 3 | L7: =IF(OR(H7="",I7=""),"",H7*I7) | M7: =IF(OR(L7="",K7=""),"",L7*K7) | O7: =IF(M7="","",M7-IF(N7="",0,N7)) | Q7: =IF(M7="","",IF(N7="", "Émise", IF(O7<=0, "Payée", IF(N7>0, "Partiellement payée", "Émise"))))
A8: 4 | L8: =IF(OR(H8="",I8=""),"",H8*I8) | M8: =IF(OR(L8="",K8=""),"",L8*K8) | O8: =IF(M8="","",M8-IF(N8="",0,N8)) | Q8: =IF(M8="","",IF(N8="", "Émise", IF(O8<=0, "Payée", IF(N8>0, "Partiellement payée", "Émise"))))
A9: 5 | L9: =IF(OR(H9="",I9=""),"",H9*I9) | M9: =IF(OR(L9="",K9=""),"",L9*K9) | O9: =IF(M9="","",M9-IF(N9="",0,N9)) | Q9: =IF(M9="","",IF(N9="", "Émise", IF(O9<=0, "Payée", IF(N9>0, "Partiellement payée", "Émise"))))
A10: 6 | L10: =IF(OR(H10="",I10=""),"",H10*I10) | M10: =IF(OR(L10="",K10=""),"",L10*K10) | O10: =IF(M10="","",M10-IF(N10="",0,N10)) | Q10: =IF(M10="","",IF(N10="", "Émise", IF(O10<=0, "Payée", IF(N10>0, "Partiellement payée", "Émise"))))
A11: 7 | L11: =IF(OR(H11="",I11=""),"",H11*I11) | M11: =IF(OR(L11="",K11=""),"",L11*K11) | O11: =IF(M11="","",M11-IF(N11="",0,N11)) | Q11: =IF(M11="","",IF(N11="", "Émise", IF(O11<=0, "Payée", IF(N11>0, "Partiellement payée", "Émise"))))
A12: 8 | L12: =IF(OR(H12="",I12=""),"",H12*I12) | M12: =IF(OR(L12="",K12=""),"",L12*K12) | O12: =IF(M12="","",M12-IF(N12="",0,N12)) | Q12: =IF(M12="","",IF(N12="", "Émise", IF(O12<=0, "Payée", IF(N12>0, "Partiellement payée", "Émise"))))
A13: 9 | L13: =IF(OR(H13="",I13=""),"",H13*I13) | M13: =IF(OR(L13="",K13=""),"",L13*K13) | O13: =IF(M13="","",M13-IF(N13="",0,N13)) | Q13: =IF(M13="","",IF(N13="", "Émise", IF(O13<=0, "Payée", IF(N13>0, "Partiellement payée", "Émise"))))
A14: 10 | L14: =IF(OR(H14="",I14=""),"",H14*I14) | M14: =IF(OR(L14="",K14=""),"",L14*K14) | O14: =IF(M14="","",M14-IF(N14="",0,N14)) | Q14: =IF(M14="","",IF(N14="", "Émise", IF(O14<=0, "Payée", IF(N14>0, "Partiellement payée", "Émise"))))
A15: 11 | L15: =IF(OR(H15="",I15=""),"",H15*I15) | M15: =IF(OR(L15="",K15=""),"",L15*K15) | O15: =IF(M15="","",M15-IF(N15="",0,N15)) | Q15: =IF(M15="","",IF(N15="", "Émise", IF(O15<=0, "Payée", IF(N15>0, "Partiellement payée", "Émise"))))
A16: 12 | L16: =IF(OR(H16="",I16=""),"",H16*I16) | M16: =IF(OR(L16="",K16=""),"",L16*K16) | O16: =IF(M16="","",M16-IF(N16="",0,N16)) | Q16: =IF(M16="","",IF(N16="", "Émise", IF(O16<=0, "Payée", IF(N16>0, "Partiellement payée", "Émise"))))
... A54: 50 | L54: =IF(OR(H54="",I54=""),"",H54*I54) | M54: =IF(OR(L54="",K54=""),"",L54*K54) | O54: =IF(M54="","",M54-IF(N54="",0,N54)) | Q54: =IF(M54="","",IF(N54="", "Émise", IF(O54<=0, "Payée", IF(N54>0, "Partiellement payée", "Émise"))))
A56: TOTAUX | H56: =SUMIF(H5:H54,">0") -> 0 | L56: =SUMIF(L5:L54,">0") -> 0 | M56: =SUMIF(M5:M54,">0") -> 0 | N56: =SUMIF(N5:N54,">0") -> 0 | O56: =SUMIF(O5:O54,">0") -> 0
A58: LÉGENDE : Texte bleu = saisie | Jaune = Montant encaissé | Gris = calcul auto | Vert = Payée / soldé | Rouge = reste dû / facture émise | Orange = partiel

Sheet CA_par_Client
A1: CHIFFRE D'AFFAIRES PAR CLIENT
A2: Résumé automatique par client (basé sur l'onglet Ventes).
A4: Client | B4: Nb Factures | C4: CA HT (XOF) | D4: Encaissé (XOF) | E4: Reste (XOF) | F4: % Encaissé
A5: BUNGE LIPID ENZYMTEC SDN BHD | B5: =COUNTIF(Ventes!$D$5:$D$54,A5) -> 0 | C5: =SUMIF(Ventes!$D$5:$D$54,A5,Ventes!$M$5:$M$54) -> 0 | D5: =SUMIF(Ventes!$D$5:$D$54,A5,Ventes!$N$5:$N$54) -> 0 | E5: =C5-D5 -> 0 | F5: =IF(C5=0,"",D5/C5)
A6: Client 2 | B6: =COUNTIF(Ventes!$D$5:$D$54,A6) -> 0 | C6: =SUMIF(Ventes!$D$5:$D$54,A6,Ventes!$M$5:$M$54) -> 0 | D6: =SUMIF(Ventes!$D$5:$D$54,A6,Ventes!$N$5:$N$54) -> 0 | E6: =C6-D6 -> 0 | F6: =IF(C6=0,"",D6/C6)
A7: Client 3 | B7: =COUNTIF(Ventes!$D$5:$D$54,A7) -> 0 | C7: =SUMIF(Ventes!$D$5:$D$54,A7,Ventes!$M$5:$M$54) -> 0 | D7: =SUMIF(Ventes!$D$5:$D$54,A7,Ventes!$N$5:$N$54) -> 0 | E7: =C7-D7 -> 0 | F7: =IF(C7=0,"",D7/C7)
A9: TOTAL | C9: =SUM(C5:C8) -> 0 | D9: =SUM(D5:D8) -> 0 | E9: =SUM(E5:E8) -> 0

Sheet CA_par_Produit
A1: CHIFFRE D'AFFAIRES PAR PRODUIT
A4: Produit | B4: Quantité totale (MT) | C4: CA HT (XOF) | D4: Encaissé (XOF) | E4: Reste (XOF)
A5: Shea Nut (Noir de Karité) | B5: =SUMIF(Ventes!$G$5:$G$54,A5,Ventes!$H$5:$H$54) -> 0 | C5: =SUMIF(Ventes!$G$5:$G$54,A5,Ventes!$M$5:$M$54) -> 0 | D5: =SUMIF(Ventes!$G$5:$G$54,A5,Ventes!$N$5:$N$54) -> 0 | E5: =C5-D5 -> 0
A6: Cotton Seed (Graines de Coton) | B6: =SUMIF(Ventes!$G$5:$G$54,A6,Ventes!$H$5:$H$54) -> 0 | C6: =SUMIF(Ventes!$G$5:$G$54,A6,Ventes!$M$5:$M$54) -> 0 | D6: =SUMIF(Ventes!$G$5:$G$54,A6,Ventes!$N$5:$N$54) -> 0 | E6: =C6-D6 -> 0
A7: Soja (Graines de Soja) | B7: =SUMIF(Ventes!$G$5:$G$54,A7,Ventes!$H$5:$H$54) -> 0 | C7: =SUMIF(Ventes!$G$5:$G$54,A7,Ventes!$M$5:$M$54) -> 0 | D7: =SUMIF(Ventes!$G$5:$G$54,A7,Ventes!$N$5:$N$54) -> 0 | E7: =C7-D7 -> 0
A8: Beurre de Karité Brut | B8: =SUMIF(Ventes!$G$5:$G$54,A8,Ventes!$H$5:$H$54) -> 0 | C8: =SUMIF(Ventes!$G$5:$G$54,A8,Ventes!$M$5:$M$54) -> 0 | D8: =SUMIF(Ventes!$G$5:$G$54,A8,Ventes!$N$5:$N$54) -> 0 | E8: =C8-D8 -> 0
A10: TOTAL | B10: =SUM(B5:B9) -> 0 | C10: =SUM(C5:C9) -> 0 | D10: =SUM(D5:D9) -> 0 | E10: =SUM(E5:E9) -> 0

Sheet Listes
A1: LISTES DE RÉFÉRENCE — CHIFFRE D'AFFAIRES
A2: Clients | B2: Produits | C2: Incoterms | D2: Devises | E2: Statuts Facture
A3: BUNGE LIPID ENZYMTEC SDN BHD | B3: Shea Nut (Noir de Karité) | C3: FOB | D3: USD | E3: Brouillon
A4: Client 2 | B4: Cotton Seed (Graines de Coton) | C4: CIF | D4: EUR | E4: Émise
A5: Client 3 | B5: Soja (Graines de Soja) | C5: CFR | D5: XOF | E5: Partiellement payée
B6: Beurre de Karité Brut | C6: EXW | E6: Payée
C7: FCA | E7: Annulée
A12: Ajoutez ici vos clients et produits. Les listes déroulantes des autres onglets s'appuient sur ces colonnes.
