Workbook
Name L_BL: OFFSET(Connaissements!$A$3,0,0,MAX(1,COUNTA(Connaissements!$A$3:$A$202)),1)
Name L_Bookings: OFFSET(Bookings!$A$3,0,0,MAX(1,COUNTA(Bookings!$A$3:$A$202)),1)
Name L_Clients: OFFSET(Listes!$A$2,0,0,MAX(1,COUNTA(Listes!$A$2:$A$100)),1)
Name L_Conteneurs: OFFSET(Conteneurs!$A$3,0,0,MAX(1,COUNTA(Conteneurs!$A$3:$A$1002)),1)
Name L_Contrats: OFFSET(Contrats!$A$5,0,0,MAX(1,COUNTA(Contrats!$A$5:$A$204)),1)
Name L_Etapes: OFFSET(Listes!$H$2,0,0,MAX(1,COUNTA(Listes!$H$2:$H$100)),1)
Name L_Incoterms: OFFSET(Listes!$E$2,0,0,MAX(1,COUNTA(Listes!$E$2:$E$100)),1)
Name L_Produits: OFFSET(Listes!$C$2,0,0,MAX(1,COUNTA(Listes!$C$2:$C$100)),1)
Name L_Responsables: OFFSET(Listes!$I$2,0,0,MAX(1,COUNTA(Listes!$I$2:$I$100)),1)
Name L_Transitaires: OFFSET(Listes!$D$2,0,0,MAX(1,COUNTA(Listes!$D$2:$D$100)),1)
Name L_Types_Conteneur: OFFSET(Listes!$F$2,0,0,MAX(1,COUNTA(Listes!$F$2:$F$100)),1)
Name L_Types_Cout: OFFSET(Listes!$J$2,0,0,MAX(1,COUNTA(Listes!$J$2:$J$100)),1)
Name L_Types_Document: OFFSET(Listes!$G$2,0,0,MAX(1,COUNTA(Listes!$G$2:$G$100)),1)
Name LINERS: Listes!$B$2:$B$3
Name P_AlerteDoc: Listes!$M$3
Name P_AlerteETD: Listes!$M$2

Sheet Tableau_de_bord
A1: Suivi de l'export – Tableau de bord
A2: Tout se calcule automatiquement à partir des autres feuilles : il n'y a rien à saisir ici.
A3: Date du jour | B3: =TODAY() -> 46307
A5: CONTRATS (tonnes) | D5: DOCUMENTS
A6: Quantité contractée (MT) | B6: =SUM(Contrats!$G$5:$G$204) -> 0 | D6: Documents saisis | E6: =COUNTA(Documents!$A$3:$A$1002) -> 0
A7: Quantité embarquée (MT) | B7: =SUM(Contrats!$J$5:$J$204) -> 0 | D7: Demandés, en attente de réception | E7: =COUNTIFS(Documents!$I$3:$I$1002,"Demandé (en attente)") -> 0
A8: Reste à expédier (MT) | B8: =SUM(Contrats!$K$5:$K$204) -> 0 | D8: Reçus, à envoyer par DHL | E8: =COUNTIFS(Documents!$I$3:$I$1002,"Reçu (à envoyer)") -> 0
A9: Avancement global | B9: =IF(B6=0,"",B7/B6) | D9: Envoyés par DHL | E9: =COUNTIFS(Documents!$I$3:$I$1002,"Envoyé DHL") -> 0
D10: Documents en alerte | E10: =COUNT(Documents!$M$3:$M$1002) -> 0
A11: CONTENEURS
A12: Conteneurs saisis | B12: =COUNTA(Conteneurs!$A$3:$A$1002) -> 49 | D12: ÉTAPES
A13: À empoter | B13: =COUNTIFS(Conteneurs!$M$3:$M$1002,"À empoter") -> 49 | D13: Faites | E13: =COUNTIFS(Etapes!$F$5:$F$1504,"Fait") -> 0
A14: Empoté | B14: =COUNTIFS(Conteneurs!$M$3:$M$1002,"Empoté") -> 0 | D14: À venir | E14: =COUNTIFS(Etapes!$F$5:$F$1504,"À venir") -> 0
A15: Gate-In fait | B15: =COUNTIFS(Conteneurs!$M$3:$M$1002,"Gate-In fait") -> 0 | D15: En retard | E15: =COUNTIFS(Etapes!$F$5:$F$1504,"En retard") -> 0
A16: Embarqué | B16: =COUNTIFS(Conteneurs!$M$3:$M$1002,"Embarqué") -> 0
A17: Poids net embarqué (kg) | B17: =SUMIFS(Conteneurs!$H$3:$H$1002,Conteneurs!$M$3:$M$1002,"Embarqué") -> 0 | D17: COÛTS TRANSITAIRE (FCFA)
A18: Conteneurs en alerte | B18: =COUNT(Conteneurs!$P$3:$P$1002) -> 41 | D18: Total facturé | E18: =SUM(Couts_Transitaire!$G$3:$G$602) -> 0
D19: Total payé | E19: =SUM(Couts_Transitaire!$H$3:$H$602) -> 0
A20: BOOKINGS | D20: Reste à payer | E20: =SUM(Couts_Transitaire!$I$3:$I$602) -> 0
A21: Bookings saisis | B21: =COUNTA(Bookings!$A$3:$A$202) -> 10
A22: À préparer / en cours | B22: =COUNTIFS(Bookings!$M$3:$M$202,"À préparer")+COUNTIFS(Bookings!$M$3:$M$202,"En cours") -> 10 | D22: BL
A23: En retard (ETD dépassé) | B23: =COUNTIFS(Bookings!$M$3:$M$202,"En retard (ETD dépassé)") -> 0 | D23: BL suivis | E23: =COUNTA(Connaissements!$A$3:$A$202) -> 10
A24: Embarqués complets | B24: =COUNTIFS(Bookings!$M$3:$M$202,"Embarqué complet") -> 0 | D24: BL avec un point à traiter | E24: =SUMPRODUCT((Suivi_par_BL!$O$3:$O$201<>"")*(Suivi_par_BL!$O$3:$O$201<>"OK")) -> 9
A27: Conteneurs en alerte
A28: N_Conteneur | B28: N_BL | C28: Statut | D28: Alerte | E28: ETD
A29: =IF($G29="","",INDEX(Conteneurs!$A$3:$A$1002,$G29)) -> CAAU2958722 | B29: =IF($G29="","",INDEX(Conteneurs!$B$3:$B$1002,$G29)) -> 277243348 | C29: =IF($G29="","",INDEX(Conteneurs!$M$3:$M$1002,$G29)) -> À empoter | D29: =IF($G29="","",INDEX(Conteneurs!$N$3:$N$1002,$G29)) -> Gate-In à faire (ETD proche) | E29: =IF($G29="","",INDEX(Conteneurs!$Q$3:$Q$1002,$G29)) -> 46308 | G29: =IFERROR(MATCH(1,Conteneurs!$P$3:$P$1002,0),"") -> 3
A30: =IF($G30="","",INDEX(Conteneurs!$A$3:$A$1002,$G30)) -> FTAU2081655 | B30: =IF($G30="","",INDEX(Conteneurs!$B$3:$B$1002,$G30)) -> 277243348 | C30: =IF($G30="","",INDEX(Conteneurs!$M$3:$M$1002,$G30)) -> À empoter | D30: =IF($G30="","",INDEX(Conteneurs!$N$3:$N$1002,$G30)) -> Gate-In à faire (ETD proche) | E30: =IF($G30="","",INDEX(Conteneurs!$Q$3:$Q$1002,$G30)) -> 46308 | G30: =IF($G29="","",IFERROR($G29+MATCH(1,INDEX(Conteneurs!$P$3:$P$1002,$G29+1):INDEX(Conteneurs!$P$3:$P$1002,1000),0),"")) -> 4
A31: =IF($G31="","",INDEX(Conteneurs!$A$3:$A$1002,$G31)) -> SEKU1677793 | B31: =IF($G31="","",INDEX(Conteneurs!$B$3:$B$1002,$G31)) -> 277243348 | C31: =IF($G31="","",INDEX(Conteneurs!$M$3:$M$1002,$G31)) -> À empoter | D31: =IF($G31="","",INDEX(Conteneurs!$N$3:$N$1002,$G31)) -> Gate-In à faire (ETD proche) | E31: =IF($G31="","",INDEX(Conteneurs!$Q$3:$Q$1002,$G31)) -> 46308 | G31: =IF($G30="","",IFERROR($G30+MATCH(1,INDEX(Conteneurs!$P$3:$P$1002,$G30+1):INDEX(Conteneurs!$P$3:$P$1002,1000),0),"")) -> 5
A32: =IF($G32="","",INDEX(Conteneurs!$A$3:$A$1002,$G32)) -> FTAU2076920 | B32: =IF($G32="","",INDEX(Conteneurs!$B$3:$B$1002,$G32)) -> 277243348 | C32: =IF($G32="","",INDEX(Conteneurs!$M$3:$M$1002,$G32)) -> À empoter | D32: =IF($G32="","",INDEX(Conteneurs!$N$3:$N$1002,$G32)) -> Gate-In à faire (ETD proche) | E32: =IF($G32="","",INDEX(Conteneurs!$Q$3:$Q$1002,$G32)) -> 46308 | G32: =IF($G31="","",IFERROR($G31+MATCH(1,INDEX(Conteneurs!$P$3:$P$1002,$G31+1):INDEX(Conteneurs!$P$3:$P$1002,1000),0),"")) -> 6
A33: =IF($G33="","",INDEX(Conteneurs!$A$3:$A$1002,$G33)) -> CAAU2346542 | B33: =IF($G33="","",INDEX(Conteneurs!$B$3:$B$1002,$G33)) -> 277243441 | C33: =IF($G33="","",INDEX(Conteneurs!$M$3:$M$1002,$G33)) -> À empoter | D33: =IF($G33="","",INDEX(Conteneurs!$N$3:$N$1002,$G33)) -> Gate-In à faire (ETD proche) | E33: =IF($G33="","",INDEX(Conteneurs!$Q$3:$Q$1002,$G33)) -> 46308 | G33: =IF($G32="","",IFERROR($G32+MATCH(1,INDEX(Conteneurs!$P$3:$P$1002,$G32+1):INDEX(Conteneurs!$P$3:$P$1002,1000),0),"")) -> 7
A34: =IF($G34="","",INDEX(Conteneurs!$A$3:$A$1002,$G34)) -> MRSU0518275 | B34: =IF($G34="","",INDEX(Conteneurs!$B$3:$B$1002,$G34)) -> 277243441 | C34: =IF($G34="","",INDEX(Conteneurs!$M$3:$M$1002,$G34)) -> À empoter | D34: =IF($G34="","",INDEX(Conteneurs!$N$3:$N$1002,$G34)) -> Gate-In à faire (ETD proche) | E34: =IF($G34="","",INDEX(Conteneurs!$Q$3:$Q$1002,$G34)) -> 46308 | G34: =IF($G33="","",IFERROR($G33+MATCH(1,INDEX(Conteneurs!$P$3:$P$1002,$G33+1):INDEX(Conteneurs!$P$3:$P$1002,1000),0),"")) -> 8
A35: =IF($G35="","",INDEX(Conteneurs!$A$3:$A$1002,$G35)) -> BSIU3503618 | B35: =IF($G35="","",INDEX(Conteneurs!$B$3:$B$1002,$G35)) -> 277243441 | C35: =IF($G35="","",INDEX(Conteneurs!$M$3:$M$1002,$G35)) -> À empoter | D35: =IF($G35="","",INDEX(Conteneurs!$N$3:$N$1002,$G35)) -> Gate-In à faire (ETD proche) | E35: =IF($G35="","",INDEX(Conteneurs!$Q$3:$Q$1002,$G35)) -> 46308 | G35: =IF($G34="","",IFERROR($G34+MATCH(1,INDEX(Conteneurs!$P$3:$P$1002,$G34+1):INDEX(Conteneurs!$P$3:$P$1002,1000),0),"")) -> 9
A36: =IF($G36="","",INDEX(Conteneurs!$A$3:$A$1002,$G36)) -> MRSU0681092 | B36: =IF($G36="","",INDEX(Conteneurs!$B$3:$B$1002,$G36)) -> 277243441 | C36: =IF($G36="","",INDEX(Conteneurs!$M$3:$M$1002,$G36)) -> À empoter | D36: =IF($G36="","",INDEX(Conteneurs!$N$3:$N$1002,$G36)) -> Gate-In à faire (ETD proche) | E36: =IF($G36="","",INDEX(Conteneurs!$Q$3:$Q$1002,$G36)) -> 46308 | G36: =IF($G35="","",IFERROR($G35+MATCH(1,INDEX(Conteneurs!$P$3:$P$1002,$G35+1):INDEX(Conteneurs!$P$3:$P$1002,1000),0),"")) -> 10
A37: =IF($G37="","",INDEX(Conteneurs!$A$3:$A$1002,$G37)) -> FTAU2051223 | B37: =IF($G37="","",INDEX(Conteneurs!$B$3:$B$1002,$G37)) -> 277243441 | C37: =IF($G37="","",INDEX(Conteneurs!$M$3:$M$1002,$G37)) -> À empoter | D37: =IF($G37="","",INDEX(Conteneurs!$N$3:$N$1002,$G37)) -> Gate-In à faire (ETD proche) | E37: =IF($G37="","",INDEX(Conteneurs!$Q$3:$Q$1002,$G37)) -> 46308 | G37: =IF($G36="","",IFERROR($G36+MATCH(1,INDEX(Conteneurs!$P$3:$P$1002,$G36+1):INDEX(Conteneurs!$P$3:$P$1002,1000),0),"")) -> 11
A38: =IF($G38="","",INDEX(Conteneurs!$A$3:$A$1002,$G38)) -> MRSU0614113 | B38: =IF($G38="","",INDEX(Conteneurs!$B$3:$B$1002,$G38)) -> 277243441 | C38: =IF($G38="","",INDEX(Conteneurs!$M$3:$M$1002,$G38)) -> À empoter | D38: =IF($G38="","",INDEX(Conteneurs!$N$3:$N$1002,$G38)) -> Gate-In à faire (ETD proche) | E38: =IF($G38="","",INDEX(Conteneurs!$Q$3:$Q$1002,$G38)) -> 46308 | G38: =IF($G37="","",IFERROR($G37+MATCH(1,INDEX(Conteneurs!$P$3:$P$1002,$G37+1):INDEX(Conteneurs!$P$3:$P$1002,1000),0),"")) -> 12
A39: =IF($G39="","",INDEX(Conteneurs!$A$3:$A$1002,$G39)) -> MRSU0425315 | B39: =IF($G39="","",INDEX(Conteneurs!$B$3:$B$1002,$G39)) -> 277243505 | C39: =IF($G39="","",INDEX(Conteneurs!$M$3:$M$1002,$G39)) -> À empoter | D39: =IF($G39="","",INDEX(Conteneurs!$N$3:$N$1002,$G39)) -> Gate-In à faire (ETD proche) | E39: =IF($G39="","",INDEX(Conteneurs!$Q$3:$Q$1002,$G39)) -> 46308 | G39: =IF($G38="","",IFERROR($G38+MATCH(1,INDEX(Conteneurs!$P$3:$P$1002,$G38+1):INDEX(Conteneurs!$P$3:$P$1002,1000),0),"")) -> 13
A40: =IF($G40="","",INDEX(Conteneurs!$A$3:$A$1002,$G40)) -> TIIU2260280 | B40: =IF($G40="","",INDEX(Conteneurs!$B$3:$B$1002,$G40)) -> 277243505 | C40: =IF($G40="","",INDEX(Conteneurs!$M$3:$M$1002,$G40)) -> À empoter | D40: =IF($G40="","",INDEX(Conteneurs!$N$3:$N$1002,$G40)) -> Gate-In à faire (ETD proche) | E40: =IF($G40="","",INDEX(Conteneurs!$Q$3:$Q$1002,$G40)) -> 46308 | G40: =IF($G39="","",IFERROR($G39+MATCH(1,INDEX(Conteneurs!$P$3:$P$1002,$G39+1):INDEX(Conteneurs!$P$3:$P$1002,1000),0),"")) -> 14
A41: =IF($G41="","",INDEX(Conteneurs!$A$3:$A$1002,$G41)) -> TTNU1229704 | B41: =IF($G41="","",INDEX(Conteneurs!$B$3:$B$1002,$G41)) -> 277243505 | C41: =IF($G41="","",INDEX(Conteneurs!$M$3:$M$1002,$G41)) -> À empoter | D41: =IF($G41="","",INDEX(Conteneurs!$N$3:$N$1002,$G41)) -> Gate-In à faire (ETD proche) | E41: =IF($G41="","",INDEX(Conteneurs!$Q$3:$Q$1002,$G41)) -> 46308 | G41: =IF($G40="","",IFERROR($G40+MATCH(1,INDEX(Conteneurs!$P$3:$P$1002,$G40+1):INDEX(Conteneurs!$P$3:$P$1002,1000),0),"")) -> 15
... A43: =IF($G43="","",INDEX(Conteneurs!$A$3:$A$1002,$G43)) -> TEMU0694118 | B43: =IF($G43="","",INDEX(Conteneurs!$B$3:$B$1002,$G43)) -> 277243505 | C43: =IF($G43="","",INDEX(Conteneurs!$M$3:$M$1002,$G43)) -> À empoter | D43: =IF($G43="","",INDEX(Conteneurs!$N$3:$N$1002,$G43)) -> Gate-In à faire (ETD proche) | E43: =IF($G43="","",INDEX(Conteneurs!$Q$3:$Q$1002,$G43)) -> 46308 | G43: =IF($G42="","",IFERROR($G42+MATCH(1,INDEX(Conteneurs!$P$3:$P$1002,$G42+1):INDEX(Conteneurs!$P$3:$P$1002,1000),0),"")) -> 17
A64: Documents en alerte
A65: Type_Document | B65: N_BL | C65: Date_Demande | D65: Alerte | E65: Jours_Attente
A66: =IF($G66="","",INDEX(Documents!$B$3:$B$1002,$G66)) | B66: =IF($G66="","",INDEX(Documents!$A$3:$A$1002,$G66)) | C66: =IF($G66="","",INDEX(Documents!$D$3:$D$1002,$G66)) | D66: =IF($G66="","",INDEX(Documents!$K$3:$K$1002,$G66)) | E66: =IF($G66="","",INDEX(Documents!$J$3:$J$1002,$G66)) | G66: =IFERROR(MATCH(1,Documents!$M$3:$M$1002,0),"")
A67: =IF($G67="","",INDEX(Documents!$B$3:$B$1002,$G67)) | B67: =IF($G67="","",INDEX(Documents!$A$3:$A$1002,$G67)) | C67: =IF($G67="","",INDEX(Documents!$D$3:$D$1002,$G67)) | D67: =IF($G67="","",INDEX(Documents!$K$3:$K$1002,$G67)) | E67: =IF($G67="","",INDEX(Documents!$J$3:$J$1002,$G67)) | G67: =IF($G66="","",IFERROR($G66+MATCH(1,INDEX(Documents!$M$3:$M$1002,$G66+1):INDEX(Documents!$M$3:$M$1002,1000),0),""))
A68: =IF($G68="","",INDEX(Documents!$B$3:$B$1002,$G68)) | B68: =IF($G68="","",INDEX(Documents!$A$3:$A$1002,$G68)) | C68: =IF($G68="","",INDEX(Documents!$D$3:$D$1002,$G68)) | D68: =IF($G68="","",INDEX(Documents!$K$3:$K$1002,$G68)) | E68: =IF($G68="","",INDEX(Documents!$J$3:$J$1002,$G68)) | G68: =IF($G67="","",IFERROR($G67+MATCH(1,INDEX(Documents!$M$3:$M$1002,$G67+1):INDEX(Documents!$M$3:$M$1002,1000),0),""))
A69: =IF($G69="","",INDEX(Documents!$B$3:$B$1002,$G69)) | B69: =IF($G69="","",INDEX(Documents!$A$3:$A$1002,$G69)) | C69: =IF($G69="","",INDEX(Documents!$D$3:$D$1002,$G69)) | D69: =IF($G69="","",INDEX(Documents!$K$3:$K$1002,$G69)) | E69: =IF($G69="","",INDEX(Documents!$J$3:$J$1002,$G69)) | G69: =IF($G68="","",IFERROR($G68+MATCH(1,INDEX(Documents!$M$3:$M$1002,$G68+1):INDEX(Documents!$M$3:$M$1002,1000),0),""))
A70: =IF($G70="","",INDEX(Documents!$B$3:$B$1002,$G70)) | B70: =IF($G70="","",INDEX(Documents!$A$3:$A$1002,$G70)) | C70: =IF($G70="","",INDEX(Documents!$D$3:$D$1002,$G70)) | D70: =IF($G70="","",INDEX(Documents!$K$3:$K$1002,$G70)) | E70: =IF($G70="","",INDEX(Documents!$J$3:$J$1002,$G70)) | G70: =IF($G69="","",IFERROR($G69+MATCH(1,INDEX(Documents!$M$3:$M$1002,$G69+1):INDEX(Documents!$M$3:$M$1002,1000),0),""))
A71: =IF($G71="","",INDEX(Documents!$B$3:$B$1002,$G71)) | B71: =IF($G71="","",INDEX(Documents!$A$3:$A$1002,$G71)) | C71: =IF($G71="","",INDEX(Documents!$D$3:$D$1002,$G71)) | D71: =IF($G71="","",INDEX(Documents!$K$3:$K$1002,$G71)) | E71: =IF($G71="","",INDEX(Documents!$J$3:$J$1002,$G71)) | G71: =IF($G70="","",IFERROR($G70+MATCH(1,INDEX(Documents!$M$3:$M$1002,$G70+1):INDEX(Documents!$M$3:$M$1002,1000),0),""))
A72: =IF($G72="","",INDEX(Documents!$B$3:$B$1002,$G72)) | B72: =IF($G72="","",INDEX(Documents!$A$3:$A$1002,$G72)) | C72: =IF($G72="","",INDEX(Documents!$D$3:$D$1002,$G72)) | D72: =IF($G72="","",INDEX(Documents!$K$3:$K$1002,$G72)) | E72: =IF($G72="","",INDEX(Documents!$J$3:$J$1002,$G72)) | G72: =IF($G71="","",IFERROR($G71+MATCH(1,INDEX(Documents!$M$3:$M$1002,$G71+1):INDEX(Documents!$M$3:$M$1002,1000),0),""))
A73: =IF($G73="","",INDEX(Documents!$B$3:$B$1002,$G73)) | B73: =IF($G73="","",INDEX(Documents!$A$3:$A$1002,$G73)) | C73: =IF($G73="","",INDEX(Documents!$D$3:$D$1002,$G73)) | D73: =IF($G73="","",INDEX(Documents!$K$3:$K$1002,$G73)) | E73: =IF($G73="","",INDEX(Documents!$J$3:$J$1002,$G73)) | G73: =IF($G72="","",IFERROR($G72+MATCH(1,INDEX(Documents!$M$3:$M$1002,$G72+1):INDEX(Documents!$M$3:$M$1002,1000),0),""))
A74: =IF($G74="","",INDEX(Documents!$B$3:$B$1002,$G74)) | B74: =IF($G74="","",INDEX(Documents!$A$3:$A$1002,$G74)) | C74: =IF($G74="","",INDEX(Documents!$D$3:$D$1002,$G74)) | D74: =IF($G74="","",INDEX(Documents!$K$3:$K$1002,$G74)) | E74: =IF($G74="","",INDEX(Documents!$J$3:$J$1002,$G74)) | G74: =IF($G73="","",IFERROR($G73+MATCH(1,INDEX(Documents!$M$3:$M$1002,$G73+1):INDEX(Documents!$M$3:$M$1002,1000),0),""))
A75: =IF($G75="","",INDEX(Documents!$B$3:$B$1002,$G75)) | B75: =IF($G75="","",INDEX(Documents!$A$3:$A$1002,$G75)) | C75: =IF($G75="","",INDEX(Documents!$D$3:$D$1002,$G75)) | D75: =IF($G75="","",INDEX(Documents!$K$3:$K$1002,$G75)) | E75: =IF($G75="","",INDEX(Documents!$J$3:$J$1002,$G75)) | G75: =IF($G74="","",IFERROR($G74+MATCH(1,INDEX(Documents!$M$3:$M$1002,$G74+1):INDEX(Documents!$M$3:$M$1002,1000),0),""))
A76: =IF($G76="","",INDEX(Documents!$B$3:$B$1002,$G76)) | B76: =IF($G76="","",INDEX(Documents!$A$3:$A$1002,$G76)) | C76: =IF($G76="","",INDEX(Documents!$D$3:$D$1002,$G76)) | D76: =IF($G76="","",INDEX(Documents!$K$3:$K$1002,$G76)) | E76: =IF($G76="","",INDEX(Documents!$J$3:$J$1002,$G76)) | G76: =IF($G75="","",IFERROR($G75+MATCH(1,INDEX(Documents!$M$3:$M$1002,$G75+1):INDEX(Documents!$M$3:$M$1002,1000),0),""))
A77: =IF($G77="","",INDEX(Documents!$B$3:$B$1002,$G77)) | B77: =IF($G77="","",INDEX(Documents!$A$3:$A$1002,$G77)) | C77: =IF($G77="","",INDEX(Documents!$D$3:$D$1002,$G77)) | D77: =IF($G77="","",INDEX(Documents!$K$3:$K$1002,$G77)) | E77: =IF($G77="","",INDEX(Documents!$J$3:$J$1002,$G77)) | G77: =IF($G76="","",IFERROR($G76+MATCH(1,INDEX(Documents!$M$3:$M$1002,$G76+1):INDEX(Documents!$M$3:$M$1002,1000),0),""))
A78: =IF($G78="","",INDEX(Documents!$B$3:$B$1002,$G78)) | B78: =IF($G78="","",INDEX(Documents!$A$3:$A$1002,$G78)) | C78: =IF($G78="","",INDEX(Documents!$D$3:$D$1002,$G78)) | D78: =IF($G78="","",INDEX(Documents!$K$3:$K$1002,$G78)) | E78: =IF($G78="","",INDEX(Documents!$J$3:$J$1002,$G78)) | G78: =IF($G77="","",IFERROR($G77+MATCH(1,INDEX(Documents!$M$3:$M$1002,$G77+1):INDEX(Documents!$M$3:$M$1002,1000),0),""))
... A80: =IF($G80="","",INDEX(Documents!$B$3:$B$1002,$G80)) | B80: =IF($G80="","",INDEX(Documents!$A$3:$A$1002,$G80)) | C80: =IF($G80="","",INDEX(Documents!$D$3:$D$1002,$G80)) | D80: =IF($G80="","",INDEX(Documents!$K$3:$K$1002,$G80)) | E80: =IF($G80="","",INDEX(Documents!$J$3:$J$1002,$G80)) | G80: =IF($G79="","",IFERROR($G79+MATCH(1,INDEX(Documents!$M$3:$M$1002,$G79+1):INDEX(Documents!$M$3:$M$1002,1000),0),""))
A82: Étapes en retard
A83: Nom_Etape | B83: N_BL | C83: Date_Prevue | D83: Responsable | E83: Retard_Jours
A84: =IF($G84="","",INDEX(Etapes!$B$5:$B$1504,$G84)) | B84: =IF($G84="","",INDEX(Etapes!$A$5:$A$1504,$G84)) | C84: =IF($G84="","",INDEX(Etapes!$C$5:$C$1504,$G84)) | D84: =IF($G84="","",INDEX(Etapes!$E$5:$E$1504,$G84)) | E84: =IF($G84="","",INDEX(Etapes!$G$5:$G$1504,$G84)) | G84: =IFERROR(MATCH(1,Etapes!$I$5:$I$1504,0),"")
A85: =IF($G85="","",INDEX(Etapes!$B$5:$B$1504,$G85)) | B85: =IF($G85="","",INDEX(Etapes!$A$5:$A$1504,$G85)) | C85: =IF($G85="","",INDEX(Etapes!$C$5:$C$1504,$G85)) | D85: =IF($G85="","",INDEX(Etapes!$E$5:$E$1504,$G85)) | E85: =IF($G85="","",INDEX(Etapes!$G$5:$G$1504,$G85)) | G85: =IF($G84="","",IFERROR($G84+MATCH(1,INDEX(Etapes!$I$5:$I$1504,$G84+1):INDEX(Etapes!$I$5:$I$1504,1500),0),""))
A86: =IF($G86="","",INDEX(Etapes!$B$5:$B$1504,$G86)) | B86: =IF($G86="","",INDEX(Etapes!$A$5:$A$1504,$G86)) | C86: =IF($G86="","",INDEX(Etapes!$C$5:$C$1504,$G86)) | D86: =IF($G86="","",INDEX(Etapes!$E$5:$E$1504,$G86)) | E86: =IF($G86="","",INDEX(Etapes!$G$5:$G$1504,$G86)) | G86: =IF($G85="","",IFERROR($G85+MATCH(1,INDEX(Etapes!$I$5:$I$1504,$G85+1):INDEX(Etapes!$I$5:$I$1504,1500),0),""))
A87: =IF($G87="","",INDEX(Etapes!$B$5:$B$1504,$G87)) | B87: =IF($G87="","",INDEX(Etapes!$A$5:$A$1504,$G87)) | C87: =IF($G87="","",INDEX(Etapes!$C$5:$C$1504,$G87)) | D87: =IF($G87="","",INDEX(Etapes!$E$5:$E$1504,$G87)) | E87: =IF($G87="","",INDEX(Etapes!$G$5:$G$1504,$G87)) | G87: =IF($G86="","",IFERROR($G86+MATCH(1,INDEX(Etapes!$I$5:$I$1504,$G86+1):INDEX(Etapes!$I$5:$I$1504,1500),0),""))
A88: =IF($G88="","",INDEX(Etapes!$B$5:$B$1504,$G88)) | B88: =IF($G88="","",INDEX(Etapes!$A$5:$A$1504,$G88)) | C88: =IF($G88="","",INDEX(Etapes!$C$5:$C$1504,$G88)) | D88: =IF($G88="","",INDEX(Etapes!$E$5:$E$1504,$G88)) | E88: =IF($G88="","",INDEX(Etapes!$G$5:$G$1504,$G88)) | G88: =IF($G87="","",IFERROR($G87+MATCH(1,INDEX(Etapes!$I$5:$I$1504,$G87+1):INDEX(Etapes!$I$5:$I$1504,1500),0),""))
A89: =IF($G89="","",INDEX(Etapes!$B$5:$B$1504,$G89)) | B89: =IF($G89="","",INDEX(Etapes!$A$5:$A$1504,$G89)) | C89: =IF($G89="","",INDEX(Etapes!$C$5:$C$1504,$G89)) | D89: =IF($G89="","",INDEX(Etapes!$E$5:$E$1504,$G89)) | E89: =IF($G89="","",INDEX(Etapes!$G$5:$G$1504,$G89)) | G89: =IF($G88="","",IFERROR($G88+MATCH(1,INDEX(Etapes!$I$5:$I$1504,$G88+1):INDEX(Etapes!$I$5:$I$1504,1500),0),""))
A90: =IF($G90="","",INDEX(Etapes!$B$5:$B$1504,$G90)) | B90: =IF($G90="","",INDEX(Etapes!$A$5:$A$1504,$G90)) | C90: =IF($G90="","",INDEX(Etapes!$C$5:$C$1504,$G90)) | D90: =IF($G90="","",INDEX(Etapes!$E$5:$E$1504,$G90)) | E90: =IF($G90="","",INDEX(Etapes!$G$5:$G$1504,$G90)) | G90: =IF($G89="","",IFERROR($G89+MATCH(1,INDEX(Etapes!$I$5:$I$1504,$G89+1):INDEX(Etapes!$I$5:$I$1504,1500),0),""))
A91: =IF($G91="","",INDEX(Etapes!$B$5:$B$1504,$G91)) | B91: =IF($G91="","",INDEX(Etapes!$A$5:$A$1504,$G91)) | C91: =IF($G91="","",INDEX(Etapes!$C$5:$C$1504,$G91)) | D91: =IF($G91="","",INDEX(Etapes!$E$5:$E$1504,$G91)) | E91: =IF($G91="","",INDEX(Etapes!$G$5:$G$1504,$G91)) | G91: =IF($G90="","",IFERROR($G90+MATCH(1,INDEX(Etapes!$I$5:$I$1504,$G90+1):INDEX(Etapes!$I$5:$I$1504,1500),0),""))
A92: =IF($G92="","",INDEX(Etapes!$B$5:$B$1504,$G92)) | B92: =IF($G92="","",INDEX(Etapes!$A$5:$A$1504,$G92)) | C92: =IF($G92="","",INDEX(Etapes!$C$5:$C$1504,$G92)) | D92: =IF($G92="","",INDEX(Etapes!$E$5:$E$1504,$G92)) | E92: =IF($G92="","",INDEX(Etapes!$G$5:$G$1504,$G92)) | G92: =IF($G91="","",IFERROR($G91+MATCH(1,INDEX(Etapes!$I$5:$I$1504,$G91+1):INDEX(Etapes!$I$5:$I$1504,1500),0),""))
A93: =IF($G93="","",INDEX(Etapes!$B$5:$B$1504,$G93)) | B93: =IF($G93="","",INDEX(Etapes!$A$5:$A$1504,$G93)) | C93: =IF($G93="","",INDEX(Etapes!$C$5:$C$1504,$G93)) | D93: =IF($G93="","",INDEX(Etapes!$E$5:$E$1504,$G93)) | E93: =IF($G93="","",INDEX(Etapes!$G$5:$G$1504,$G93)) | G93: =IF($G92="","",IFERROR($G92+MATCH(1,INDEX(Etapes!$I$5:$I$1504,$G92+1):INDEX(Etapes!$I$5:$I$1504,1500),0),""))
A94: =IF($G94="","",INDEX(Etapes!$B$5:$B$1504,$G94)) | B94: =IF($G94="","",INDEX(Etapes!$A$5:$A$1504,$G94)) | C94: =IF($G94="","",INDEX(Etapes!$C$5:$C$1504,$G94)) | D94: =IF($G94="","",INDEX(Etapes!$E$5:$E$1504,$G94)) | E94: =IF($G94="","",INDEX(Etapes!$G$5:$G$1504,$G94)) | G94: =IF($G93="","",IFERROR($G93+MATCH(1,INDEX(Etapes!$I$5:$I$1504,$G93+1):INDEX(Etapes!$I$5:$I$1504,1500),0),""))
A95: =IF($G95="","",INDEX(Etapes!$B$5:$B$1504,$G95)) | B95: =IF($G95="","",INDEX(Etapes!$A$5:$A$1504,$G95)) | C95: =IF($G95="","",INDEX(Etapes!$C$5:$C$1504,$G95)) | D95: =IF($G95="","",INDEX(Etapes!$E$5:$E$1504,$G95)) | E95: =IF($G95="","",INDEX(Etapes!$G$5:$G$1504,$G95)) | G95: =IF($G94="","",IFERROR($G94+MATCH(1,INDEX(Etapes!$I$5:$I$1504,$G94+1):INDEX(Etapes!$I$5:$I$1504,1500),0),""))
A96: =IF($G96="","",INDEX(Etapes!$B$5:$B$1504,$G96)) | B96: =IF($G96="","",INDEX(Etapes!$A$5:$A$1504,$G96)) | C96: =IF($G96="","",INDEX(Etapes!$C$5:$C$1504,$G96)) | D96: =IF($G96="","",INDEX(Etapes!$E$5:$E$1504,$G96)) | E96: =IF($G96="","",INDEX(Etapes!$G$5:$G$1504,$G96)) | G96: =IF($G95="","",IFERROR($G95+MATCH(1,INDEX(Etapes!$I$5:$I$1504,$G95+1):INDEX(Etapes!$I$5:$I$1504,1500),0),""))
... A98: =IF($G98="","",INDEX(Etapes!$B$5:$B$1504,$G98)) | B98: =IF($G98="","",INDEX(Etapes!$A$5:$A$1504,$G98)) | C98: =IF($G98="","",INDEX(Etapes!$C$5:$C$1504,$G98)) | D98: =IF($G98="","",INDEX(Etapes!$E$5:$E$1504,$G98)) | E98: =IF($G98="","",INDEX(Etapes!$G$5:$G$1504,$G98)) | G98: =IF($G97="","",IFERROR($G97+MATCH(1,INDEX(Etapes!$I$5:$I$1504,$G97+1):INDEX(Etapes!$I$5:$I$1504,1500),0),""))
A99: Chaque liste affiche les 15 premiers cas. Les autres se voient en filtrant la feuille concernée.

Sheet Suivi_par_BL
A1: Une ligne par BL, remplie automatiquement : il n'y a rien à saisir ici. La colonne Situation indique le premier point à traiter, par ordre de priorité : étapes en retard, contrôle du BL, conteneurs non embarqués, documents à finaliser, coûts à payer. « OK » = tout est terminé.
A2: N_BL | B2: N_Booking | C2: N_Contrat | D2: Navire | E2: ETD | F2: ETA | G2: Conteneurs_Declares | H2: Conteneurs_Saisis | I2: Conteneurs_Embarques | J2: Ecart_Poids_Net_Kg | K2: Documents | L2: Documents_Envoyes_DHL | M2: Etapes_En_Retard | N2: Reste_A_Payer_Transitaire | O2: Situation
A3: =IF(Connaissements!$A4="","",Connaissements!$A4) -> 277243441 | B3: =IF($A3="","",Connaissements!$B4) -> 277243441 | C3: =IF($A3="","",Connaissements!$G4) -> 4600063618 | D3: =IF($A3="","",IFERROR(IF(INDEX(Bookings!$D$3:$D$202,MATCH($B3,Bookings!$A$3:$A$202,0))="","",INDEX(Bookings!$D$3:$D$202,MATCH($B3,Bookings!$A$3:$A$202,0))),"")) -> RHONE MAERSK | E3: =IF($A3="","",IFERROR(IF(INDEX(Bookings!$G$3:$G$202,MATCH($B3,Bookings!$A$3:$A$202,0))="","",INDEX(Bookings!$G$3:$G$202,MATCH($B3,Bookings!$A$3:$A$202,0))),"")) -> 46308 | F3: =IF($A3="","",IFERROR(IF(INDEX(Bookings!$H$3:$H$202,MATCH($B3,Bookings!$A$3:$A$202,0))="","",INDEX(Bookings!$H$3:$H$202,MATCH($B3,Bookings!$A$3:$A$202,0))),"")) -> 46329 | G3: =IF($A3="","",IF(Connaissements!$F4="","",Connaissements!$F4)) -> 6 | H3: =IF($A3="","",Connaissements!$H4) -> 6 | I3: =IF($A3="","",COUNTIFS(Conteneurs!$B$3:$B$1002,$A3,Conteneurs!$M$3:$M$1002,"Embarqué")) -> 0 | J3: =IF($A3="","",Connaissements!$J4) -> 0 | K3: =IF($A3="","",COUNTIFS(Documents!$A$3:$A$1002,$A3)) -> 0 | L3: =IF($A3="","",COUNTIFS(Documents!$A$3:$A$1002,$A3,Documents!$I$3:$I$1002,"Envoyé DHL")) -> 0 | M3: =IF($A3="","",COUNTIFS(Etapes!$A$5:$A$1504,$A3,Etapes!$F$5:$F$1504,"En retard")) -> 0 | N3: =IF($A3="","",SUMIFS(Couts_Transitaire!$I$3:$I$602,Couts_Transitaire!$B$3:$B$602,$A3)) -> 0 | O3: =IF($A3="","",IF($M3>0,"Étapes en retard",IF(Connaissements!$K4<>"OK","Contrôle BL à corriger",IF($H3=0,"Aucun conteneur saisi",IF($I3<$H3,"Conteneurs non embarqués",IF($L3<$K3,"Documents à finaliser",IF($N3>0,"Coûts à payer","OK"))))))) -> Conteneurs non embarqués
A4: =IF(Connaissements!$A5="","",Connaissements!$A5) -> 277243505 | B4: =IF($A4="","",Connaissements!$B5) -> 277243505 | C4: =IF($A4="","",Connaissements!$G5) -> 4600063618 | D4: =IF($A4="","",IFERROR(IF(INDEX(Bookings!$D$3:$D$202,MATCH($B4,Bookings!$A$3:$A$202,0))="","",INDEX(Bookings!$D$3:$D$202,MATCH($B4,Bookings!$A$3:$A$202,0))),"")) -> RHONE MAERSK | E4: =IF($A4="","",IFERROR(IF(INDEX(Bookings!$G$3:$G$202,MATCH($B4,Bookings!$A$3:$A$202,0))="","",INDEX(Bookings!$G$3:$G$202,MATCH($B4,Bookings!$A$3:$A$202,0))),"")) -> 46308 | F4: =IF($A4="","",IFERROR(IF(INDEX(Bookings!$H$3:$H$202,MATCH($B4,Bookings!$A$3:$A$202,0))="","",INDEX(Bookings!$H$3:$H$202,MATCH($B4,Bookings!$A$3:$A$202,0))),"")) -> 46329 | G4: =IF($A4="","",IF(Connaissements!$F5="","",Connaissements!$F5)) -> 5 | H4: =IF($A4="","",Connaissements!$H5) -> 5 | I4: =IF($A4="","",COUNTIFS(Conteneurs!$B$3:$B$1002,$A4,Conteneurs!$M$3:$M$1002,"Embarqué")) -> 0 | J4: =IF($A4="","",Connaissements!$J5) -> 0 | K4: =IF($A4="","",COUNTIFS(Documents!$A$3:$A$1002,$A4)) -> 0 | L4: =IF($A4="","",COUNTIFS(Documents!$A$3:$A$1002,$A4,Documents!$I$3:$I$1002,"Envoyé DHL")) -> 0 | M4: =IF($A4="","",COUNTIFS(Etapes!$A$5:$A$1504,$A4,Etapes!$F$5:$F$1504,"En retard")) -> 0 | N4: =IF($A4="","",SUMIFS(Couts_Transitaire!$I$3:$I$602,Couts_Transitaire!$B$3:$B$602,$A4)) -> 0 | O4: =IF($A4="","",IF($M4>0,"Étapes en retard",IF(Connaissements!$K5<>"OK","Contrôle BL à corriger",IF($H4=0,"Aucun conteneur saisi",IF($I4<$H4,"Conteneurs non embarqués",IF($L4<$K4,"Documents à finaliser",IF($N4>0,"Coûts à payer","OK"))))))) -> Conteneurs non embarqués
A5: =IF(Connaissements!$A6="","",Connaissements!$A6) -> 277243596 | B5: =IF($A5="","",Connaissements!$B6) -> 277243596 | C5: =IF($A5="","",Connaissements!$G6) -> 4600063618 | D5: =IF($A5="","",IFERROR(IF(INDEX(Bookings!$D$3:$D$202,MATCH($B5,Bookings!$A$3:$A$202,0))="","",INDEX(Bookings!$D$3:$D$202,MATCH($B5,Bookings!$A$3:$A$202,0))),"")) -> RHONE MAERSK | E5: =IF($A5="","",IFERROR(IF(INDEX(Bookings!$G$3:$G$202,MATCH($B5,Bookings!$A$3:$A$202,0))="","",INDEX(Bookings!$G$3:$G$202,MATCH($B5,Bookings!$A$3:$A$202,0))),"")) -> 46308 | F5: =IF($A5="","",IFERROR(IF(INDEX(Bookings!$H$3:$H$202,MATCH($B5,Bookings!$A$3:$A$202,0))="","",INDEX(Bookings!$H$3:$H$202,MATCH($B5,Bookings!$A$3:$A$202,0))),"")) -> 46329 | G5: =IF($A5="","",IF(Connaissements!$F6="","",Connaissements!$F6)) -> 4 | H5: =IF($A5="","",Connaissements!$H6) -> 4 | I5: =IF($A5="","",COUNTIFS(Conteneurs!$B$3:$B$1002,$A5,Conteneurs!$M$3:$M$1002,"Embarqué")) -> 0 | J5: =IF($A5="","",Connaissements!$J6) -> 0 | K5: =IF($A5="","",COUNTIFS(Documents!$A$3:$A$1002,$A5)) -> 0 | L5: =IF($A5="","",COUNTIFS(Documents!$A$3:$A$1002,$A5,Documents!$I$3:$I$1002,"Envoyé DHL")) -> 0 | M5: =IF($A5="","",COUNTIFS(Etapes!$A$5:$A$1504,$A5,Etapes!$F$5:$F$1504,"En retard")) -> 0 | N5: =IF($A5="","",SUMIFS(Couts_Transitaire!$I$3:$I$602,Couts_Transitaire!$B$3:$B$602,$A5)) -> 0 | O5: =IF($A5="","",IF($M5>0,"Étapes en retard",IF(Connaissements!$K6<>"OK","Contrôle BL à corriger",IF($H5=0,"Aucun conteneur saisi",IF($I5<$H5,"Conteneurs non embarqués",IF($L5<$K5,"Documents à finaliser",IF($N5>0,"Coûts à payer","OK"))))))) -> Conteneurs non embarqués
A6: =IF(Connaissements!$A7="","",Connaissements!$A7) -> 277443031 | B6: =IF($A6="","",Connaissements!$B7) -> 277443031 | C6: =IF($A6="","",Connaissements!$G7) -> 4600063618 | D6: =IF($A6="","",IFERROR(IF(INDEX(Bookings!$D$3:$D$202,MATCH($B6,Bookings!$A$3:$A$202,0))="","",INDEX(Bookings!$D$3:$D$202,MATCH($B6,Bookings!$A$3:$A$202,0))),"")) -> RHONE MAERSK | E6: =IF($A6="","",IFERROR(IF(INDEX(Bookings!$G$3:$G$202,MATCH($B6,Bookings!$A$3:$A$202,0))="","",INDEX(Bookings!$G$3:$G$202,MATCH($B6,Bookings!$A$3:$A$202,0))),"")) -> 46309 | F6: =IF($A6="","",IFERROR(IF(INDEX(Bookings!$H$3:$H$202,MATCH($B6,Bookings!$A$3:$A$202,0))="","",INDEX(Bookings!$H$3:$H$202,MATCH($B6,Bookings!$A$3:$A$202,0))),"")) -> 46329 | G6: =IF($A6="","",IF(Connaissements!$F7="","",Connaissements!$F7)) -> 6 | H6: =IF($A6="","",Connaissements!$H7) -> 6 | I6: =IF($A6="","",COUNTIFS(Conteneurs!$B$3:$B$1002,$A6,Conteneurs!$M$3:$M$1002,"Embarqué")) -> 0 | J6: =IF($A6="","",Connaissements!$J7) -> 0 | K6: =IF($A6="","",COUNTIFS(Documents!$A$3:$A$1002,$A6)) -> 0 | L6: =IF($A6="","",COUNTIFS(Documents!$A$3:$A$1002,$A6,Documents!$I$3:$I$1002,"Envoyé DHL")) -> 0 | M6: =IF($A6="","",COUNTIFS(Etapes!$A$5:$A$1504,$A6,Etapes!$F$5:$F$1504,"En retard")) -> 0 | N6: =IF($A6="","",SUMIFS(Couts_Transitaire!$I$3:$I$602,Couts_Transitaire!$B$3:$B$602,$A6)) -> 0 | O6: =IF($A6="","",IF($M6>0,"Étapes en retard",IF(Connaissements!$K7<>"OK","Contrôle BL à corriger",IF($H6=0,"Aucun conteneur saisi",IF($I6<$H6,"Conteneurs non embarqués",IF($L6<$K6,"Documents à finaliser",IF($N6>0,"Coûts à payer","OK"))))))) -> Conteneurs non embarqués
A7: =IF(Connaissements!$A8="","",Connaissements!$A8) -> 277763418 | B7: =IF($A7="","",Connaissements!$B8) -> 277763418 | C7: =IF($A7="","",Connaissements!$G8) -> 4600063618 | D7: =IF($A7="","",IFERROR(IF(INDEX(Bookings!$D$3:$D$202,MATCH($B7,Bookings!$A$3:$A$202,0))="","",INDEX(Bookings!$D$3:$D$202,MATCH($B7,Bookings!$A$3:$A$202,0))),"")) -> RHONE MAERSK | E7: =IF($A7="","",IFERROR(IF(INDEX(Bookings!$G$3:$G$202,MATCH($B7,Bookings!$A$3:$A$202,0))="","",INDEX(Bookings!$G$3:$G$202,MATCH($B7,Bookings!$A$3:$A$202,0))),"")) -> 46309 | F7: =IF($A7="","",IFERROR(IF(INDEX(Bookings!$H$3:$H$202,MATCH($B7,Bookings!$A$3:$A$202,0))="","",INDEX(Bookings!$H$3:$H$202,MATCH($B7,Bookings!$A$3:$A$202,0))),"")) -> 46329 | G7: =IF($A7="","",IF(Connaissements!$F8="","",Connaissements!$F8)) -> 5 | H7: =IF($A7="","",Connaissements!$H8) -> 5 | I7: =IF($A7="","",COUNTIFS(Conteneurs!$B$3:$B$1002,$A7,Conteneurs!$M$3:$M$1002,"Embarqué")) -> 0 | J7: =IF($A7="","",Connaissements!$J8) -> 0 | K7: =IF($A7="","",COUNTIFS(Documents!$A$3:$A$1002,$A7)) -> 0 | L7: =IF($A7="","",COUNTIFS(Documents!$A$3:$A$1002,$A7,Documents!$I$3:$I$1002,"Envoyé DHL")) -> 0 | M7: =IF($A7="","",COUNTIFS(Etapes!$A$5:$A$1504,$A7,Etapes!$F$5:$F$1504,"En retard")) -> 0 | N7: =IF($A7="","",SUMIFS(Couts_Transitaire!$I$3:$I$602,Couts_Transitaire!$B$3:$B$602,$A7)) -> 0 | O7: =IF($A7="","",IF($M7>0,"Étapes en retard",IF(Connaissements!$K8<>"OK","Contrôle BL à corriger",IF($H7=0,"Aucun conteneur saisi",IF($I7<$H7,"Conteneurs non embarqués",IF($L7<$K7,"Documents à finaliser",IF($N7>0,"Coûts à payer","OK"))))))) -> Conteneurs non embarqués
A8: =IF(Connaissements!$A9="","",Connaissements!$A9) -> 277770098 | B8: =IF($A8="","",Connaissements!$B9) -> 277770098 | C8: =IF($A8="","",Connaissements!$G9) -> 4600063618 | D8: =IF($A8="","",IFERROR(IF(INDEX(Bookings!$D$3:$D$202,MATCH($B8,Bookings!$A$3:$A$202,0))="","",INDEX(Bookings!$D$3:$D$202,MATCH($B8,Bookings!$A$3:$A$202,0))),"")) -> RHONE MAERSK | E8: =IF($A8="","",IFERROR(IF(INDEX(Bookings!$G$3:$G$202,MATCH($B8,Bookings!$A$3:$A$202,0))="","",INDEX(Bookings!$G$3:$G$202,MATCH($B8,Bookings!$A$3:$A$202,0))),"")) -> 46309 | F8: =IF($A8="","",IFERROR(IF(INDEX(Bookings!$H$3:$H$202,MATCH($B8,Bookings!$A$3:$A$202,0))="","",INDEX(Bookings!$H$3:$H$202,MATCH($B8,Bookings!$A$3:$A$202,0))),"")) -> 46329 | G8: =IF($A8="","",IF(Connaissements!$F9="","",Connaissements!$F9)) -> 5 | H8: =IF($A8="","",Connaissements!$H9) -> 5 | I8: =IF($A8="","",COUNTIFS(Conteneurs!$B$3:$B$1002,$A8,Conteneurs!$M$3:$M$1002,"Embarqué")) -> 0 | J8: =IF($A8="","",Connaissements!$J9) -> 21400 | K8: =IF($A8="","",COUNTIFS(Documents!$A$3:$A$1002,$A8)) -> 0 | L8: =IF($A8="","",COUNTIFS(Documents!$A$3:$A$1002,$A8,Documents!$I$3:$I$1002,"Envoyé DHL")) -> 0 | M8: =IF($A8="","",COUNTIFS(Etapes!$A$5:$A$1504,$A8,Etapes!$F$5:$F$1504,"En retard")) -> 0 | N8: =IF($A8="","",SUMIFS(Couts_Transitaire!$I$3:$I$602,Couts_Transitaire!$B$3:$B$602,$A8)) -> 0 | O8: =IF($A8="","",IF($M8>0,"Étapes en retard",IF(Connaissements!$K9<>"OK","Contrôle BL à corriger",IF($H8=0,"Aucun conteneur saisi",IF($I8<$H8,"Conteneurs non embarqués",IF($L8<$K8,"Documents à finaliser",IF($N8>0,"Coûts à payer","OK"))))))) -> Contrôle BL à corriger
A9: =IF(Connaissements!$A10="","",Connaissements!$A10) -> 277770206 | B9: =IF($A9="","",Connaissements!$B10) -> 277770206 | C9: =IF($A9="","",Connaissements!$G10) -> 4600063618 | D9: =IF($A9="","",IFERROR(IF(INDEX(Bookings!$D$3:$D$202,MATCH($B9,Bookings!$A$3:$A$202,0))="","",INDEX(Bookings!$D$3:$D$202,MATCH($B9,Bookings!$A$3:$A$202,0))),"")) -> ALS CERES | E9: =IF($A9="","",IFERROR(IF(INDEX(Bookings!$G$3:$G$202,MATCH($B9,Bookings!$A$3:$A$202,0))="","",INDEX(Bookings!$G$3:$G$202,MATCH($B9,Bookings!$A$3:$A$202,0))),"")) -> 46314 | F9: =IF($A9="","",IFERROR(IF(INDEX(Bookings!$H$3:$H$202,MATCH($B9,Bookings!$A$3:$A$202,0))="","",INDEX(Bookings!$H$3:$H$202,MATCH($B9,Bookings!$A$3:$A$202,0))),"")) -> 46343 | G9: =IF($A9="","",IF(Connaissements!$F10="","",Connaissements!$F10)) -> 5 | H9: =IF($A9="","",Connaissements!$H10) -> 5 | I9: =IF($A9="","",COUNTIFS(Conteneurs!$B$3:$B$1002,$A9,Conteneurs!$M$3:$M$1002,"Embarqué")) -> 0 | J9: =IF($A9="","",Connaissements!$J10) -> 0 | K9: =IF($A9="","",COUNTIFS(Documents!$A$3:$A$1002,$A9)) -> 0 | L9: =IF($A9="","",COUNTIFS(Documents!$A$3:$A$1002,$A9,Documents!$I$3:$I$1002,"Envoyé DHL")) -> 0 | M9: =IF($A9="","",COUNTIFS(Etapes!$A$5:$A$1504,$A9,Etapes!$F$5:$F$1504,"En retard")) -> 0 | N9: =IF($A9="","",SUMIFS(Couts_Transitaire!$I$3:$I$602,Couts_Transitaire!$B$3:$B$602,$A9)) -> 0 | O9: =IF($A9="","",IF($M9>0,"Étapes en retard",IF(Connaissements!$K10<>"OK","Contrôle BL à corriger",IF($H9=0,"Aucun conteneur saisi",IF($I9<$H9,"Conteneurs non embarqués",IF($L9<$K9,"Documents à finaliser",IF($N9>0,"Coûts à payer","OK"))))))) -> Conteneurs non embarqués
A10: =IF(Connaissements!$A11="","",Connaissements!$A11) -> 278981635 | B10: =IF($A10="","",Connaissements!$B11) -> 278981635 | C10: =IF($A10="","",Connaissements!$G11) -> 4600063618 | D10: =IF($A10="","",IFERROR(IF(INDEX(Bookings!$D$3:$D$202,MATCH($B10,Bookings!$A$3:$A$202,0))="","",INDEX(Bookings!$D$3:$D$202,MATCH($B10,Bookings!$A$3:$A$202,0))),"")) -> RHONE MAERSK | E10: =IF($A10="","",IFERROR(IF(INDEX(Bookings!$G$3:$G$202,MATCH($B10,Bookings!$A$3:$A$202,0))="","",INDEX(Bookings!$G$3:$G$202,MATCH($B10,Bookings!$A$3:$A$202,0))),"")) -> 46309 | F10: =IF($A10="","",IFERROR(IF(INDEX(Bookings!$H$3:$H$202,MATCH($B10,Bookings!$A$3:$A$202,0))="","",INDEX(Bookings!$H$3:$H$202,MATCH($B10,Bookings!$A$3:$A$202,0))),"")) -> 46329 | G10: =IF($A10="","",IF(Connaissements!$F11="","",Connaissements!$F11)) -> 6 | H10: =IF($A10="","",Connaissements!$H11) -> 6 | I10: =IF($A10="","",COUNTIFS(Conteneurs!$B$3:$B$1002,$A10,Conteneurs!$M$3:$M$1002,"Embarqué")) -> 0 | J10: =IF($A10="","",Connaissements!$J11) -> 0 | K10: =IF($A10="","",COUNTIFS(Documents!$A$3:$A$1002,$A10)) -> 0 | L10: =IF($A10="","",COUNTIFS(Documents!$A$3:$A$1002,$A10,Documents!$I$3:$I$1002,"Envoyé DHL")) -> 0 | M10: =IF($A10="","",COUNTIFS(Etapes!$A$5:$A$1504,$A10,Etapes!$F$5:$F$1504,"En retard")) -> 0 | N10: =IF($A10="","",SUMIFS(Couts_Transitaire!$I$3:$I$602,Couts_Transitaire!$B$3:$B$602,$A10)) -> 0 | O10: =IF($A10="","",IF($M10>0,"Étapes en retard",IF(Connaissements!$K11<>"OK","Contrôle BL à corriger",IF($H10=0,"Aucun conteneur saisi",IF($I10<$H10,"Conteneurs non embarqués",IF($L10<$K10,"Documents à finaliser",IF($N10>0,"Coûts à payer","OK"))))))) -> Conteneurs non embarqués
A11: =IF(Connaissements!$A12="","",Connaissements!$A12) -> 279324047 | B11: =IF($A11="","",Connaissements!$B12) -> 279324047 | C11: =IF($A11="","",Connaissements!$G12) -> 4600063618 | D11: =IF($A11="","",IFERROR(IF(INDEX(Bookings!$D$3:$D$202,MATCH($B11,Bookings!$A$3:$A$202,0))="","",INDEX(Bookings!$D$3:$D$202,MATCH($B11,Bookings!$A$3:$A$202,0))),"")) -> ALS CERES | E11: =IF($A11="","",IFERROR(IF(INDEX(Bookings!$G$3:$G$202,MATCH($B11,Bookings!$A$3:$A$202,0))="","",INDEX(Bookings!$G$3:$G$202,MATCH($B11,Bookings!$A$3:$A$202,0))),"")) -> 46314 | F11: =IF($A11="","",IFERROR(IF(INDEX(Bookings!$H$3:$H$202,MATCH($B11,Bookings!$A$3:$A$202,0))="","",INDEX(Bookings!$H$3:$H$202,MATCH($B11,Bookings!$A$3:$A$202,0))),"")) -> 46343 | G11: =IF($A11="","",IF(Connaissements!$F12="","",Connaissements!$F12)) -> 1 | H11: =IF($A11="","",Connaissements!$H12) -> 1 | I11: =IF($A11="","",COUNTIFS(Conteneurs!$B$3:$B$1002,$A11,Conteneurs!$M$3:$M$1002,"Embarqué")) -> 0 | J11: =IF($A11="","",Connaissements!$J12) -> 0 | K11: =IF($A11="","",COUNTIFS(Documents!$A$3:$A$1002,$A11)) -> 0 | L11: =IF($A11="","",COUNTIFS(Documents!$A$3:$A$1002,$A11,Documents!$I$3:$I$1002,"Envoyé DHL")) -> 0 | M11: =IF($A11="","",COUNTIFS(Etapes!$A$5:$A$1504,$A11,Etapes!$F$5:$F$1504,"En retard")) -> 0 | N11: =IF($A11="","",SUMIFS(Couts_Transitaire!$I$3:$I$602,Couts_Transitaire!$B$3:$B$602,$A11)) -> 0 | O11: =IF($A11="","",IF($M11>0,"Étapes en retard",IF(Connaissements!$K12<>"OK","Contrôle BL à corriger",IF($H11=0,"Aucun conteneur saisi",IF($I11<$H11,"Conteneurs non embarqués",IF($L11<$K11,"Documents à finaliser",IF($N11>0,"Coûts à payer","OK"))))))) -> Conteneurs non embarqués
A12: =IF(Connaissements!$A13="","",Connaissements!$A13) | B12: =IF($A12="","",Connaissements!$B13) | C12: =IF($A12="","",Connaissements!$G13) | D12: =IF($A12="","",IFERROR(IF(INDEX(Bookings!$D$3:$D$202,MATCH($B12,Bookings!$A$3:$A$202,0))="","",INDEX(Bookings!$D$3:$D$202,MATCH($B12,Bookings!$A$3:$A$202,0))),"")) | E12: =IF($A12="","",IFERROR(IF(INDEX(Bookings!$G$3:$G$202,MATCH($B12,Bookings!$A$3:$A$202,0))="","",INDEX(Bookings!$G$3:$G$202,MATCH($B12,Bookings!$A$3:$A$202,0))),"")) | F12: =IF($A12="","",IFERROR(IF(INDEX(Bookings!$H$3:$H$202,MATCH($B12,Bookings!$A$3:$A$202,0))="","",INDEX(Bookings!$H$3:$H$202,MATCH($B12,Bookings!$A$3:$A$202,0))),"")) | G12: =IF($A12="","",IF(Connaissements!$F13="","",Connaissements!$F13)) | H12: =IF($A12="","",Connaissements!$H13) | I12: =IF($A12="","",COUNTIFS(Conteneurs!$B$3:$B$1002,$A12,Conteneurs!$M$3:$M$1002,"Embarqué")) | J12: =IF($A12="","",Connaissements!$J13) | K12: =IF($A12="","",COUNTIFS(Documents!$A$3:$A$1002,$A12)) | L12: =IF($A12="","",COUNTIFS(Documents!$A$3:$A$1002,$A12,Documents!$I$3:$I$1002,"Envoyé DHL")) | M12: =IF($A12="","",COUNTIFS(Etapes!$A$5:$A$1504,$A12,Etapes!$F$5:$F$1504,"En retard")) | N12: =IF($A12="","",SUMIFS(Couts_Transitaire!$I$3:$I$602,Couts_Transitaire!$B$3:$B$602,$A12)) | O12: =IF($A12="","",IF($M12>0,"Étapes en retard",IF(Connaissements!$K13<>"OK","Contrôle BL à corriger",IF($H12=0,"Aucun conteneur saisi",IF($I12<$H12,"Conteneurs non embarqués",IF($L12<$K12,"Documents à finaliser",IF($N12>0,"Coûts à payer","OK")))))))
A13: =IF(Connaissements!$A14="","",Connaissements!$A14) | B13: =IF($A13="","",Connaissements!$B14) | C13: =IF($A13="","",Connaissements!$G14) | D13: =IF($A13="","",IFERROR(IF(INDEX(Bookings!$D$3:$D$202,MATCH($B13,Bookings!$A$3:$A$202,0))="","",INDEX(Bookings!$D$3:$D$202,MATCH($B13,Bookings!$A$3:$A$202,0))),"")) | E13: =IF($A13="","",IFERROR(IF(INDEX(Bookings!$G$3:$G$202,MATCH($B13,Bookings!$A$3:$A$202,0))="","",INDEX(Bookings!$G$3:$G$202,MATCH($B13,Bookings!$A$3:$A$202,0))),"")) | F13: =IF($A13="","",IFERROR(IF(INDEX(Bookings!$H$3:$H$202,MATCH($B13,Bookings!$A$3:$A$202,0))="","",INDEX(Bookings!$H$3:$H$202,MATCH($B13,Bookings!$A$3:$A$202,0))),"")) | G13: =IF($A13="","",IF(Connaissements!$F14="","",Connaissements!$F14)) | H13: =IF($A13="","",Connaissements!$H14) | I13: =IF($A13="","",COUNTIFS(Conteneurs!$B$3:$B$1002,$A13,Conteneurs!$M$3:$M$1002,"Embarqué")) | J13: =IF($A13="","",Connaissements!$J14) | K13: =IF($A13="","",COUNTIFS(Documents!$A$3:$A$1002,$A13)) | L13: =IF($A13="","",COUNTIFS(Documents!$A$3:$A$1002,$A13,Documents!$I$3:$I$1002,"Envoyé DHL")) | M13: =IF($A13="","",COUNTIFS(Etapes!$A$5:$A$1504,$A13,Etapes!$F$5:$F$1504,"En retard")) | N13: =IF($A13="","",SUMIFS(Couts_Transitaire!$I$3:$I$602,Couts_Transitaire!$B$3:$B$602,$A13)) | O13: =IF($A13="","",IF($M13>0,"Étapes en retard",IF(Connaissements!$K14<>"OK","Contrôle BL à corriger",IF($H13=0,"Aucun conteneur saisi",IF($I13<$H13,"Conteneurs non embarqués",IF($L13<$K13,"Documents à finaliser",IF($N13>0,"Coûts à payer","OK")))))))
A14: =IF(Connaissements!$A15="","",Connaissements!$A15) | B14: =IF($A14="","",Connaissements!$B15) | C14: =IF($A14="","",Connaissements!$G15) | D14: =IF($A14="","",IFERROR(IF(INDEX(Bookings!$D$3:$D$202,MATCH($B14,Bookings!$A$3:$A$202,0))="","",INDEX(Bookings!$D$3:$D$202,MATCH($B14,Bookings!$A$3:$A$202,0))),"")) | E14: =IF($A14="","",IFERROR(IF(INDEX(Bookings!$G$3:$G$202,MATCH($B14,Bookings!$A$3:$A$202,0))="","",INDEX(Bookings!$G$3:$G$202,MATCH($B14,Bookings!$A$3:$A$202,0))),"")) | F14: =IF($A14="","",IFERROR(IF(INDEX(Bookings!$H$3:$H$202,MATCH($B14,Bookings!$A$3:$A$202,0))="","",INDEX(Bookings!$H$3:$H$202,MATCH($B14,Bookings!$A$3:$A$202,0))),"")) | G14: =IF($A14="","",IF(Connaissements!$F15="","",Connaissements!$F15)) | H14: =IF($A14="","",Connaissements!$H15) | I14: =IF($A14="","",COUNTIFS(Conteneurs!$B$3:$B$1002,$A14,Conteneurs!$M$3:$M$1002,"Embarqué")) | J14: =IF($A14="","",Connaissements!$J15) | K14: =IF($A14="","",COUNTIFS(Documents!$A$3:$A$1002,$A14)) | L14: =IF($A14="","",COUNTIFS(Documents!$A$3:$A$1002,$A14,Documents!$I$3:$I$1002,"Envoyé DHL")) | M14: =IF($A14="","",COUNTIFS(Etapes!$A$5:$A$1504,$A14,Etapes!$F$5:$F$1504,"En retard")) | N14: =IF($A14="","",SUMIFS(Couts_Transitaire!$I$3:$I$602,Couts_Transitaire!$B$3:$B$602,$A14)) | O14: =IF($A14="","",IF($M14>0,"Étapes en retard",IF(Connaissements!$K15<>"OK","Contrôle BL à corriger",IF($H14=0,"Aucun conteneur saisi",IF($I14<$H14,"Conteneurs non embarqués",IF($L14<$K14,"Documents à finaliser",IF($N14>0,"Coûts à payer","OK")))))))
... A201: =IF(Connaissements!$A202="","",Connaissements!$A202) | B201: =IF($A201="","",Connaissements!$B202) | C201: =IF($A201="","",Connaissements!$G202) | D201: =IF($A201="","",IFERROR(IF(INDEX(Bookings!$D$3:$D$202,MATCH($B201,Bookings!$A$3:$A$202,0))="","",INDEX(Bookings!$D$3:$D$202,MATCH($B201,Bookings!$A$3:$A$202,0))),"")) | E201: =IF($A201="","",IFERROR(IF(INDEX(Bookings!$G$3:$G$202,MATCH($B201,Bookings!$A$3:$A$202,0))="","",INDEX(Bookings!$G$3:$G$202,MATCH($B201,Bookings!$A$3:$A$202,0))),"")) | F201: =IF($A201="","",IFERROR(IF(INDEX(Bookings!$H$3:$H$202,MATCH($B201,Bookings!$A$3:$A$202,0))="","",INDEX(Bookings!$H$3:$H$202,MATCH($B201,Bookings!$A$3:$A$202,0))),"")) | G201: =IF($A201="","",IF(Connaissements!$F202="","",Connaissements!$F202)) | H201: =IF($A201="","",Connaissements!$H202) | I201: =IF($A201="","",COUNTIFS(Conteneurs!$B$3:$B$1002,$A201,Conteneurs!$M$3:$M$1002,"Embarqué")) | J201: =IF($A201="","",Connaissements!$J202) | K201: =IF($A201="","",COUNTIFS(Documents!$A$3:$A$1002,$A201)) | L201: =IF($A201="","",COUNTIFS(Documents!$A$3:$A$1002,$A201,Documents!$I$3:$I$1002,"Envoyé DHL")) | M201: =IF($A201="","",COUNTIFS(Etapes!$A$5:$A$1504,$A201,Etapes!$F$5:$F$1504,"En retard")) | N201: =IF($A201="","",SUMIFS(Couts_Transitaire!$I$3:$I$602,Couts_Transitaire!$B$3:$B$602,$A201)) | O201: =IF($A201="","",IF($M201>0,"Étapes en retard",IF(Connaissements!$K202<>"OK","Contrôle BL à corriger",IF($H201=0,"Aucun conteneur saisi",IF($I201<$H201,"Conteneurs non embarqués",IF($L201<$K201,"Documents à finaliser",IF($N201>0,"Coûts à payer","OK")))))))

Sheet Contrats
A1: Contrats
A2: Une ligne = un contrat de vente. Remplissez les colonnes bleues ; les colonnes grises se calculent toutes seules à partir des conteneurs embarqués. Quantités en tonnes (MT). Le prix unitaire est libre (devise et unité à votre convenance). La ligne 5 est un exemple à supprimer.
A4: N_Contrat | B4: Client | C4: Pays | D4: Produit | E4: Date_Contrat | F4: LINERS | G4: Quantite_MT | H4: Prix_Unitaire | I4: Incoterm | J4: Quantite_Embarquee_MT | K4: Reste_A_Expedier_MT | L4: Avancement | M4: Observations
A5: 4600063618 | B5: BUNGE LODERS | C5: MALAYSIA | D5: Shea Butter | F5: MAERSK | I5: FOB
J6: =IF($A6="","",SUMIFS(Conteneurs!$H$3:$H$1002,Conteneurs!$L$3:$L$1002,$A6,Conteneurs!$M$3:$M$1002,"Embarqué")/1000) | K6: =IF(OR($A6="",$G6=""),"",$G6-$J6) | L6: =IF(OR($A6="",N($G6)=0),"",$J6/$G6)
J7: =IF($A7="","",SUMIFS(Conteneurs!$H$3:$H$1002,Conteneurs!$L$3:$L$1002,$A7,Conteneurs!$M$3:$M$1002,"Embarqué")/1000) | K7: =IF(OR($A7="",$G7=""),"",$G7-$J7) | L7: =IF(OR($A7="",N($G7)=0),"",$J7/$G7)
J8: =IF($A8="","",SUMIFS(Conteneurs!$H$3:$H$1002,Conteneurs!$L$3:$L$1002,$A8,Conteneurs!$M$3:$M$1002,"Embarqué")/1000) | K8: =IF(OR($A8="",$G8=""),"",$G8-$J8) | L8: =IF(OR($A8="",N($G8)=0),"",$J8/$G8)
J9: =IF($A9="","",SUMIFS(Conteneurs!$H$3:$H$1002,Conteneurs!$L$3:$L$1002,$A9,Conteneurs!$M$3:$M$1002,"Embarqué")/1000) | K9: =IF(OR($A9="",$G9=""),"",$G9-$J9) | L9: =IF(OR($A9="",N($G9)=0),"",$J9/$G9)
J10: =IF($A10="","",SUMIFS(Conteneurs!$H$3:$H$1002,Conteneurs!$L$3:$L$1002,$A10,Conteneurs!$M$3:$M$1002,"Embarqué")/1000) | K10: =IF(OR($A10="",$G10=""),"",$G10-$J10) | L10: =IF(OR($A10="",N($G10)=0),"",$J10/$G10)
J11: =IF($A11="","",SUMIFS(Conteneurs!$H$3:$H$1002,Conteneurs!$L$3:$L$1002,$A11,Conteneurs!$M$3:$M$1002,"Embarqué")/1000) | K11: =IF(OR($A11="",$G11=""),"",$G11-$J11) | L11: =IF(OR($A11="",N($G11)=0),"",$J11/$G11)
J12: =IF($A12="","",SUMIFS(Conteneurs!$H$3:$H$1002,Conteneurs!$L$3:$L$1002,$A12,Conteneurs!$M$3:$M$1002,"Embarqué")/1000) | K12: =IF(OR($A12="",$G12=""),"",$G12-$J12) | L12: =IF(OR($A12="",N($G12)=0),"",$J12/$G12)
J13: =IF($A13="","",SUMIFS(Conteneurs!$H$3:$H$1002,Conteneurs!$L$3:$L$1002,$A13,Conteneurs!$M$3:$M$1002,"Embarqué")/1000) | K13: =IF(OR($A13="",$G13=""),"",$G13-$J13) | L13: =IF(OR($A13="",N($G13)=0),"",$J13/$G13)
J14: =IF($A14="","",SUMIFS(Conteneurs!$H$3:$H$1002,Conteneurs!$L$3:$L$1002,$A14,Conteneurs!$M$3:$M$1002,"Embarqué")/1000) | K14: =IF(OR($A14="",$G14=""),"",$G14-$J14) | L14: =IF(OR($A14="",N($G14)=0),"",$J14/$G14)
J15: =IF($A15="","",SUMIFS(Conteneurs!$H$3:$H$1002,Conteneurs!$L$3:$L$1002,$A15,Conteneurs!$M$3:$M$1002,"Embarqué")/1000) | K15: =IF(OR($A15="",$G15=""),"",$G15-$J15) | L15: =IF(OR($A15="",N($G15)=0),"",$J15/$G15)
J16: =IF($A16="","",SUMIFS(Conteneurs!$H$3:$H$1002,Conteneurs!$L$3:$L$1002,$A16,Conteneurs!$M$3:$M$1002,"Embarqué")/1000) | K16: =IF(OR($A16="",$G16=""),"",$G16-$J16) | L16: =IF(OR($A16="",N($G16)=0),"",$J16/$G16)
J17: =IF($A17="","",SUMIFS(Conteneurs!$H$3:$H$1002,Conteneurs!$L$3:$L$1002,$A17,Conteneurs!$M$3:$M$1002,"Embarqué")/1000) | K17: =IF(OR($A17="",$G17=""),"",$G17-$J17) | L17: =IF(OR($A17="",N($G17)=0),"",$J17/$G17)
... J204: =IF($A204="","",SUMIFS(Conteneurs!$H$3:$H$1002,Conteneurs!$L$3:$L$1002,$A204,Conteneurs!$M$3:$M$1002,"Embarqué")/1000) | K204: =IF(OR($A204="",$G204=""),"",$G204-$J204) | L204: =IF(OR($A204="",N($G204)=0),"",$J204/$G204)

Sheet Bookings
A1: Une ligne = un booking. Choisissez le contrat dans la liste. Colonnes grises = automatiques : conteneurs saisis, conteneurs embarqués, jours avant l'ETD et statut. Un booking est « En retard » quand son ETD est dépassé et que tous les conteneurs prévus ne sont pas embarqués. La ligne 5 est un exemple à supprimer.
A2: N_Booking | B2: N_Contrat | C2: Transitaire | D2: Navire | E2: Voyage | F2: Port_Destination | G2: ETD | H2: ETA | I2: Nb_Conteneurs_Prevus | J2: Nb_Conteneurs_Saisis | K2: Conteneurs_Embarques | L2: Jours_Avant_ETD | M2: Statut_Booking | N2: Observations
A3: 277243348 | B3: 4600063618 | C3: RAJIBER | D3: RHONE MAERSK | E3: 637E | F3: TANJUNG PELEPAS | G3: 46308 | H3: 46329 | I3: 6 | J3: =IF($A3="","",COUNTIFS(Conteneurs!$K$3:$K$1002,$A3)) -> 6 | K3: 0 | L3: =IF(G3="","",IF(G3-TODAY()<0,"Départ passé",G3-TODAY())) -> 1 | M3: =IF($A3="","",IF(AND(N($I3)>0,$K3>=$I3),"Embarqué complet",IF(AND($G3<>"",N($G3)<TODAY()),"En retard (ETD dépassé)",IF($J3=0,"À préparer","En cours")))) -> En cours
A4: 277243441 | B4: 4600063618 | C4: HAMA INTER | D4: RHONE MAERSK | E4: 637E | F4: TANJUNG PELEPAS | G4: 46308 | H4: 46329 | I4: 6 | J4: =IF($A4="","",COUNTIFS(Conteneurs!$K$3:$K$1002,$A4)) -> 6 | K4: =IF($A4="","",COUNTIFS(Conteneurs!$K$3:$K$1002,$A4,Conteneurs!$M$3:$M$1002,"Embarqué")) -> 0 | L4: =IF(OR($A4="",$G4=""),"",$G4-TODAY()) -> 1 | M4: =IF($A4="","",IF(AND(N($I4)>0,$K4>=$I4),"Embarqué complet",IF(AND($G4<>"",N($G4)<TODAY()),"En retard (ETD dépassé)",IF($J4=0,"À préparer","En cours")))) -> En cours
A5: 277243505 | B5: 4600063618 | C5: TRANS SOHA | D5: RHONE MAERSK | E5: 637E | F5: TANJUNG PELEPAS | G5: 46308 | H5: 46329 | I5: 5 | J5: =IF($A5="","",COUNTIFS(Conteneurs!$K$3:$K$1002,$A5)) -> 5 | K5: =IF($A5="","",COUNTIFS(Conteneurs!$K$3:$K$1002,$A5,Conteneurs!$M$3:$M$1002,"Embarqué")) -> 0 | L5: =IF(OR($A5="",$G5=""),"",$G5-TODAY()) -> 1 | M5: =IF($A5="","",IF(AND(N($I5)>0,$K5>=$I5),"Embarqué complet",IF(AND($G5<>"",N($G5)<TODAY()),"En retard (ETD dépassé)",IF($J5=0,"À préparer","En cours")))) -> En cours
A6: 277243596 | B6: 4600063618 | C6: HAMA INTER | D6: RHONE MAERSK | E6: 637E | F6: TANJUNG PELEPAS | G6: 46308 | H6: 46329 | I6: 4 | J6: =IF($A6="","",COUNTIFS(Conteneurs!$K$3:$K$1002,$A6)) -> 4 | K6: =IF($A6="","",COUNTIFS(Conteneurs!$K$3:$K$1002,$A6,Conteneurs!$M$3:$M$1002,"Embarqué")) -> 0 | L6: =IF(OR($A6="",$G6=""),"",$G6-TODAY()) -> 1 | M6: =IF($A6="","",IF(AND(N($I6)>0,$K6>=$I6),"Embarqué complet",IF(AND($G6<>"",N($G6)<TODAY()),"En retard (ETD dépassé)",IF($J6=0,"À préparer","En cours")))) -> En cours
A7: 277443031 | B7: 4600063618 | C7: HAMA INTER | D7: RHONE MAERSK | E7: 637E | F7: TANJUNG PELEPAS | G7: 46309 | H7: 46329 | I7: 6 | J7: =IF($A7="","",COUNTIFS(Conteneurs!$K$3:$K$1002,$A7)) -> 6 | K7: =IF($A7="","",COUNTIFS(Conteneurs!$K$3:$K$1002,$A7,Conteneurs!$M$3:$M$1002,"Embarqué")) -> 0 | L7: =IF(OR($A7="",$G7=""),"",$G7-TODAY()) -> 2 | M7: =IF($A7="","",IF(AND(N($I7)>0,$K7>=$I7),"Embarqué complet",IF(AND($G7<>"",N($G7)<TODAY()),"En retard (ETD dépassé)",IF($J7=0,"À préparer","En cours")))) -> En cours
A8: 277763418 | B8: 4600063618 | C8: RAJIBER | D8: RHONE MAERSK | E8: 637E | F8: TANJUNG PELEPAS | G8: 46309 | H8: 46329 | I8: 5 | J8: =IF($A8="","",COUNTIFS(Conteneurs!$K$3:$K$1002,$A8)) -> 5 | K8: =IF($A8="","",COUNTIFS(Conteneurs!$K$3:$K$1002,$A8,Conteneurs!$M$3:$M$1002,"Embarqué")) -> 0 | L8: =IF(OR($A8="",$G8=""),"",$G8-TODAY()) -> 2 | M8: =IF($A8="","",IF(AND(N($I8)>0,$K8>=$I8),"Embarqué complet",IF(AND($G8<>"",N($G8)<TODAY()),"En retard (ETD dépassé)",IF($J8=0,"À préparer","En cours")))) -> En cours
A9: 277770098 | B9: 4600063618 | C9: HAMA INTER | D9: RHONE MAERSK | E9: 637E | F9: TANJUNG PELEPAS | G9: 46309 | H9: 46329 | I9: 5 | J9: =IF($A9="","",COUNTIFS(Conteneurs!$K$3:$K$1002,$A9)) -> 5 | K9: =IF($A9="","",COUNTIFS(Conteneurs!$K$3:$K$1002,$A9,Conteneurs!$M$3:$M$1002,"Embarqué")) -> 0 | L9: =IF(OR($A9="",$G9=""),"",$G9-TODAY()) -> 2 | M9: =IF($A9="","",IF(AND(N($I9)>0,$K9>=$I9),"Embarqué complet",IF(AND($G9<>"",N($G9)<TODAY()),"En retard (ETD dépassé)",IF($J9=0,"À préparer","En cours")))) -> En cours
A10: 277770206 | B10: 4600063618 | C10: TRANS SOHA | D10: ALS CERES | E10: 640E | F10: TANJUNG PELEPAS | G10: 46314 | H10: 46343 | I10: 5 | J10: =IF($A10="","",COUNTIFS(Conteneurs!$K$3:$K$1002,$A10)) -> 5 | K10: =IF($A10="","",COUNTIFS(Conteneurs!$K$3:$K$1002,$A10,Conteneurs!$M$3:$M$1002,"Embarqué")) -> 0 | L10: =IF(OR($A10="",$G10=""),"",$G10-TODAY()) -> 7 | M10: =IF($A10="","",IF(AND(N($I10)>0,$K10>=$I10),"Embarqué complet",IF(AND($G10<>"",N($G10)<TODAY()),"En retard (ETD dépassé)",IF($J10=0,"À préparer","En cours")))) -> En cours
A11: 278981635 | B11: 4600063618 | C11: RAJIBER | D11: RHONE MAERSK | E11: 637E | F11: TANJUNG PELEPAS | G11: 46309 | H11: 46329 | I11: 6 | J11: =IF($A11="","",COUNTIFS(Conteneurs!$K$3:$K$1002,$A11)) -> 6 | K11: =IF($A11="","",COUNTIFS(Conteneurs!$K$3:$K$1002,$A11,Conteneurs!$M$3:$M$1002,"Embarqué")) -> 0 | L11: =IF(OR($A11="",$G11=""),"",$G11-TODAY()) -> 2 | M11: =IF($A11="","",IF(AND(N($I11)>0,$K11>=$I11),"Embarqué complet",IF(AND($G11<>"",N($G11)<TODAY()),"En retard (ETD dépassé)",IF($J11=0,"À préparer","En cours")))) -> En cours
A12: 279324047 | B12: 4600063618 | C12: HAMA INTER | D12: ALS CERES | E12: 640E | F12: TANJUNG PELEPAS | G12: 46314 | H12: 46343 | I12: 1 | J12: =IF($A12="","",COUNTIFS(Conteneurs!$K$3:$K$1002,$A12)) -> 1 | K12: =IF($A12="","",COUNTIFS(Conteneurs!$K$3:$K$1002,$A12,Conteneurs!$M$3:$M$1002,"Embarqué")) -> 0 | L12: =IF(OR($A12="",$G12=""),"",$G12-TODAY()) -> 7 | M12: =IF($A12="","",IF(AND(N($I12)>0,$K12>=$I12),"Embarqué complet",IF(AND($G12<>"",N($G12)<TODAY()),"En retard (ETD dépassé)",IF($J12=0,"À préparer","En cours")))) -> En cours
J13: =IF($A13="","",COUNTIFS(Conteneurs!$K$3:$K$1002,$A13)) | K13: =IF($A13="","",COUNTIFS(Conteneurs!$K$3:$K$1002,$A13,Conteneurs!$M$3:$M$1002,"Embarqué")) | L13: =IF(OR($A13="",$G13=""),"",$G13-TODAY()) | M13: =IF($A13="","",IF(AND(N($I13)>0,$K13>=$I13),"Embarqué complet",IF(AND($G13<>"",N($G13)<TODAY()),"En retard (ETD dépassé)",IF($J13=0,"À préparer","En cours"))))
J14: =IF($A14="","",COUNTIFS(Conteneurs!$K$3:$K$1002,$A14)) | K14: =IF($A14="","",COUNTIFS(Conteneurs!$K$3:$K$1002,$A14,Conteneurs!$M$3:$M$1002,"Embarqué")) | L14: =IF(OR($A14="",$G14=""),"",$G14-TODAY()) | M14: =IF($A14="","",IF(AND(N($I14)>0,$K14>=$I14),"Embarqué complet",IF(AND($G14<>"",N($G14)<TODAY()),"En retard (ETD dépassé)",IF($J14=0,"À préparer","En cours"))))
J15: =IF($A15="","",COUNTIFS(Conteneurs!$K$3:$K$1002,$A15)) | K15: =IF($A15="","",COUNTIFS(Conteneurs!$K$3:$K$1002,$A15,Conteneurs!$M$3:$M$1002,"Embarqué")) | L15: =IF(OR($A15="",$G15=""),"",$G15-TODAY()) | M15: =IF($A15="","",IF(AND(N($I15)>0,$K15>=$I15),"Embarqué complet",IF(AND($G15<>"",N($G15)<TODAY()),"En retard (ETD dépassé)",IF($J15=0,"À préparer","En cours"))))
J16: =IF($A16="","",COUNTIFS(Conteneurs!$K$3:$K$1002,$A16)) | K16: =IF($A16="","",COUNTIFS(Conteneurs!$K$3:$K$1002,$A16,Conteneurs!$M$3:$M$1002,"Embarqué")) | L16: =IF(OR($A16="",$G16=""),"",$G16-TODAY()) | M16: =IF($A16="","",IF(AND(N($I16)>0,$K16>=$I16),"Embarqué complet",IF(AND($G16<>"",N($G16)<TODAY()),"En retard (ETD dépassé)",IF($J16=0,"À préparer","En cours"))))
J17: =IF($A17="","",COUNTIFS(Conteneurs!$K$3:$K$1002,$A17)) | K17: =IF($A17="","",COUNTIFS(Conteneurs!$K$3:$K$1002,$A17,Conteneurs!$M$3:$M$1002,"Embarqué")) | L17: =IF(OR($A17="",$G17=""),"",$G17-TODAY()) | M17: =IF($A17="","",IF(AND(N($I17)>0,$K17>=$I17),"Embarqué complet",IF(AND($G17<>"",N($G17)<TODAY()),"En retard (ETD dépassé)",IF($J17=0,"À préparer","En cours"))))
J18: =IF($A18="","",COUNTIFS(Conteneurs!$K$3:$K$1002,$A18)) | K18: =IF($A18="","",COUNTIFS(Conteneurs!$K$3:$K$1002,$A18,Conteneurs!$M$3:$M$1002,"Embarqué")) | L18: =IF(OR($A18="",$G18=""),"",$G18-TODAY()) | M18: =IF($A18="","",IF(AND(N($I18)>0,$K18>=$I18),"Embarqué complet",IF(AND($G18<>"",N($G18)<TODAY()),"En retard (ETD dépassé)",IF($J18=0,"À préparer","En cours"))))
J19: =IF($A19="","",COUNTIFS(Conteneurs!$K$3:$K$1002,$A19)) | K19: =IF($A19="","",COUNTIFS(Conteneurs!$K$3:$K$1002,$A19,Conteneurs!$M$3:$M$1002,"Embarqué")) | L19: =IF(OR($A19="",$G19=""),"",$G19-TODAY()) | M19: =IF($A19="","",IF(AND(N($I19)>0,$K19>=$I19),"Embarqué complet",IF(AND($G19<>"",N($G19)<TODAY()),"En retard (ETD dépassé)",IF($J19=0,"À préparer","En cours"))))
J20: =IF($A20="","",COUNTIFS(Conteneurs!$K$3:$K$1002,$A20)) | K20: =IF($A20="","",COUNTIFS(Conteneurs!$K$3:$K$1002,$A20,Conteneurs!$M$3:$M$1002,"Embarqué")) | L20: =IF(OR($A20="",$G20=""),"",$G20-TODAY()) | M20: =IF($A20="","",IF(AND(N($I20)>0,$K20>=$I20),"Embarqué complet",IF(AND($G20<>"",N($G20)<TODAY()),"En retard (ETD dépassé)",IF($J20=0,"À préparer","En cours"))))
J21: =IF($A21="","",COUNTIFS(Conteneurs!$K$3:$K$1002,$A21)) | K21: =IF($A21="","",COUNTIFS(Conteneurs!$K$3:$K$1002,$A21,Conteneurs!$M$3:$M$1002,"Embarqué")) | L21: =IF(OR($A21="",$G21=""),"",$G21-TODAY()) | M21: =IF($A21="","",IF(AND(N($I21)>0,$K21>=$I21),"Embarqué complet",IF(AND($G21<>"",N($G21)<TODAY()),"En retard (ETD dépassé)",IF($J21=0,"À préparer","En cours"))))
J22: =IF($A22="","",COUNTIFS(Conteneurs!$K$3:$K$1002,$A22)) | K22: =IF($A22="","",COUNTIFS(Conteneurs!$K$3:$K$1002,$A22,Conteneurs!$M$3:$M$1002,"Embarqué")) | L22: =IF(OR($A22="",$G22=""),"",$G22-TODAY()) | M22: =IF($A22="","",IF(AND(N($I22)>0,$K22>=$I22),"Embarqué complet",IF(AND($G22<>"",N($G22)<TODAY()),"En retard (ETD dépassé)",IF($J22=0,"À préparer","En cours"))))
J23: =IF($A23="","",COUNTIFS(Conteneurs!$K$3:$K$1002,$A23)) | K23: =IF($A23="","",COUNTIFS(Conteneurs!$K$3:$K$1002,$A23,Conteneurs!$M$3:$M$1002,"Embarqué")) | L23: =IF(OR($A23="",$G23=""),"",$G23-TODAY()) | M23: =IF($A23="","",IF(AND(N($I23)>0,$K23>=$I23),"Embarqué complet",IF(AND($G23<>"",N($G23)<TODAY()),"En retard (ETD dépassé)",IF($J23=0,"À préparer","En cours"))))
J24: =IF($A24="","",COUNTIFS(Conteneurs!$K$3:$K$1002,$A24)) | K24: =IF($A24="","",COUNTIFS(Conteneurs!$K$3:$K$1002,$A24,Conteneurs!$M$3:$M$1002,"Embarqué")) | L24: =IF(OR($A24="",$G24=""),"",$G24-TODAY()) | M24: =IF($A24="","",IF(AND(N($I24)>0,$K24>=$I24),"Embarqué complet",IF(AND($G24<>"",N($G24)<TODAY()),"En retard (ETD dépassé)",IF($J24=0,"À préparer","En cours"))))
... J202: =IF($A202="","",COUNTIFS(Conteneurs!$K$3:$K$1002,$A202)) | K202: =IF($A202="","",COUNTIFS(Conteneurs!$K$3:$K$1002,$A202,Conteneurs!$M$3:$M$1002,"Embarqué")) | L202: =IF(OR($A202="",$G202=""),"",$G202-TODAY()) | M202: =IF($A202="","",IF(AND(N($I202)>0,$K202>=$I202),"Embarqué complet",IF(AND($G202<>"",N($G202)<TODAY()),"En retard (ETD dépassé)",IF($J202=0,"À préparer","En cours"))))

Sheet Connaissements
A1: Une ligne = un BL. Saisissez les poids et le nombre de conteneurs déclarés sur le BL (colonnes bleues) : la feuille les compare automatiquement aux conteneurs réellement saisis. Poids en kg. Colonne « Controle_BL » : OK si tout concorde, sinon elle indique l'écart. La ligne 5 est un exemple à supprimer.
A2: N_BL | B2: N_Booking | C2: Date_BL | D2: Poids_Brut_Declare_Kg | E2: Poids_Net_Declare_Kg | F2: Nb_Conteneurs_Declares | G2: N_Contrat | H2: Nb_Conteneurs_Saisis | I2: Poids_Net_Conteneurs_Kg | J2: Ecart_Poids_Net_Kg | K2: Controle_BL | L2: Observations
A3: 277243348 | B3: 277243348 | D3: 126140 | E3: 125300 | F3: 6 | G3: =IF($B3="","",IFERROR(INDEX(Bookings!$B$3:$B$202,MATCH($B3,Bookings!$A$3:$A$202,0)),"")) -> 4600063618 | H3: =IF($A3="","",COUNTIFS(Conteneurs!$B$3:$B$1002,$A3)) -> 6 | I3: =IF($A3="","",SUMIFS(Conteneurs!$H$3:$H$1002,Conteneurs!$B$3:$B$1002,$A3)) -> 125300 | J3: =IF(OR($A3="",$E3=""),"",$E3-$I3) -> 0 | K3: =IF($A3="","",IF(AND(OR($F3="",$H3=$F3),OR($E3="",ABS(N($E3)-$I3)<=0.5)),"OK","Écart : "&TRIM(IF(AND($F3<>"",$H3<>$F3),"nb conteneurs ","")&IF(AND($E3<>"",ABS(N($E3)-$I3)>0.5),"poids net","")))) -> OK
A4: 277243441 | B4: 277243441 | D4: 128940 | E4: 128340 | F4: 6 | G4: =IF($B4="","",IFERROR(INDEX(Bookings!$B$3:$B$202,MATCH($B4,Bookings!$A$3:$A$202,0)),"")) -> 4600063618 | H4: =IF($A4="","",COUNTIFS(Conteneurs!$B$3:$B$1002,$A4)) -> 6 | I4: =IF($A4="","",SUMIFS(Conteneurs!$H$3:$H$1002,Conteneurs!$B$3:$B$1002,$A4)) -> 128340 | J4: =IF(OR($A4="",$E4=""),"",$E4-$I4) -> 0 | K4: =IF($A4="","",IF(AND(OR($F4="",$H4=$F4),OR($E4="",ABS(N($E4)-$I4)<=0.5)),"OK","Écart : "&TRIM(IF(AND($F4<>"",$H4<>$F4),"nb conteneurs ","")&IF(AND($E4<>"",ABS(N($E4)-$I4)>0.5),"poids net","")))) -> OK
A5: 277243505 | B5: 277243505 | D5: 107460 | E5: 106760 | F5: 5 | G5: =IF($B5="","",IFERROR(INDEX(Bookings!$B$3:$B$202,MATCH($B5,Bookings!$A$3:$A$202,0)),"")) -> 4600063618 | H5: =IF($A5="","",COUNTIFS(Conteneurs!$B$3:$B$1002,$A5)) -> 5 | I5: =IF($A5="","",SUMIFS(Conteneurs!$H$3:$H$1002,Conteneurs!$B$3:$B$1002,$A5)) -> 106760 | J5: =IF(OR($A5="",$E5=""),"",$E5-$I5) -> 0 | K5: =IF($A5="","",IF(AND(OR($F5="",$H5=$F5),OR($E5="",ABS(N($E5)-$I5)<=0.5)),"OK","Écart : "&TRIM(IF(AND($F5<>"",$H5<>$F5),"nb conteneurs ","")&IF(AND($E5<>"",ABS(N($E5)-$I5)>0.5),"poids net","")))) -> OK
A6: 277243596 | B6: 277243596 | D6: 86160 | E6: 85600 | F6: 4 | G6: =IF($B6="","",IFERROR(INDEX(Bookings!$B$3:$B$202,MATCH($B6,Bookings!$A$3:$A$202,0)),"")) -> 4600063618 | H6: =IF($A6="","",COUNTIFS(Conteneurs!$B$3:$B$1002,$A6)) -> 4 | I6: =IF($A6="","",SUMIFS(Conteneurs!$H$3:$H$1002,Conteneurs!$B$3:$B$1002,$A6)) -> 85600 | J6: =IF(OR($A6="",$E6=""),"",$E6-$I6) -> 0 | K6: =IF($A6="","",IF(AND(OR($F6="",$H6=$F6),OR($E6="",ABS(N($E6)-$I6)<=0.5)),"OK","Écart : "&TRIM(IF(AND($F6<>"",$H6<>$F6),"nb conteneurs ","")&IF(AND($E6<>"",ABS(N($E6)-$I6)>0.5),"poids net","")))) -> OK
A7: 277443031 | B7: 277443031 | D7: 128600 | E7: 127760 | F7: 6 | G7: =IF($B7="","",IFERROR(INDEX(Bookings!$B$3:$B$202,MATCH($B7,Bookings!$A$3:$A$202,0)),"")) -> 4600063618 | H7: =IF($A7="","",COUNTIFS(Conteneurs!$B$3:$B$1002,$A7)) -> 6 | I7: =IF($A7="","",SUMIFS(Conteneurs!$H$3:$H$1002,Conteneurs!$B$3:$B$1002,$A7)) -> 127760 | J7: =IF(OR($A7="",$E7=""),"",$E7-$I7) -> 0 | K7: =IF($A7="","",IF(AND(OR($F7="",$H7=$F7),OR($E7="",ABS(N($E7)-$I7)<=0.5)),"OK","Écart : "&TRIM(IF(AND($F7<>"",$H7<>$F7),"nb conteneurs ","")&IF(AND($E7<>"",ABS(N($E7)-$I7)>0.5),"poids net","")))) -> OK
A8: 277763418 | B8: 277763418 | D8: 107720 | E8: 107020 | F8: 5 | G8: =IF($B8="","",IFERROR(INDEX(Bookings!$B$3:$B$202,MATCH($B8,Bookings!$A$3:$A$202,0)),"")) -> 4600063618 | H8: =IF($A8="","",COUNTIFS(Conteneurs!$B$3:$B$1002,$A8)) -> 5 | I8: =IF($A8="","",SUMIFS(Conteneurs!$H$3:$H$1002,Conteneurs!$B$3:$B$1002,$A8)) -> 107020 | J8: =IF(OR($A8="",$E8=""),"",$E8-$I8) -> 0 | K8: =IF($A8="","",IF(AND(OR($F8="",$H8=$F8),OR($E8="",ABS(N($E8)-$I8)<=0.5)),"OK","Écart : "&TRIM(IF(AND($F8<>"",$H8<>$F8),"nb conteneurs ","")&IF(AND($E8<>"",ABS(N($E8)-$I8)>0.5),"poids net","")))) -> OK
A9: 277770098 | B9: 277770098 | D9: 128880 | E9: 128040 | F9: 5 | G9: =IF($B9="","",IFERROR(INDEX(Bookings!$B$3:$B$202,MATCH($B9,Bookings!$A$3:$A$202,0)),"")) -> 4600063618 | H9: =IF($A9="","",COUNTIFS(Conteneurs!$B$3:$B$1002,$A9)) -> 5 | I9: =IF($A9="","",SUMIFS(Conteneurs!$H$3:$H$1002,Conteneurs!$B$3:$B$1002,$A9)) -> 106640 | J9: =IF(OR($A9="",$E9=""),"",$E9-$I9) -> 21400 | K9: =IF($A9="","",IF(AND(OR($F9="",$H9=$F9),OR($E9="",ABS(N($E9)-$I9)<=0.5)),"OK","Écart : "&TRIM(IF(AND($F9<>"",$H9<>$F9),"nb conteneurs ","")&IF(AND($E9<>"",ABS(N($E9)-$I9)>0.5),"poids net","")))) -> Écart : poids net | L9: L'ecart est mis sur le BL 279324047
A10: 277770206 | B10: 277770206 | D10: 105040 | E10: 104340 | F10: 5 | G10: =IF($B10="","",IFERROR(INDEX(Bookings!$B$3:$B$202,MATCH($B10,Bookings!$A$3:$A$202,0)),"")) -> 4600063618 | H10: =IF($A10="","",COUNTIFS(Conteneurs!$B$3:$B$1002,$A10)) -> 5 | I10: =IF($A10="","",SUMIFS(Conteneurs!$H$3:$H$1002,Conteneurs!$B$3:$B$1002,$A10)) -> 104340 | J10: =IF(OR($A10="",$E10=""),"",$E10-$I10) -> 0 | K10: =IF($A10="","",IF(AND(OR($F10="",$H10=$F10),OR($E10="",ABS(N($E10)-$I10)<=0.5)),"OK","Écart : "&TRIM(IF(AND($F10<>"",$H10<>$F10),"nb conteneurs ","")&IF(AND($E10<>"",ABS(N($E10)-$I10)>0.5),"poids net","")))) -> OK
A11: 278981635 | B11: 278981635 | D11: 127620 | E11: 126780 | F11: 6 | G11: =IF($B11="","",IFERROR(INDEX(Bookings!$B$3:$B$202,MATCH($B11,Bookings!$A$3:$A$202,0)),"")) -> 4600063618 | H11: =IF($A11="","",COUNTIFS(Conteneurs!$B$3:$B$1002,$A11)) -> 6 | I11: =IF($A11="","",SUMIFS(Conteneurs!$H$3:$H$1002,Conteneurs!$B$3:$B$1002,$A11)) -> 126780 | J11: =IF(OR($A11="",$E11=""),"",$E11-$I11) -> 0 | K11: =IF($A11="","",IF(AND(OR($F11="",$H11=$F11),OR($E11="",ABS(N($E11)-$I11)<=0.5)),"OK","Écart : "&TRIM(IF(AND($F11<>"",$H11<>$F11),"nb conteneurs ","")&IF(AND($E11<>"",ABS(N($E11)-$I11)>0.5),"poids net","")))) -> OK
A12: 279324047 | B12: 279324047 | D12: 32620 | E12: 21400 | F12: 1 | G12: =IF($B12="","",IFERROR(INDEX(Bookings!$B$3:$B$202,MATCH($B12,Bookings!$A$3:$A$202,0)),"")) -> 4600063618 | H12: =IF($A12="","",COUNTIFS(Conteneurs!$B$3:$B$1002,$A12)) -> 1 | I12: =IF($A12="","",SUMIFS(Conteneurs!$H$3:$H$1002,Conteneurs!$B$3:$B$1002,$A12)) -> 21400 | J12: =IF(OR($A12="",$E12=""),"",$E12-$I12) -> 0 | K12: =IF($A12="","",IF(AND(OR($F12="",$H12=$F12),OR($E12="",ABS(N($E12)-$I12)<=0.5)),"OK","Écart : "&TRIM(IF(AND($F12<>"",$H12<>$F12),"nb conteneurs ","")&IF(AND($E12<>"",ABS(N($E12)-$I12)>0.5),"poids net","")))) -> OK
G13: =IF($B13="","",IFERROR(INDEX(Bookings!$B$3:$B$202,MATCH($B13,Bookings!$A$3:$A$202,0)),"")) | H13: =IF($A13="","",COUNTIFS(Conteneurs!$B$3:$B$1002,$A13)) | I13: =IF($A13="","",SUMIFS(Conteneurs!$H$3:$H$1002,Conteneurs!$B$3:$B$1002,$A13)) | J13: =IF(OR($A13="",$E13=""),"",$E13-$I13) | K13: =IF($A13="","",IF(AND(OR($F13="",$H13=$F13),OR($E13="",ABS(N($E13)-$I13)<=0.5)),"OK","Écart : "&TRIM(IF(AND($F13<>"",$H13<>$F13),"nb conteneurs ","")&IF(AND($E13<>"",ABS(N($E13)-$I13)>0.5),"poids net",""))))
G14: =IF($B14="","",IFERROR(INDEX(Bookings!$B$3:$B$202,MATCH($B14,Bookings!$A$3:$A$202,0)),"")) | H14: =IF($A14="","",COUNTIFS(Conteneurs!$B$3:$B$1002,$A14)) | I14: =IF($A14="","",SUMIFS(Conteneurs!$H$3:$H$1002,Conteneurs!$B$3:$B$1002,$A14)) | J14: =IF(OR($A14="",$E14=""),"",$E14-$I14) | K14: =IF($A14="","",IF(AND(OR($F14="",$H14=$F14),OR($E14="",ABS(N($E14)-$I14)<=0.5)),"OK","Écart : "&TRIM(IF(AND($F14<>"",$H14<>$F14),"nb conteneurs ","")&IF(AND($E14<>"",ABS(N($E14)-$I14)>0.5),"poids net",""))))
G15: =IF($B15="","",IFERROR(INDEX(Bookings!$B$3:$B$202,MATCH($B15,Bookings!$A$3:$A$202,0)),"")) | H15: =IF($A15="","",COUNTIFS(Conteneurs!$B$3:$B$1002,$A15)) | I15: =IF($A15="","",SUMIFS(Conteneurs!$H$3:$H$1002,Conteneurs!$B$3:$B$1002,$A15)) | J15: =IF(OR($A15="",$E15=""),"",$E15-$I15)
G16: =IF($B16="","",IFERROR(INDEX(Bookings!$B$3:$B$202,MATCH($B16,Bookings!$A$3:$A$202,0)),"")) | H16: =IF($A16="","",COUNTIFS(Conteneurs!$B$3:$B$1002,$A16)) | I16: =IF($A16="","",SUMIFS(Conteneurs!$H$3:$H$1002,Conteneurs!$B$3:$B$1002,$A16)) | J16: =IF(OR($A16="",$E16=""),"",$E16-$I16) | K16: =IF($A16="","",IF(AND(OR($F16="",$H16=$F16),OR($E16="",ABS(N($E16)-$I16)<=0.5)),"OK","Écart : "&TRIM(IF(AND($F16<>"",$H16<>$F16),"nb conteneurs ","")&IF(AND($E16<>"",ABS(N($E16)-$I16)>0.5),"poids net",""))))
G17: =IF($B17="","",IFERROR(INDEX(Bookings!$B$3:$B$202,MATCH($B17,Bookings!$A$3:$A$202,0)),"")) | H17: =IF($A17="","",COUNTIFS(Conteneurs!$B$3:$B$1002,$A17)) | I17: =IF($A17="","",SUMIFS(Conteneurs!$H$3:$H$1002,Conteneurs!$B$3:$B$1002,$A17)) | J17: =IF(OR($A17="",$E17=""),"",$E17-$I17) | K17: =IF($A17="","",IF(AND(OR($F17="",$H17=$F17),OR($E17="",ABS(N($E17)-$I17)<=0.5)),"OK","Écart : "&TRIM(IF(AND($F17<>"",$H17<>$F17),"nb conteneurs ","")&IF(AND($E17<>"",ABS(N($E17)-$I17)>0.5),"poids net",""))))
G18: =IF($B18="","",IFERROR(INDEX(Bookings!$B$3:$B$202,MATCH($B18,Bookings!$A$3:$A$202,0)),"")) | H18: =IF($A18="","",COUNTIFS(Conteneurs!$B$3:$B$1002,$A18)) | I18: =IF($A18="","",SUMIFS(Conteneurs!$H$3:$H$1002,Conteneurs!$B$3:$B$1002,$A18)) | J18: =IF(OR($A18="",$E18=""),"",$E18-$I18) | K18: =IF($A18="","",IF(AND(OR($F18="",$H18=$F18),OR($E18="",ABS(N($E18)-$I18)<=0.5)),"OK","Écart : "&TRIM(IF(AND($F18<>"",$H18<>$F18),"nb conteneurs ","")&IF(AND($E18<>"",ABS(N($E18)-$I18)>0.5),"poids net",""))))
G19: =IF($B19="","",IFERROR(INDEX(Bookings!$B$3:$B$202,MATCH($B19,Bookings!$A$3:$A$202,0)),"")) | H19: =IF($A19="","",COUNTIFS(Conteneurs!$B$3:$B$1002,$A19)) | I19: =IF($A19="","",SUMIFS(Conteneurs!$H$3:$H$1002,Conteneurs!$B$3:$B$1002,$A19)) | J19: =IF(OR($A19="",$E19=""),"",$E19-$I19) | K19: =IF($A19="","",IF(AND(OR($F19="",$H19=$F19),OR($E19="",ABS(N($E19)-$I19)<=0.5)),"OK","Écart : "&TRIM(IF(AND($F19<>"",$H19<>$F19),"nb conteneurs ","")&IF(AND($E19<>"",ABS(N($E19)-$I19)>0.5),"poids net",""))))
G20: =IF($B20="","",IFERROR(INDEX(Bookings!$B$3:$B$202,MATCH($B20,Bookings!$A$3:$A$202,0)),"")) | H20: =IF($A20="","",COUNTIFS(Conteneurs!$B$3:$B$1002,$A20)) | I20: =IF($A20="","",SUMIFS(Conteneurs!$H$3:$H$1002,Conteneurs!$B$3:$B$1002,$A20)) | J20: =IF(OR($A20="",$E20=""),"",$E20-$I20) | K20: =IF($A20="","",IF(AND(OR($F20="",$H20=$F20),OR($E20="",ABS(N($E20)-$I20)<=0.5)),"OK","Écart : "&TRIM(IF(AND($F20<>"",$H20<>$F20),"nb conteneurs ","")&IF(AND($E20<>"",ABS(N($E20)-$I20)>0.5),"poids net",""))))
G21: =IF($B21="","",IFERROR(INDEX(Bookings!$B$3:$B$202,MATCH($B21,Bookings!$A$3:$A$202,0)),"")) | H21: =IF($A21="","",COUNTIFS(Conteneurs!$B$3:$B$1002,$A21)) | I21: =IF($A21="","",SUMIFS(Conteneurs!$H$3:$H$1002,Conteneurs!$B$3:$B$1002,$A21)) | J21: =IF(OR($A21="",$E21=""),"",$E21-$I21) | K21: =IF($A21="","",IF(AND(OR($F21="",$H21=$F21),OR($E21="",ABS(N($E21)-$I21)<=0.5)),"OK","Écart : "&TRIM(IF(AND($F21<>"",$H21<>$F21),"nb conteneurs ","")&IF(AND($E21<>"",ABS(N($E21)-$I21)>0.5),"poids net",""))))
G22: =IF($B22="","",IFERROR(INDEX(Bookings!$B$3:$B$202,MATCH($B22,Bookings!$A$3:$A$202,0)),"")) | H22: =IF($A22="","",COUNTIFS(Conteneurs!$B$3:$B$1002,$A22)) | I22: =IF($A22="","",SUMIFS(Conteneurs!$H$3:$H$1002,Conteneurs!$B$3:$B$1002,$A22)) | J22: =IF(OR($A22="",$E22=""),"",$E22-$I22) | K22: =IF($A22="","",IF(AND(OR($F22="",$H22=$F22),OR($E22="",ABS(N($E22)-$I22)<=0.5)),"OK","Écart : "&TRIM(IF(AND($F22<>"",$H22<>$F22),"nb conteneurs ","")&IF(AND($E22<>"",ABS(N($E22)-$I22)>0.5),"poids net",""))))
G23: =IF($B23="","",IFERROR(INDEX(Bookings!$B$3:$B$202,MATCH($B23,Bookings!$A$3:$A$202,0)),"")) | H23: =IF($A23="","",COUNTIFS(Conteneurs!$B$3:$B$1002,$A23)) | I23: =IF($A23="","",SUMIFS(Conteneurs!$H$3:$H$1002,Conteneurs!$B$3:$B$1002,$A23)) | J23: =IF(OR($A23="",$E23=""),"",$E23-$I23) | K23: =IF($A23="","",IF(AND(OR($F23="",$H23=$F23),OR($E23="",ABS(N($E23)-$I23)<=0.5)),"OK","Écart : "&TRIM(IF(AND($F23<>"",$H23<>$F23),"nb conteneurs ","")&IF(AND($E23<>"",ABS(N($E23)-$I23)>0.5),"poids net",""))))
G24: =IF($B24="","",IFERROR(INDEX(Bookings!$B$3:$B$202,MATCH($B24,Bookings!$A$3:$A$202,0)),"")) | H24: =IF($A24="","",COUNTIFS(Conteneurs!$B$3:$B$1002,$A24)) | I24: =IF($A24="","",SUMIFS(Conteneurs!$H$3:$H$1002,Conteneurs!$B$3:$B$1002,$A24)) | J24: =IF(OR($A24="",$E24=""),"",$E24-$I24) | K24: =IF($A24="","",IF(AND(OR($F24="",$H24=$F24),OR($E24="",ABS(N($E24)-$I24)<=0.5)),"OK","Écart : "&TRIM(IF(AND($F24<>"",$H24<>$F24),"nb conteneurs ","")&IF(AND($E24<>"",ABS(N($E24)-$I24)>0.5),"poids net",""))))
G25: =IF($B25="","",IFERROR(INDEX(Bookings!$B$3:$B$202,MATCH($B25,Bookings!$A$3:$A$202,0)),"")) | H25: =IF($A25="","",COUNTIFS(Conteneurs!$B$3:$B$1002,$A25)) | I25: =IF($A25="","",SUMIFS(Conteneurs!$H$3:$H$1002,Conteneurs!$B$3:$B$1002,$A25)) | J25: =IF(OR($A25="",$E25=""),"",$E25-$I25) | K25: =IF($A25="","",IF(AND(OR($F25="",$H25=$F25),OR($E25="",ABS(N($E25)-$I25)<=0.5)),"OK","Écart : "&TRIM(IF(AND($F25<>"",$H25<>$F25),"nb conteneurs ","")&IF(AND($E25<>"",ABS(N($E25)-$I25)>0.5),"poids net",""))))
G26: =IF($B26="","",IFERROR(INDEX(Bookings!$B$3:$B$202,MATCH($B26,Bookings!$A$3:$A$202,0)),"")) | H26: =IF($A26="","",COUNTIFS(Conteneurs!$B$3:$B$1002,$A26)) | I26: =IF($A26="","",SUMIFS(Conteneurs!$H$3:$H$1002,Conteneurs!$B$3:$B$1002,$A26)) | J26: =IF(OR($A26="",$E26=""),"",$E26-$I26) | K26: =IF($A26="","",IF(AND(OR($F26="",$H26=$F26),OR($E26="",ABS(N($E26)-$I26)<=0.5)),"OK","Écart : "&TRIM(IF(AND($F26<>"",$H26<>$F26),"nb conteneurs ","")&IF(AND($E26<>"",ABS(N($E26)-$I26)>0.5),"poids net",""))))
G27: =IF($B27="","",IFERROR(INDEX(Bookings!$B$3:$B$202,MATCH($B27,Bookings!$A$3:$A$202,0)),"")) | H27: =IF($A27="","",COUNTIFS(Conteneurs!$B$3:$B$1002,$A27)) | I27: =IF($A27="","",SUMIFS(Conteneurs!$H$3:$H$1002,Conteneurs!$B$3:$B$1002,$A27)) | J27: =IF(OR($A27="",$E27=""),"",$E27-$I27) | K27: =IF($A27="","",IF(AND(OR($F27="",$H27=$F27),OR($E27="",ABS(N($E27)-$I27)<=0.5)),"OK","Écart : "&TRIM(IF(AND($F27<>"",$H27<>$F27),"nb conteneurs ","")&IF(AND($E27<>"",ABS(N($E27)-$I27)>0.5),"poids net",""))))
... G202: =IF($B202="","",IFERROR(INDEX(Bookings!$B$3:$B$202,MATCH($B202,Bookings!$A$3:$A$202,0)),"")) | H202: =IF($A202="","",COUNTIFS(Conteneurs!$B$3:$B$1002,$A202)) | I202: =IF($A202="","",SUMIFS(Conteneurs!$H$3:$H$1002,Conteneurs!$B$3:$B$1002,$A202)) | J202: =IF(OR($A202="",$E202=""),"",$E202-$I202) | K202: =IF($A202="","",IF(AND(OR($F202="",$H202=$F202),OR($E202="",ABS(N($E202)-$I202)<=0.5)),"OK","Écart : "&TRIM(IF(AND($F202<>"",$H202<>$F202),"nb conteneurs ","")&IF(AND($E202<>"",ABS(N($E202)-$I202)>0.5),"poids net",""))))

Sheet Conteneurs
A1: Une ligne = un conteneur. Renseignez les dates au fur et à mesure : le statut se met à jour tout seul (À empoter → Empoté → Gate-In fait → Embarqué). La colonne Alerte signale : ETD dépassé sans embarquement, Gate-In à faire quand l'ETD est proche, poids net manquant. Poids en kg. La ligne 5 est un exemple à supprimer.
A2: N_Conteneur | B2: N_BL | C2: N_Plomb | D2: Type_Conteneur | E2: Date_Empotage | F2: Date_GateIn | G2: Date_Embarquement | H2: Poids_Net_Kg | I2: Tare Weight | J2: Poids_Brut_Kg | K2: N_Booking | L2: N_Contrat | M2: Statut_Conteneur | N2: Alerte | O2: Observations | P2: flag | Q2: etd
A3: MRSU0979277 | B3: 277243348 | C3: ML-GH0085102 | D3: 20' FLEXITANK | H3: =J3-I3 -> 21080 | I3: 15280 | J3: 36360 | K3: =IF($B3="","",IFERROR(INDEX(Connaissements!$B$3:$B$202,MATCH($B3,Connaissements!$A$3:$A$202,0)),"")) -> 277243348 | L3: =IF($B3="","",IFERROR(INDEX(Connaissements!$G$3:$G$202,MATCH($B3,Connaissements!$A$3:$A$202,0)),"")) -> 4600063618 | M3: =IF($A3="","",IF($G3<>"","Embarqué",IF($F3<>"","Gate-In fait",IF($E3<>"","Empoté","À empoter")))) -> À empoter | N3: =IF(OR($A3="",$G3<>""),"",IF(AND($Q3<>"",N($Q3)<TODAY()),"RETARD : ETD dépassé, pas embarqué",IF(AND($Q3<>"",N($Q3)-TODAY()<=P_AlerteETD,$F3=""),"Gate-In à faire (ETD proche)",IF(AND($E3<>"",$H3=""),"Poids net à saisir",""))))
A4: CAAU2421733 | B4: 277243348 | C4: ML-GH0085101 | D4: 20' FLEXITANK | H4: =J4-I4 -> 21040 | I4: 15000 | J4: 36040 | K4: =IF($B4="","",IFERROR(INDEX(Connaissements!$B$3:$B$202,MATCH($B4,Connaissements!$A$3:$A$202,0)),"")) -> 277243348 | L4: =IF($B4="","",IFERROR(INDEX(Connaissements!$G$3:$G$202,MATCH($B4,Connaissements!$A$3:$A$202,0)),"")) -> 4600063618 | M4: =IF($A4="","",IF($G4<>"","Embarqué",IF($F4<>"","Gate-In fait",IF($E4<>"","Empoté","À empoter")))) -> À empoter | N4: =IF(OR($A4="",$G4<>""),"",IF(AND($Q4<>"",N($Q4)<TODAY()),"RETARD : ETD dépassé, pas embarqué",IF(AND($Q4<>"",N($Q4)-TODAY()<=P_AlerteETD,$F4=""),"Gate-In à faire (ETD proche)",IF(AND($E4<>"",$H4=""),"Poids net à saisir",""))))
A5: CAAU2958722 | B5: 277243348 | C5: ML-GH0085105 | D5: 20' FLEXITANK | H5: =J5-I5 -> 20500 | I5: 15200 | J5: 35700 | K5: =IF($B5="","",IFERROR(INDEX(Connaissements!$B$3:$B$202,MATCH($B5,Connaissements!$A$3:$A$202,0)),"")) -> 277243348 | L5: =IF($B5="","",IFERROR(INDEX(Connaissements!$G$3:$G$202,MATCH($B5,Connaissements!$A$3:$A$202,0)),"")) -> 4600063618 | M5: =IF($A5="","",IF($G5<>"","Embarqué",IF($F5<>"","Gate-In fait",IF($E5<>"","Empoté","À empoter")))) -> À empoter | N5: =IF(OR($A5="",$G5<>""),"",IF(AND($Q5<>"",N($Q5)<TODAY()),"RETARD : ETD dépassé, pas embarqué",IF(AND($Q5<>"",N($Q5)-TODAY()<=P_AlerteETD,$F5=""),"Gate-In à faire (ETD proche)",IF(AND($E5<>"",$H5=""),"Poids net à saisir","")))) -> Gate-In à faire (ETD proche) | P5: =IF($N5<>"",1,"") -> 1 | Q5: =IF($K5="","",IFERROR(IF(INDEX(Bookings!$G$3:$G$202,MATCH($K5,Bookings!$A$3:$A$202,0))="","",INDEX(Bookings!$G$3:$G$202,MATCH($K5,Bookings!$A$3:$A$202,0))),"")) -> 46308
A6: FTAU2081655 | B6: 277243348 | C6: ML-GH0085062 | D6: 20' FLEXITANK | H6: =J6-I6 -> 20520 | I6: 15560 | J6: 36080 | K6: =IF($B6="","",IFERROR(INDEX(Connaissements!$B$3:$B$202,MATCH($B6,Connaissements!$A$3:$A$202,0)),"")) -> 277243348 | L6: =IF($B6="","",IFERROR(INDEX(Connaissements!$G$3:$G$202,MATCH($B6,Connaissements!$A$3:$A$202,0)),"")) -> 4600063618 | M6: =IF($A6="","",IF($G6<>"","Embarqué",IF($F6<>"","Gate-In fait",IF($E6<>"","Empoté","À empoter")))) -> À empoter | N6: =IF(OR($A6="",$G6<>""),"",IF(AND($Q6<>"",N($Q6)<TODAY()),"RETARD : ETD dépassé, pas embarqué",IF(AND($Q6<>"",N($Q6)-TODAY()<=P_AlerteETD,$F6=""),"Gate-In à faire (ETD proche)",IF(AND($E6<>"",$H6=""),"Poids net à saisir","")))) -> Gate-In à faire (ETD proche) | P6: =IF($N6<>"",1,"") -> 1 | Q6: =IF($K6="","",IFERROR(IF(INDEX(Bookings!$G$3:$G$202,MATCH($K6,Bookings!$A$3:$A$202,0))="","",INDEX(Bookings!$G$3:$G$202,MATCH($K6,Bookings!$A$3:$A$202,0))),"")) -> 46308
A7: SEKU1677793 | B7: 277243348 | C7: ML-GH0084319 | D7: 20' FLEXITANK | H7: =J7-I7 -> 21340 | I7: 15100 | J7: 36440 | K7: =IF($B7="","",IFERROR(INDEX(Connaissements!$B$3:$B$202,MATCH($B7,Connaissements!$A$3:$A$202,0)),"")) -> 277243348 | L7: =IF($B7="","",IFERROR(INDEX(Connaissements!$G$3:$G$202,MATCH($B7,Connaissements!$A$3:$A$202,0)),"")) -> 4600063618 | M7: =IF($A7="","",IF($G7<>"","Embarqué",IF($F7<>"","Gate-In fait",IF($E7<>"","Empoté","À empoter")))) -> À empoter | N7: =IF(OR($A7="",$G7<>""),"",IF(AND($Q7<>"",N($Q7)<TODAY()),"RETARD : ETD dépassé, pas embarqué",IF(AND($Q7<>"",N($Q7)-TODAY()<=P_AlerteETD,$F7=""),"Gate-In à faire (ETD proche)",IF(AND($E7<>"",$H7=""),"Poids net à saisir","")))) -> Gate-In à faire (ETD proche) | P7: =IF($N7<>"",1,"") -> 1 | Q7: =IF($K7="","",IFERROR(IF(INDEX(Bookings!$G$3:$G$202,MATCH($K7,Bookings!$A$3:$A$202,0))="","",INDEX(Bookings!$G$3:$G$202,MATCH($K7,Bookings!$A$3:$A$202,0))),"")) -> 46308
A8: FTAU2076920 | B8: 277243348 | C8: ML-GH0084318 | D8: 20' FLEXITANK | H8: =J8-I8 -> 20820 | I8: 15560 | J8: 36380 | K8: =IF($B8="","",IFERROR(INDEX(Connaissements!$B$3:$B$202,MATCH($B8,Connaissements!$A$3:$A$202,0)),"")) -> 277243348 | L8: =IF($B8="","",IFERROR(INDEX(Connaissements!$G$3:$G$202,MATCH($B8,Connaissements!$A$3:$A$202,0)),"")) -> 4600063618 | M8: =IF($A8="","",IF($G8<>"","Embarqué",IF($F8<>"","Gate-In fait",IF($E8<>"","Empoté","À empoter")))) -> À empoter | N8: =IF(OR($A8="",$G8<>""),"",IF(AND($Q8<>"",N($Q8)<TODAY()),"RETARD : ETD dépassé, pas embarqué",IF(AND($Q8<>"",N($Q8)-TODAY()<=P_AlerteETD,$F8=""),"Gate-In à faire (ETD proche)",IF(AND($E8<>"",$H8=""),"Poids net à saisir","")))) -> Gate-In à faire (ETD proche) | P8: =IF($N8<>"",1,"") -> 1 | Q8: =IF($K8="","",IFERROR(IF(INDEX(Bookings!$G$3:$G$202,MATCH($K8,Bookings!$A$3:$A$202,0))="","",INDEX(Bookings!$G$3:$G$202,MATCH($K8,Bookings!$A$3:$A$202,0))),"")) -> 46308
A9: CAAU2346542 | B9: 277243441 | C9: ML-GH0085086 | D9: 20' FLEXITANK | H9: =J9-I9 -> 21500 | I9: 14080 | J9: 35580 | K9: =IF($B9="","",IFERROR(INDEX(Connaissements!$B$3:$B$202,MATCH($B9,Connaissements!$A$3:$A$202,0)),"")) -> 277243441 | L9: =IF($B9="","",IFERROR(INDEX(Connaissements!$G$3:$G$202,MATCH($B9,Connaissements!$A$3:$A$202,0)),"")) -> 4600063618 | M9: =IF($A9="","",IF($G9<>"","Embarqué",IF($F9<>"","Gate-In fait",IF($E9<>"","Empoté","À empoter")))) -> À empoter | N9: =IF(OR($A9="",$G9<>""),"",IF(AND($Q9<>"",N($Q9)<TODAY()),"RETARD : ETD dépassé, pas embarqué",IF(AND($Q9<>"",N($Q9)-TODAY()<=P_AlerteETD,$F9=""),"Gate-In à faire (ETD proche)",IF(AND($E9<>"",$H9=""),"Poids net à saisir","")))) -> Gate-In à faire (ETD proche) | P9: =IF($N9<>"",1,"") -> 1 | Q9: =IF($K9="","",IFERROR(IF(INDEX(Bookings!$G$3:$G$202,MATCH($K9,Bookings!$A$3:$A$202,0))="","",INDEX(Bookings!$G$3:$G$202,MATCH($K9,Bookings!$A$3:$A$202,0))),"")) -> 46308
A10: MRSU0518275 | B10: 277243441 | C10: ML-GH0085090 | D10: 20' FLEXITANK | H10: =J10-I10 -> 21280 | I10: 16120 | J10: 37400 | K10: =IF($B10="","",IFERROR(INDEX(Connaissements!$B$3:$B$202,MATCH($B10,Connaissements!$A$3:$A$202,0)),"")) -> 277243441 | L10: =IF($B10="","",IFERROR(INDEX(Connaissements!$G$3:$G$202,MATCH($B10,Connaissements!$A$3:$A$202,0)),"")) -> 4600063618 | M10: =IF($A10="","",IF($G10<>"","Embarqué",IF($F10<>"","Gate-In fait",IF($E10<>"","Empoté","À empoter")))) -> À empoter | N10: =IF(OR($A10="",$G10<>""),"",IF(AND($Q10<>"",N($Q10)<TODAY()),"RETARD : ETD dépassé, pas embarqué",IF(AND($Q10<>"",N($Q10)-TODAY()<=P_AlerteETD,$F10=""),"Gate-In à faire (ETD proche)",IF(AND($E10<>"",$H10=""),"Poids net à saisir","")))) -> Gate-In à faire (ETD proche) | P10: =IF($N10<>"",1,"") -> 1 | Q10: =IF($K10="","",IFERROR(IF(INDEX(Bookings!$G$3:$G$202,MATCH($K10,Bookings!$A$3:$A$202,0))="","",INDEX(Bookings!$G$3:$G$202,MATCH($K10,Bookings!$A$3:$A$202,0))),"")) -> 46308
A11: BSIU3503618 | B11: 277243441 | C11: ML-GH0085082 | D11: 20' FLEXITANK | H11: =J11-I11 -> 21440 | I11: 11200 | J11: 32640 | K11: =IF($B11="","",IFERROR(INDEX(Connaissements!$B$3:$B$202,MATCH($B11,Connaissements!$A$3:$A$202,0)),"")) -> 277243441 | L11: =IF($B11="","",IFERROR(INDEX(Connaissements!$G$3:$G$202,MATCH($B11,Connaissements!$A$3:$A$202,0)),"")) -> 4600063618 | M11: =IF($A11="","",IF($G11<>"","Embarqué",IF($F11<>"","Gate-In fait",IF($E11<>"","Empoté","À empoter")))) -> À empoter | N11: =IF(OR($A11="",$G11<>""),"",IF(AND($Q11<>"",N($Q11)<TODAY()),"RETARD : ETD dépassé, pas embarqué",IF(AND($Q11<>"",N($Q11)-TODAY()<=P_AlerteETD,$F11=""),"Gate-In à faire (ETD proche)",IF(AND($E11<>"",$H11=""),"Poids net à saisir","")))) -> Gate-In à faire (ETD proche) | P11: =IF($N11<>"",1,"") -> 1 | Q11: =IF($K11="","",IFERROR(IF(INDEX(Bookings!$G$3:$G$202,MATCH($K11,Bookings!$A$3:$A$202,0))="","",INDEX(Bookings!$G$3:$G$202,MATCH($K11,Bookings!$A$3:$A$202,0))),"")) -> 46308
A12: MRSU0681092 | B12: 277243441 | C12: ML-GH0085084 | D12: 20' FLEXITANK | H12: =J12-I12 -> 21460 | I12: 14300 | J12: 35760 | K12: =IF($B12="","",IFERROR(INDEX(Connaissements!$B$3:$B$202,MATCH($B12,Connaissements!$A$3:$A$202,0)),"")) -> 277243441 | L12: =IF($B12="","",IFERROR(INDEX(Connaissements!$G$3:$G$202,MATCH($B12,Connaissements!$A$3:$A$202,0)),"")) -> 4600063618 | M12: =IF($A12="","",IF($G12<>"","Embarqué",IF($F12<>"","Gate-In fait",IF($E12<>"","Empoté","À empoter")))) -> À empoter | N12: =IF(OR($A12="",$G12<>""),"",IF(AND($Q12<>"",N($Q12)<TODAY()),"RETARD : ETD dépassé, pas embarqué",IF(AND($Q12<>"",N($Q12)-TODAY()<=P_AlerteETD,$F12=""),"Gate-In à faire (ETD proche)",IF(AND($E12<>"",$H12=""),"Poids net à saisir","")))) -> Gate-In à faire (ETD proche) | P12: =IF($N12<>"",1,"") -> 1 | Q12: =IF($K12="","",IFERROR(IF(INDEX(Bookings!$G$3:$G$202,MATCH($K12,Bookings!$A$3:$A$202,0))="","",INDEX(Bookings!$G$3:$G$202,MATCH($K12,Bookings!$A$3:$A$202,0))),"")) -> 46308
A13: FTAU2051223 | B13: 277243441 | C13: ML-GH0085083 | D13: 20' FLEXITANK | H13: =J13-I13 -> 21380 | I13: 14160 | J13: 35540 | K13: =IF($B13="","",IFERROR(INDEX(Connaissements!$B$3:$B$202,MATCH($B13,Connaissements!$A$3:$A$202,0)),"")) -> 277243441 | L13: =IF($B13="","",IFERROR(INDEX(Connaissements!$G$3:$G$202,MATCH($B13,Connaissements!$A$3:$A$202,0)),"")) -> 4600063618 | M13: =IF($A13="","",IF($G13<>"","Embarqué",IF($F13<>"","Gate-In fait",IF($E13<>"","Empoté","À empoter")))) -> À empoter | N13: =IF(OR($A13="",$G13<>""),"",IF(AND($Q13<>"",N($Q13)<TODAY()),"RETARD : ETD dépassé, pas embarqué",IF(AND($Q13<>"",N($Q13)-TODAY()<=P_AlerteETD,$F13=""),"Gate-In à faire (ETD proche)",IF(AND($E13<>"",$H13=""),"Poids net à saisir","")))) -> Gate-In à faire (ETD proche) | P13: =IF($N13<>"",1,"") -> 1 | Q13: =IF($K13="","",IFERROR(IF(INDEX(Bookings!$G$3:$G$202,MATCH($K13,Bookings!$A$3:$A$202,0))="","",INDEX(Bookings!$G$3:$G$202,MATCH($K13,Bookings!$A$3:$A$202,0))),"")) -> 46308
A14: MRSU0614113 | B14: 277243441 | C14: ML-GH0085087 | D14: 20' FLEXITANK | H14: =J14-I14 -> 21280 | I14: 16340 | J14: 37620 | K14: =IF($B14="","",IFERROR(INDEX(Connaissements!$B$3:$B$202,MATCH($B14,Connaissements!$A$3:$A$202,0)),"")) -> 277243441 | L14: =IF($B14="","",IFERROR(INDEX(Connaissements!$G$3:$G$202,MATCH($B14,Connaissements!$A$3:$A$202,0)),"")) -> 4600063618 | M14: =IF($A14="","",IF($G14<>"","Embarqué",IF($F14<>"","Gate-In fait",IF($E14<>"","Empoté","À empoter")))) -> À empoter | N14: =IF(OR($A14="",$G14<>""),"",IF(AND($Q14<>"",N($Q14)<TODAY()),"RETARD : ETD dépassé, pas embarqué",IF(AND($Q14<>"",N($Q14)-TODAY()<=P_AlerteETD,$F14=""),"Gate-In à faire (ETD proche)",IF(AND($E14<>"",$H14=""),"Poids net à saisir","")))) -> Gate-In à faire (ETD proche) | P14: =IF($N14<>"",1,"") -> 1 | Q14: =IF($K14="","",IFERROR(IF(INDEX(Bookings!$G$3:$G$202,MATCH($K14,Bookings!$A$3:$A$202,0))="","",INDEX(Bookings!$G$3:$G$202,MATCH($K14,Bookings!$A$3:$A$202,0))),"")) -> 46308
A15: MRSU0425315 | B15: 277243505 | C15: ML-GH0085099 | D15: 20' FLEXITANK | H15: =J15-I15 -> 21440 | I15: 41800 | J15: 63240 | K15: =IF($B15="","",IFERROR(INDEX(Connaissements!$B$3:$B$202,MATCH($B15,Connaissements!$A$3:$A$202,0)),"")) -> 277243505 | L15: =IF($B15="","",IFERROR(INDEX(Connaissements!$G$3:$G$202,MATCH($B15,Connaissements!$A$3:$A$202,0)),"")) -> 4600063618 | M15: =IF($A15="","",IF($G15<>"","Embarqué",IF($F15<>"","Gate-In fait",IF($E15<>"","Empoté","À empoter")))) -> À empoter | N15: =IF(OR($A15="",$G15<>""),"",IF(AND($Q15<>"",N($Q15)<TODAY()),"RETARD : ETD dépassé, pas embarqué",IF(AND($Q15<>"",N($Q15)-TODAY()<=P_AlerteETD,$F15=""),"Gate-In à faire (ETD proche)",IF(AND($E15<>"",$H15=""),"Poids net à saisir","")))) -> Gate-In à faire (ETD proche) | P15: =IF($N15<>"",1,"") -> 1 | Q15: =IF($K15="","",IFERROR(IF(INDEX(Bookings!$G$3:$G$202,MATCH($K15,Bookings!$A$3:$A$202,0))="","",INDEX(Bookings!$G$3:$G$202,MATCH($K15,Bookings!$A$3:$A$202,0))),"")) -> 46308
A16: TIIU2260280 | B16: 277243505 | C16: ML-GH0085065 | D16: 20' FLEXITANK | H16: =J16-I16 -> 21200 | I16: 38280 | J16: 59480 | K16: =IF($B16="","",IFERROR(INDEX(Connaissements!$B$3:$B$202,MATCH($B16,Connaissements!$A$3:$A$202,0)),"")) -> 277243505 | L16: =IF($B16="","",IFERROR(INDEX(Connaissements!$G$3:$G$202,MATCH($B16,Connaissements!$A$3:$A$202,0)),"")) -> 4600063618 | M16: =IF($A16="","",IF($G16<>"","Embarqué",IF($F16<>"","Gate-In fait",IF($E16<>"","Empoté","À empoter")))) -> À empoter | N16: =IF(OR($A16="",$G16<>""),"",IF(AND($Q16<>"",N($Q16)<TODAY()),"RETARD : ETD dépassé, pas embarqué",IF(AND($Q16<>"",N($Q16)-TODAY()<=P_AlerteETD,$F16=""),"Gate-In à faire (ETD proche)",IF(AND($E16<>"",$H16=""),"Poids net à saisir","")))) -> Gate-In à faire (ETD proche) | P16: =IF($N16<>"",1,"") -> 1 | Q16: =IF($K16="","",IFERROR(IF(INDEX(Bookings!$G$3:$G$202,MATCH($K16,Bookings!$A$3:$A$202,0))="","",INDEX(Bookings!$G$3:$G$202,MATCH($K16,Bookings!$A$3:$A$202,0))),"")) -> 46308
... A51: FTAU2054135 | B51: 278981635 | C51: ML-GH0085135 | D51: 20' FLEXITANK | H51: =J51-I51 -> 20820 | I51: 15160 | J51: 35980 | K51: =IF($B51="","",IFERROR(INDEX(Connaissements!$B$3:$B$202,MATCH($B51,Connaissements!$A$3:$A$202,0)),"")) -> 278981635 | L51: =IF($B51="","",IFERROR(INDEX(Connaissements!$G$3:$G$202,MATCH($B51,Connaissements!$A$3:$A$202,0)),"")) -> 4600063618 | M51: =IF($A51="","",IF($G51<>"","Embarqué",IF($F51<>"","Gate-In fait",IF($E51<>"","Empoté","À empoter")))) -> À empoter | N51: =IF(OR($A51="",$G51<>""),"",IF(AND($Q51<>"",N($Q51)<TODAY()),"RETARD : ETD dépassé, pas embarqué",IF(AND($Q51<>"",N($Q51)-TODAY()<=P_AlerteETD,$F51=""),"Gate-In à faire (ETD proche)",IF(AND($E51<>"",$H51=""),"Poids net à saisir","")))) -> Gate-In à faire (ETD proche) | P51: =IF($N51<>"",1,"") -> 1 | Q51: =IF($K51="","",IFERROR(IF(INDEX(Bookings!$G$3:$G$202,MATCH($K51,Bookings!$A$3:$A$202,0))="","",INDEX(Bookings!$G$3:$G$202,MATCH($K51,Bookings!$A$3:$A$202,0))),"")) -> 46309
H52: =J52-I52 -> 0 | K52: =IF($B52="","",IFERROR(INDEX(Connaissements!$B$3:$B$202,MATCH($B52,Connaissements!$A$3:$A$202,0)),"")) | L52: =IF($B52="","",IFERROR(INDEX(Connaissements!$G$3:$G$202,MATCH($B52,Connaissements!$A$3:$A$202,0)),"")) | M52: =IF($A52="","",IF($G52<>"","Embarqué",IF($F52<>"","Gate-In fait",IF($E52<>"","Empoté","À empoter")))) | N52: =IF(OR($A52="",$G52<>""),"",IF(AND($Q52<>"",N($Q52)<TODAY()),"RETARD : ETD dépassé, pas embarqué",IF(AND($Q52<>"",N($Q52)-TODAY()<=P_AlerteETD,$F52=""),"Gate-In à faire (ETD proche)",IF(AND($E52<>"",$H52=""),"Poids net à saisir","")))) | P52: =IF($N52<>"",1,"") | Q52: =IF($K52="","",IFERROR(IF(INDEX(Bookings!$G$3:$G$202,MATCH($K52,Bookings!$A$3:$A$202,0))="","",INDEX(Bookings!$G$3:$G$202,MATCH($K52,Bookings!$A$3:$A$202,0))),""))
H53: =J53-I53 -> 0 | K53: =IF($B53="","",IFERROR(INDEX(Connaissements!$B$3:$B$202,MATCH($B53,Connaissements!$A$3:$A$202,0)),"")) | L53: =IF($B53="","",IFERROR(INDEX(Connaissements!$G$3:$G$202,MATCH($B53,Connaissements!$A$3:$A$202,0)),"")) | M53: =IF($A53="","",IF($G53<>"","Embarqué",IF($F53<>"","Gate-In fait",IF($E53<>"","Empoté","À empoter")))) | N53: =IF(OR($A53="",$G53<>""),"",IF(AND($Q53<>"",N($Q53)<TODAY()),"RETARD : ETD dépassé, pas embarqué",IF(AND($Q53<>"",N($Q53)-TODAY()<=P_AlerteETD,$F53=""),"Gate-In à faire (ETD proche)",IF(AND($E53<>"",$H53=""),"Poids net à saisir","")))) | P53: =IF($N53<>"",1,"") | Q53: =IF($K53="","",IFERROR(IF(INDEX(Bookings!$G$3:$G$202,MATCH($K53,Bookings!$A$3:$A$202,0))="","",INDEX(Bookings!$G$3:$G$202,MATCH($K53,Bookings!$A$3:$A$202,0))),""))
H54: =J54-I54 -> 0 | K54: =IF($B54="","",IFERROR(INDEX(Connaissements!$B$3:$B$202,MATCH($B54,Connaissements!$A$3:$A$202,0)),"")) | L54: =IF($B54="","",IFERROR(INDEX(Connaissements!$G$3:$G$202,MATCH($B54,Connaissements!$A$3:$A$202,0)),"")) | M54: =IF($A54="","",IF($G54<>"","Embarqué",IF($F54<>"","Gate-In fait",IF($E54<>"","Empoté","À empoter")))) | N54: =IF(OR($A54="",$G54<>""),"",IF(AND($Q54<>"",N($Q54)<TODAY()),"RETARD : ETD dépassé, pas embarqué",IF(AND($Q54<>"",N($Q54)-TODAY()<=P_AlerteETD,$F54=""),"Gate-In à faire (ETD proche)",IF(AND($E54<>"",$H54=""),"Poids net à saisir","")))) | P54: =IF($N54<>"",1,"") | Q54: =IF($K54="","",IFERROR(IF(INDEX(Bookings!$G$3:$G$202,MATCH($K54,Bookings!$A$3:$A$202,0))="","",INDEX(Bookings!$G$3:$G$202,MATCH($K54,Bookings!$A$3:$A$202,0))),""))
H55: =J55-I55 -> 0 | K55: =IF($B55="","",IFERROR(INDEX(Connaissements!$B$3:$B$202,MATCH($B55,Connaissements!$A$3:$A$202,0)),"")) | L55: =IF($B55="","",IFERROR(INDEX(Connaissements!$G$3:$G$202,MATCH($B55,Connaissements!$A$3:$A$202,0)),"")) | M55: =IF($A55="","",IF($G55<>"","Embarqué",IF($F55<>"","Gate-In fait",IF($E55<>"","Empoté","À empoter")))) | N55: =IF(OR($A55="",$G55<>""),"",IF(AND($Q55<>"",N($Q55)<TODAY()),"RETARD : ETD dépassé, pas embarqué",IF(AND($Q55<>"",N($Q55)-TODAY()<=P_AlerteETD,$F55=""),"Gate-In à faire (ETD proche)",IF(AND($E55<>"",$H55=""),"Poids net à saisir","")))) | P55: =IF($N55<>"",1,"") | Q55: =IF($K55="","",IFERROR(IF(INDEX(Bookings!$G$3:$G$202,MATCH($K55,Bookings!$A$3:$A$202,0))="","",INDEX(Bookings!$G$3:$G$202,MATCH($K55,Bookings!$A$3:$A$202,0))),""))
H56: =J56-I56 -> 0 | K56: =IF($B56="","",IFERROR(INDEX(Connaissements!$B$3:$B$202,MATCH($B56,Connaissements!$A$3:$A$202,0)),"")) | L56: =IF($B56="","",IFERROR(INDEX(Connaissements!$G$3:$G$202,MATCH($B56,Connaissements!$A$3:$A$202,0)),"")) | M56: =IF($A56="","",IF($G56<>"","Embarqué",IF($F56<>"","Gate-In fait",IF($E56<>"","Empoté","À empoter")))) | N56: =IF(OR($A56="",$G56<>""),"",IF(AND($Q56<>"",N($Q56)<TODAY()),"RETARD : ETD dépassé, pas embarqué",IF(AND($Q56<>"",N($Q56)-TODAY()<=P_AlerteETD,$F56=""),"Gate-In à faire (ETD proche)",IF(AND($E56<>"",$H56=""),"Poids net à saisir","")))) | P56: =IF($N56<>"",1,"") | Q56: =IF($K56="","",IFERROR(IF(INDEX(Bookings!$G$3:$G$202,MATCH($K56,Bookings!$A$3:$A$202,0))="","",INDEX(Bookings!$G$3:$G$202,MATCH($K56,Bookings!$A$3:$A$202,0))),""))
H57: =J57-I57 -> 0 | K57: =IF($B57="","",IFERROR(INDEX(Connaissements!$B$3:$B$202,MATCH($B57,Connaissements!$A$3:$A$202,0)),"")) | L57: =IF($B57="","",IFERROR(INDEX(Connaissements!$G$3:$G$202,MATCH($B57,Connaissements!$A$3:$A$202,0)),"")) | M57: =IF($A57="","",IF($G57<>"","Embarqué",IF($F57<>"","Gate-In fait",IF($E57<>"","Empoté","À empoter")))) | N57: =IF(OR($A57="",$G57<>""),"",IF(AND($Q57<>"",N($Q57)<TODAY()),"RETARD : ETD dépassé, pas embarqué",IF(AND($Q57<>"",N($Q57)-TODAY()<=P_AlerteETD,$F57=""),"Gate-In à faire (ETD proche)",IF(AND($E57<>"",$H57=""),"Poids net à saisir","")))) | P57: =IF($N57<>"",1,"") | Q57: =IF($K57="","",IFERROR(IF(INDEX(Bookings!$G$3:$G$202,MATCH($K57,Bookings!$A$3:$A$202,0))="","",INDEX(Bookings!$G$3:$G$202,MATCH($K57,Bookings!$A$3:$A$202,0))),""))
H58: =J58-I58 -> 0 | K58: =IF($B58="","",IFERROR(INDEX(Connaissements!$B$3:$B$202,MATCH($B58,Connaissements!$A$3:$A$202,0)),"")) | L58: =IF($B58="","",IFERROR(INDEX(Connaissements!$G$3:$G$202,MATCH($B58,Connaissements!$A$3:$A$202,0)),"")) | M58: =IF($A58="","",IF($G58<>"","Embarqué",IF($F58<>"","Gate-In fait",IF($E58<>"","Empoté","À empoter")))) | N58: =IF(OR($A58="",$G58<>""),"",IF(AND($Q58<>"",N($Q58)<TODAY()),"RETARD : ETD dépassé, pas embarqué",IF(AND($Q58<>"",N($Q58)-TODAY()<=P_AlerteETD,$F58=""),"Gate-In à faire (ETD proche)",IF(AND($E58<>"",$H58=""),"Poids net à saisir","")))) | P58: =IF($N58<>"",1,"") | Q58: =IF($K58="","",IFERROR(IF(INDEX(Bookings!$G$3:$G$202,MATCH($K58,Bookings!$A$3:$A$202,0))="","",INDEX(Bookings!$G$3:$G$202,MATCH($K58,Bookings!$A$3:$A$202,0))),""))
H59: =J59-I59 -> 0 | K59: =IF($B59="","",IFERROR(INDEX(Connaissements!$B$3:$B$202,MATCH($B59,Connaissements!$A$3:$A$202,0)),"")) | L59: =IF($B59="","",IFERROR(INDEX(Connaissements!$G$3:$G$202,MATCH($B59,Connaissements!$A$3:$A$202,0)),"")) | M59: =IF($A59="","",IF($G59<>"","Embarqué",IF($F59<>"","Gate-In fait",IF($E59<>"","Empoté","À empoter")))) | N59: =IF(OR($A59="",$G59<>""),"",IF(AND($Q59<>"",N($Q59)<TODAY()),"RETARD : ETD dépassé, pas embarqué",IF(AND($Q59<>"",N($Q59)-TODAY()<=P_AlerteETD,$F59=""),"Gate-In à faire (ETD proche)",IF(AND($E59<>"",$H59=""),"Poids net à saisir","")))) | P59: =IF($N59<>"",1,"") | Q59: =IF($K59="","",IFERROR(IF(INDEX(Bookings!$G$3:$G$202,MATCH($K59,Bookings!$A$3:$A$202,0))="","",INDEX(Bookings!$G$3:$G$202,MATCH($K59,Bookings!$A$3:$A$202,0))),""))
H60: =J60-I60 -> 0 | K60: =IF($B60="","",IFERROR(INDEX(Connaissements!$B$3:$B$202,MATCH($B60,Connaissements!$A$3:$A$202,0)),"")) | L60: =IF($B60="","",IFERROR(INDEX(Connaissements!$G$3:$G$202,MATCH($B60,Connaissements!$A$3:$A$202,0)),"")) | M60: =IF($A60="","",IF($G60<>"","Embarqué",IF($F60<>"","Gate-In fait",IF($E60<>"","Empoté","À empoter")))) | N60: =IF(OR($A60="",$G60<>""),"",IF(AND($Q60<>"",N($Q60)<TODAY()),"RETARD : ETD dépassé, pas embarqué",IF(AND($Q60<>"",N($Q60)-TODAY()<=P_AlerteETD,$F60=""),"Gate-In à faire (ETD proche)",IF(AND($E60<>"",$H60=""),"Poids net à saisir","")))) | P60: =IF($N60<>"",1,"") | Q60: =IF($K60="","",IFERROR(IF(INDEX(Bookings!$G$3:$G$202,MATCH($K60,Bookings!$A$3:$A$202,0))="","",INDEX(Bookings!$G$3:$G$202,MATCH($K60,Bookings!$A$3:$A$202,0))),""))
H61: =J61-I61 -> 0 | K61: =IF($B61="","",IFERROR(INDEX(Connaissements!$B$3:$B$202,MATCH($B61,Connaissements!$A$3:$A$202,0)),"")) | L61: =IF($B61="","",IFERROR(INDEX(Connaissements!$G$3:$G$202,MATCH($B61,Connaissements!$A$3:$A$202,0)),"")) | M61: =IF($A61="","",IF($G61<>"","Embarqué",IF($F61<>"","Gate-In fait",IF($E61<>"","Empoté","À empoter")))) | N61: =IF(OR($A61="",$G61<>""),"",IF(AND($Q61<>"",N($Q61)<TODAY()),"RETARD : ETD dépassé, pas embarqué",IF(AND($Q61<>"",N($Q61)-TODAY()<=P_AlerteETD,$F61=""),"Gate-In à faire (ETD proche)",IF(AND($E61<>"",$H61=""),"Poids net à saisir","")))) | P61: =IF($N61<>"",1,"") | Q61: =IF($K61="","",IFERROR(IF(INDEX(Bookings!$G$3:$G$202,MATCH($K61,Bookings!$A$3:$A$202,0))="","",INDEX(Bookings!$G$3:$G$202,MATCH($K61,Bookings!$A$3:$A$202,0))),""))
H62: =J62-I62 -> 0 | K62: =IF($B62="","",IFERROR(INDEX(Connaissements!$B$3:$B$202,MATCH($B62,Connaissements!$A$3:$A$202,0)),"")) | L62: =IF($B62="","",IFERROR(INDEX(Connaissements!$G$3:$G$202,MATCH($B62,Connaissements!$A$3:$A$202,0)),"")) | M62: =IF($A62="","",IF($G62<>"","Embarqué",IF($F62<>"","Gate-In fait",IF($E62<>"","Empoté","À empoter")))) | N62: =IF(OR($A62="",$G62<>""),"",IF(AND($Q62<>"",N($Q62)<TODAY()),"RETARD : ETD dépassé, pas embarqué",IF(AND($Q62<>"",N($Q62)-TODAY()<=P_AlerteETD,$F62=""),"Gate-In à faire (ETD proche)",IF(AND($E62<>"",$H62=""),"Poids net à saisir","")))) | P62: =IF($N62<>"",1,"") | Q62: =IF($K62="","",IFERROR(IF(INDEX(Bookings!$G$3:$G$202,MATCH($K62,Bookings!$A$3:$A$202,0))="","",INDEX(Bookings!$G$3:$G$202,MATCH($K62,Bookings!$A$3:$A$202,0))),""))
H63: =J63-I63 -> 0 | K63: =IF($B63="","",IFERROR(INDEX(Connaissements!$B$3:$B$202,MATCH($B63,Connaissements!$A$3:$A$202,0)),"")) | L63: =IF($B63="","",IFERROR(INDEX(Connaissements!$G$3:$G$202,MATCH($B63,Connaissements!$A$3:$A$202,0)),"")) | M63: =IF($A63="","",IF($G63<>"","Embarqué",IF($F63<>"","Gate-In fait",IF($E63<>"","Empoté","À empoter")))) | N63: =IF(OR($A63="",$G63<>""),"",IF(AND($Q63<>"",N($Q63)<TODAY()),"RETARD : ETD dépassé, pas embarqué",IF(AND($Q63<>"",N($Q63)-TODAY()<=P_AlerteETD,$F63=""),"Gate-In à faire (ETD proche)",IF(AND($E63<>"",$H63=""),"Poids net à saisir","")))) | P63: =IF($N63<>"",1,"") | Q63: =IF($K63="","",IFERROR(IF(INDEX(Bookings!$G$3:$G$202,MATCH($K63,Bookings!$A$3:$A$202,0))="","",INDEX(Bookings!$G$3:$G$202,MATCH($K63,Bookings!$A$3:$A$202,0))),""))
... H1002: =J1002-I1002 -> 0 | K1002: =IF($B1002="","",IFERROR(INDEX(Connaissements!$B$3:$B$202,MATCH($B1002,Connaissements!$A$3:$A$202,0)),"")) | L1002: =IF($B1002="","",IFERROR(INDEX(Connaissements!$G$3:$G$202,MATCH($B1002,Connaissements!$A$3:$A$202,0)),"")) | M1002: =IF($A1002="","",IF($G1002<>"","Embarqué",IF($F1002<>"","Gate-In fait",IF($E1002<>"","Empoté","À empoter")))) | N1002: =IF(OR($A1002="",$G1002<>""),"",IF(AND($Q1002<>"",N($Q1002)<TODAY()),"RETARD : ETD dépassé, pas embarqué",IF(AND($Q1002<>"",N($Q1002)-TODAY()<=P_AlerteETD,$F1002=""),"Gate-In à faire (ETD proche)",IF(AND($E1002<>"",$H1002=""),"Poids net à saisir","")))) | P1002: =IF($N1002<>"",1,"") | Q1002: =IF($K1002="","",IFERROR(IF(INDEX(Bookings!$G$3:$G$202,MATCH($K1002,Bookings!$A$3:$A$202,0))="","",INDEX(Bookings!$G$3:$G$202,MATCH($K1002,Bookings!$A$3:$A$202,0))),""))
H1003: =J1003-I1003 -> 0
H1004: =J1004-I1004 -> 0
H1005: =J1005-I1005 -> 0
H1006: =J1006-I1006 -> 0
H1007: =J1007-I1007 -> 0
H1008: =J1008-I1008 -> 0
H1009: =J1009-I1009 -> 0
H1010: =J1010-I1010 -> 0
H1011: =J1011-I1011 -> 0
H1012: =J1012-I1012 -> 0
H1013: =J1013-I1013 -> 0
H1014: =J1014-I1014 -> 0
... H13628: =J13628-I13628 -> 0

Sheet Documents
A1: Une ligne = un document pour un BL. Renseignez les dates au fur et à mesure : demande, réception, envoi DHL (+ numéro de suivi DHL). Le statut est automatique. Alerte : document demandé et non reçu depuis trop longtemps (seuil dans Listes), ou reçu mais pas encore envoyé par DHL. La ligne 5 est un exemple à supprimer.
A2: N_BL | B2: Type_Document | C2: N_Document | D2: Date_Demande | E2: Date_Reception | F2: Date_Envoi_DHL | G2: N_Suivi_DHL | H2: Transitaire | I2: Statut_Document | J2: Jours_Attente | K2: Alerte | L2: Observation | M2: flag
H3: RAJIBER | I3: =IF($A3="","",IF($F3<>"","Envoyé DHL",IF($E3<>"","Reçu (à envoyer)",IF($D3<>"","Demandé (en attente)","À demander")))) | J3: =IF(AND($A3<>"",$D3<>"",$E3=""),TODAY()-$D3,"") | K3: =IF($A3="","",IF(AND($J3<>"",N($J3)>P_AlerteDoc),"Attente > "&P_AlerteDoc&" jours",IF(AND($E3<>"",$F3=""),"Reçu : à envoyer par DHL","")))
H4: RAJIBER | I4: =IF($A4="","",IF($F4<>"","Envoyé DHL",IF($E4<>"","Reçu (à envoyer)",IF($D4<>"","Demandé (en attente)","À demander")))) | J4: =IF(AND($A4<>"",$D4<>"",$E4=""),TODAY()-$D4,"") | K4: =IF($A4="","",IF(AND($J4<>"",N($J4)>P_AlerteDoc),"Attente > "&P_AlerteDoc&" jours",IF(AND($E4<>"",$F4=""),"Reçu : à envoyer par DHL","")))
H5: RAJIBER | I5: =IF($A5="","",IF($F5<>"","Envoyé DHL",IF($E5<>"","Reçu (à envoyer)",IF($D5<>"","Demandé (en attente)","À demander")))) | J5: =IF(AND($A5<>"",$D5<>"",$E5=""),TODAY()-$D5,"") | K5: =IF($A5="","",IF(AND($J5<>"",N($J5)>P_AlerteDoc),"Attente > "&P_AlerteDoc&" jours",IF(AND($E5<>"",$F5=""),"Reçu : à envoyer par DHL",""))) | M5: =IF($K5<>"",1,"")
H6: RAJIBER | I6: =IF($A6="","",IF($F6<>"","Envoyé DHL",IF($E6<>"","Reçu (à envoyer)",IF($D6<>"","Demandé (en attente)","À demander")))) | J6: =IF(AND($A6<>"",$D6<>"",$E6=""),TODAY()-$D6,"") | K6: =IF($A6="","",IF(AND($J6<>"",N($J6)>P_AlerteDoc),"Attente > "&P_AlerteDoc&" jours",IF(AND($E6<>"",$F6=""),"Reçu : à envoyer par DHL",""))) | M6: =IF($K6<>"",1,"")
H7: RAJIBER | I7: =IF($A7="","",IF($F7<>"","Envoyé DHL",IF($E7<>"","Reçu (à envoyer)",IF($D7<>"","Demandé (en attente)","À demander")))) | J7: =IF(AND($A7<>"",$D7<>"",$E7=""),TODAY()-$D7,"") | K7: =IF($A7="","",IF(AND($J7<>"",N($J7)>P_AlerteDoc),"Attente > "&P_AlerteDoc&" jours",IF(AND($E7<>"",$F7=""),"Reçu : à envoyer par DHL",""))) | M7: =IF($K7<>"",1,"")
H8: RAJIBER | I8: =IF($A8="","",IF($F8<>"","Envoyé DHL",IF($E8<>"","Reçu (à envoyer)",IF($D8<>"","Demandé (en attente)","À demander")))) | J8: =IF(AND($A8<>"",$D8<>"",$E8=""),TODAY()-$D8,"") | K8: =IF($A8="","",IF(AND($J8<>"",N($J8)>P_AlerteDoc),"Attente > "&P_AlerteDoc&" jours",IF(AND($E8<>"",$F8=""),"Reçu : à envoyer par DHL",""))) | M8: =IF($K8<>"",1,"")
H9: RAJIBER | I9: =IF($A9="","",IF($F9<>"","Envoyé DHL",IF($E9<>"","Reçu (à envoyer)",IF($D9<>"","Demandé (en attente)","À demander")))) | J9: =IF(AND($A9<>"",$D9<>"",$E9=""),TODAY()-$D9,"") | K9: =IF($A9="","",IF(AND($J9<>"",N($J9)>P_AlerteDoc),"Attente > "&P_AlerteDoc&" jours",IF(AND($E9<>"",$F9=""),"Reçu : à envoyer par DHL",""))) | M9: =IF($K9<>"",1,"")
I10: =IF($A10="","",IF($F10<>"","Envoyé DHL",IF($E10<>"","Reçu (à envoyer)",IF($D10<>"","Demandé (en attente)","À demander")))) | J10: =IF(AND($A10<>"",$D10<>"",$E10=""),TODAY()-$D10,"") | K10: =IF($A10="","",IF(AND($J10<>"",N($J10)>P_AlerteDoc),"Attente > "&P_AlerteDoc&" jours",IF(AND($E10<>"",$F10=""),"Reçu : à envoyer par DHL",""))) | M10: =IF($K10<>"",1,"")
I11: =IF($A11="","",IF($F11<>"","Envoyé DHL",IF($E11<>"","Reçu (à envoyer)",IF($D11<>"","Demandé (en attente)","À demander")))) | J11: =IF(AND($A11<>"",$D11<>"",$E11=""),TODAY()-$D11,"") | K11: =IF($A11="","",IF(AND($J11<>"",N($J11)>P_AlerteDoc),"Attente > "&P_AlerteDoc&" jours",IF(AND($E11<>"",$F11=""),"Reçu : à envoyer par DHL",""))) | M11: =IF($K11<>"",1,"")
I12: =IF($A12="","",IF($F12<>"","Envoyé DHL",IF($E12<>"","Reçu (à envoyer)",IF($D12<>"","Demandé (en attente)","À demander")))) | J12: =IF(AND($A12<>"",$D12<>"",$E12=""),TODAY()-$D12,"") | K12: =IF($A12="","",IF(AND($J12<>"",N($J12)>P_AlerteDoc),"Attente > "&P_AlerteDoc&" jours",IF(AND($E12<>"",$F12=""),"Reçu : à envoyer par DHL",""))) | M12: =IF($K12<>"",1,"")
I13: =IF($A13="","",IF($F13<>"","Envoyé DHL",IF($E13<>"","Reçu (à envoyer)",IF($D13<>"","Demandé (en attente)","À demander")))) | J13: =IF(AND($A13<>"",$D13<>"",$E13=""),TODAY()-$D13,"") | K13: =IF($A13="","",IF(AND($J13<>"",N($J13)>P_AlerteDoc),"Attente > "&P_AlerteDoc&" jours",IF(AND($E13<>"",$F13=""),"Reçu : à envoyer par DHL",""))) | M13: =IF($K13<>"",1,"")
I14: =IF($A14="","",IF($F14<>"","Envoyé DHL",IF($E14<>"","Reçu (à envoyer)",IF($D14<>"","Demandé (en attente)","À demander")))) | J14: =IF(AND($A14<>"",$D14<>"",$E14=""),TODAY()-$D14,"") | K14: =IF($A14="","",IF(AND($J14<>"",N($J14)>P_AlerteDoc),"Attente > "&P_AlerteDoc&" jours",IF(AND($E14<>"",$F14=""),"Reçu : à envoyer par DHL",""))) | M14: =IF($K14<>"",1,"")
I15: =IF($A15="","",IF($F15<>"","Envoyé DHL",IF($E15<>"","Reçu (à envoyer)",IF($D15<>"","Demandé (en attente)","À demander")))) | J15: =IF(AND($A15<>"",$D15<>"",$E15=""),TODAY()-$D15,"") | K15: =IF($A15="","",IF(AND($J15<>"",N($J15)>P_AlerteDoc),"Attente > "&P_AlerteDoc&" jours",IF(AND($E15<>"",$F15=""),"Reçu : à envoyer par DHL",""))) | M15: =IF($K15<>"",1,"")
I16: =IF($A16="","",IF($F16<>"","Envoyé DHL",IF($E16<>"","Reçu (à envoyer)",IF($D16<>"","Demandé (en attente)","À demander")))) | J16: =IF(AND($A16<>"",$D16<>"",$E16=""),TODAY()-$D16,"") | K16: =IF($A16="","",IF(AND($J16<>"",N($J16)>P_AlerteDoc),"Attente > "&P_AlerteDoc&" jours",IF(AND($E16<>"",$F16=""),"Reçu : à envoyer par DHL",""))) | M16: =IF($K16<>"",1,"")
I17: =IF($A17="","",IF($F17<>"","Envoyé DHL",IF($E17<>"","Reçu (à envoyer)",IF($D17<>"","Demandé (en attente)","À demander")))) | J17: =IF(AND($A17<>"",$D17<>"",$E17=""),TODAY()-$D17,"") | K17: =IF($A17="","",IF(AND($J17<>"",N($J17)>P_AlerteDoc),"Attente > "&P_AlerteDoc&" jours",IF(AND($E17<>"",$F17=""),"Reçu : à envoyer par DHL",""))) | M17: =IF($K17<>"",1,"")
I18: =IF($A18="","",IF($F18<>"","Envoyé DHL",IF($E18<>"","Reçu (à envoyer)",IF($D18<>"","Demandé (en attente)","À demander")))) | J18: =IF(AND($A18<>"",$D18<>"",$E18=""),TODAY()-$D18,"") | K18: =IF($A18="","",IF(AND($J18<>"",N($J18)>P_AlerteDoc),"Attente > "&P_AlerteDoc&" jours",IF(AND($E18<>"",$F18=""),"Reçu : à envoyer par DHL",""))) | M18: =IF($K18<>"",1,"")
I19: =IF($A19="","",IF($F19<>"","Envoyé DHL",IF($E19<>"","Reçu (à envoyer)",IF($D19<>"","Demandé (en attente)","À demander")))) | J19: =IF(AND($A19<>"",$D19<>"",$E19=""),TODAY()-$D19,"") | K19: =IF($A19="","",IF(AND($J19<>"",N($J19)>P_AlerteDoc),"Attente > "&P_AlerteDoc&" jours",IF(AND($E19<>"",$F19=""),"Reçu : à envoyer par DHL",""))) | M19: =IF($K19<>"",1,"")
I20: =IF($A20="","",IF($F20<>"","Envoyé DHL",IF($E20<>"","Reçu (à envoyer)",IF($D20<>"","Demandé (en attente)","À demander")))) | J20: =IF(AND($A20<>"",$D20<>"",$E20=""),TODAY()-$D20,"") | K20: =IF($A20="","",IF(AND($J20<>"",N($J20)>P_AlerteDoc),"Attente > "&P_AlerteDoc&" jours",IF(AND($E20<>"",$F20=""),"Reçu : à envoyer par DHL",""))) | M20: =IF($K20<>"",1,"")
I21: =IF($A21="","",IF($F21<>"","Envoyé DHL",IF($E21<>"","Reçu (à envoyer)",IF($D21<>"","Demandé (en attente)","À demander")))) | J21: =IF(AND($A21<>"",$D21<>"",$E21=""),TODAY()-$D21,"") | K21: =IF($A21="","",IF(AND($J21<>"",N($J21)>P_AlerteDoc),"Attente > "&P_AlerteDoc&" jours",IF(AND($E21<>"",$F21=""),"Reçu : à envoyer par DHL",""))) | M21: =IF($K21<>"",1,"")
... I1002: =IF($A1002="","",IF($F1002<>"","Envoyé DHL",IF($E1002<>"","Reçu (à envoyer)",IF($D1002<>"","Demandé (en attente)","À demander")))) | J1002: =IF(AND($A1002<>"",$D1002<>"",$E1002=""),TODAY()-$D1002,"") | K1002: =IF($A1002="","",IF(AND($J1002<>"",N($J1002)>P_AlerteDoc),"Attente > "&P_AlerteDoc&" jours",IF(AND($E1002<>"",$F1002=""),"Reçu : à envoyer par DHL",""))) | M1002: =IF($K1002<>"",1,"")

Sheet Etapes
A1: Étapes du processus (prévu / réel)
A2: Une ligne = une étape pour un BL. Saisissez la date prévue dès la planification, puis la date réelle quand l'étape est faite. Statut automatique : Fait / À venir / En retard / Non planifié. Retard_Jours = jours de retard (positif) ou d'avance (négatif). Ajoutez autant d'étapes que nécessaire par BL. La ligne 5 est un exemple à supprimer.
A4: N_BL | B4: Nom_Etape | C4: Date_Prevue | D4: Date_Reelle | E4: Responsable | F4: Statut_Etape | G4: Retard_Jours | H4: Commentaire | I4: flag
F9: =IF($B9="","",IF($D9<>"","Fait",IF($C9="","Non planifié",IF(N($C9)<TODAY(),"En retard","À venir")))) | G9: =IF($B9="","",IF(AND($C9<>"",$D9<>""),$D9-$C9,IF($F9="En retard",TODAY()-$C9,""))) | I9: =IF($F9="En retard",1,"")
F10: =IF($B10="","",IF($D10<>"","Fait",IF($C10="","Non planifié",IF(N($C10)<TODAY(),"En retard","À venir")))) | G10: =IF($B10="","",IF(AND($C10<>"",$D10<>""),$D10-$C10,IF($F10="En retard",TODAY()-$C10,""))) | I10: =IF($F10="En retard",1,"")
F11: =IF($B11="","",IF($D11<>"","Fait",IF($C11="","Non planifié",IF(N($C11)<TODAY(),"En retard","À venir")))) | G11: =IF($B11="","",IF(AND($C11<>"",$D11<>""),$D11-$C11,IF($F11="En retard",TODAY()-$C11,""))) | I11: =IF($F11="En retard",1,"")
F12: =IF($B12="","",IF($D12<>"","Fait",IF($C12="","Non planifié",IF(N($C12)<TODAY(),"En retard","À venir")))) | G12: =IF($B12="","",IF(AND($C12<>"",$D12<>""),$D12-$C12,IF($F12="En retard",TODAY()-$C12,""))) | I12: =IF($F12="En retard",1,"")
F13: =IF($B13="","",IF($D13<>"","Fait",IF($C13="","Non planifié",IF(N($C13)<TODAY(),"En retard","À venir")))) | G13: =IF($B13="","",IF(AND($C13<>"",$D13<>""),$D13-$C13,IF($F13="En retard",TODAY()-$C13,""))) | I13: =IF($F13="En retard",1,"")
F14: =IF($B14="","",IF($D14<>"","Fait",IF($C14="","Non planifié",IF(N($C14)<TODAY(),"En retard","À venir")))) | G14: =IF($B14="","",IF(AND($C14<>"",$D14<>""),$D14-$C14,IF($F14="En retard",TODAY()-$C14,""))) | I14: =IF($F14="En retard",1,"")
F15: =IF($B15="","",IF($D15<>"","Fait",IF($C15="","Non planifié",IF(N($C15)<TODAY(),"En retard","À venir")))) | G15: =IF($B15="","",IF(AND($C15<>"",$D15<>""),$D15-$C15,IF($F15="En retard",TODAY()-$C15,""))) | I15: =IF($F15="En retard",1,"")
F16: =IF($B16="","",IF($D16<>"","Fait",IF($C16="","Non planifié",IF(N($C16)<TODAY(),"En retard","À venir")))) | G16: =IF($B16="","",IF(AND($C16<>"",$D16<>""),$D16-$C16,IF($F16="En retard",TODAY()-$C16,""))) | I16: =IF($F16="En retard",1,"")
F17: =IF($B17="","",IF($D17<>"","Fait",IF($C17="","Non planifié",IF(N($C17)<TODAY(),"En retard","À venir")))) | G17: =IF($B17="","",IF(AND($C17<>"",$D17<>""),$D17-$C17,IF($F17="En retard",TODAY()-$C17,""))) | I17: =IF($F17="En retard",1,"")
F18: =IF($B18="","",IF($D18<>"","Fait",IF($C18="","Non planifié",IF(N($C18)<TODAY(),"En retard","À venir")))) | G18: =IF($B18="","",IF(AND($C18<>"",$D18<>""),$D18-$C18,IF($F18="En retard",TODAY()-$C18,""))) | I18: =IF($F18="En retard",1,"")
F19: =IF($B19="","",IF($D19<>"","Fait",IF($C19="","Non planifié",IF(N($C19)<TODAY(),"En retard","À venir")))) | G19: =IF($B19="","",IF(AND($C19<>"",$D19<>""),$D19-$C19,IF($F19="En retard",TODAY()-$C19,""))) | I19: =IF($F19="En retard",1,"")
F20: =IF($B20="","",IF($D20<>"","Fait",IF($C20="","Non planifié",IF(N($C20)<TODAY(),"En retard","À venir")))) | G20: =IF($B20="","",IF(AND($C20<>"",$D20<>""),$D20-$C20,IF($F20="En retard",TODAY()-$C20,""))) | I20: =IF($F20="En retard",1,"")
... F1504: =IF($B1504="","",IF($D1504<>"","Fait",IF($C1504="","Non planifié",IF(N($C1504)<TODAY(),"En retard","À venir")))) | G1504: =IF($B1504="","",IF(AND($C1504<>"",$D1504<>""),$D1504-$C1504,IF($F1504="En retard",TODAY()-$C1504,""))) | I1504: =IF($F1504="En retard",1,"")

Sheet Couts_Transitaire
A1: Une ligne = un coût facturé par le transitaire. Rattachez-le au booking (obligatoire), au BL et au conteneur si possible. Montants en FCFA. Le reste à payer et le statut de paiement se calculent tout seuls. La ligne 5 est un exemple à supprimer.
A2: N_Booking | B2: N_BL | C2: N_Conteneur | D2: Transitaire | E2: Motif | F2: Type_Cout | G2: Montant_Total | H2: Montant_Paye | I2: Montant_Reste | J2: Date_Cout | K2: Date_Paiement | L2: N_Facture | M2: Observations | N2: Statut_Paiement
I3: =IF($G3="","",$G3-N($H3))
I4: =IF($G4="","",$G4-N($H4)) | N4: =IF($G4="","",IF(N($H4)>=$G4,"Payé",IF(N($H4)>0,"Partiellement payé","Non payé")))
I5: =IF($G5="","",$G5-N($H5)) | N5: =IF($G5="","",IF(N($H5)>=$G5,"Payé",IF(N($H5)>0,"Partiellement payé","Non payé")))
I6: =IF($G6="","",$G6-N($H6)) | N6: =IF($G6="","",IF(N($H6)>=$G6,"Payé",IF(N($H6)>0,"Partiellement payé","Non payé")))
I7: =IF($G7="","",$G7-N($H7)) | N7: =IF($G7="","",IF(N($H7)>=$G7,"Payé",IF(N($H7)>0,"Partiellement payé","Non payé")))
I8: =IF($G8="","",$G8-N($H8)) | N8: =IF($G8="","",IF(N($H8)>=$G8,"Payé",IF(N($H8)>0,"Partiellement payé","Non payé")))
I9: =IF($G9="","",$G9-N($H9)) | N9: =IF($G9="","",IF(N($H9)>=$G9,"Payé",IF(N($H9)>0,"Partiellement payé","Non payé")))
I10: =IF($G10="","",$G10-N($H10)) | N10: =IF($G10="","",IF(N($H10)>=$G10,"Payé",IF(N($H10)>0,"Partiellement payé","Non payé")))
I11: =IF($G11="","",$G11-N($H11)) | N11: =IF($G11="","",IF(N($H11)>=$G11,"Payé",IF(N($H11)>0,"Partiellement payé","Non payé")))
I12: =IF($G12="","",$G12-N($H12)) | N12: =IF($G12="","",IF(N($H12)>=$G12,"Payé",IF(N($H12)>0,"Partiellement payé","Non payé")))
I13: =IF($G13="","",$G13-N($H13)) | N13: =IF($G13="","",IF(N($H13)>=$G13,"Payé",IF(N($H13)>0,"Partiellement payé","Non payé")))
I14: =IF($G14="","",$G14-N($H14)) | N14: =IF($G14="","",IF(N($H14)>=$G14,"Payé",IF(N($H14)>0,"Partiellement payé","Non payé")))
I15: =IF($G15="","",$G15-N($H15)) | N15: =IF($G15="","",IF(N($H15)>=$G15,"Payé",IF(N($H15)>0,"Partiellement payé","Non payé")))
... I602: =IF($G602="","",$G602-N($H602)) | N602: =IF($G602="","",IF(N($H602)>=$G602,"Payé",IF(N($H602)>0,"Partiellement payé","Non payé")))

Sheet Listes
A1: Clients | B1: LINERS | C1: Produits | D1: Transitaires | E1: Incoterms | F1: Types_Conteneur | G1: Types_Document | H1: Etapes | I1: Responsables | J1: Types_Cout | L1: Paramètres | M1: Valeur
A2: BUNGE LODERS | B2: MSC | C2: Shea Nut | D2: TRANS SOHA | E2: FOB | F2: 20' DRY | G2: Certificat phytosanitaire | H2: Réception marchandise | I2: Responsable Exemple | J2: Fret maritime | L2: Alerte « ETD proche » : nombre de jours avant l'ETD | M2: 3
B3: MAERSK | C3: Cotton Seed | D3: RAJIBER | E3: CFR | F3: 40' DRY | G3: Certificat d'origine | H3: Empotage | J3: THC / manutention | L3: Alerte document : jours d'attente avant alerte | M3: 5
C4: Soya Bean | D4: HAMA INTER | E4: CIF | F4: 40' HC | G4: Facture commerciale | H4: Dédouanement export | J4: Transit / honoraires
C5: Shea Butter | E5: EXW | F5: 20' HC | G5: Packing list | H5: Gate-In port | J5: Douane | L5: Comment utiliser cette feuille
E6: FCA | F6: 20' FLEXITANK | G6: Connaissement (BL) original | H6: Embarquement | J6: Magasinage / surestaries | L6: Ajoutez un élément en bas de la colonne concernée : il apparaît aussitôt dans les listes déroulantes. Pas de ligne vide au milieu d'une colonne.
E7: CIP | F7: 40' FLEXITANK | G7: Certificat de fumigation | H7: Documents prêts | J7: Autres | L7: Les listes de départ (documents, étapes, types de coûts, incoterms, conteneurs) sont des propositions génériques : adaptez-les à votre activité.
E8: DAP | F8: 30' FLEXITANK | G8: Déclaration d'exportation | H8: Envoi documents DHL | J8: SEGUB GUCE | L8: Les valeurs « Client Exemple », « Transit Exemple », « Responsable Exemple » sont des exemples à remplacer.
G9: Certificat de qualité | H9: Arrivée navire (ETA) | L9: Les seuils (3 jours, 5 jours) sont donnés à titre indicatif : modifiez-les dans les cellules jaunes.
G10: Verifycopy
G11: BooKing
G12: Provisional Facture
G13: Facture Normalisée
